Workbook

Sheet Báo cáo tổng kết
A1: BÁO CÁO TỔNG KẾT KIỂM THỬ (Test Summary Report)
A3: Mã báo cáo | B3: ACBI-TSR-2026-10-14-01
A4: Hệ thống / phiên bản | B4: ACBI, commit 2194ad7
A5: Môi trường | B5: Bản demo Vercel, Gemini + LiteRouter, kho AdventureWorks (xem sheet 'Môi trường kiểm thử')
A6: Ngày lập | B6: 2026-10-14
A7: Người lập | B7: Bui Duc Hoang
A8: Cấu trúc báo cáo | B8: Theo mẫu test summary report (IEEE 829 / ISO 29119-3) và mẫu bảng test case phổ biến
A10: 1. Tóm tắt điều hành
A11: Sau khi chạy lại các ca báo AI bận cho đến khi không còn, mọi ca đều Passed. Các con số trả lời được đối chiếu độc lập với kho dữ liệu. Phân quyền được kiểm tra trên 4 vai trò và cả hai đường truy vấn. Còn giới hạn: hiệu năng khi nhiều người dùng đồng thời phụ thuộc gói AI miễn phí, dự báo chỉ tương đương phương pháp đơn giản trên dữ liệu mẫu, chưa có pentest và dữ liệu thật. Khuyến nghị: thí điểm giới hạn có điều kiện (mục 5).
A13: 2. Kết quả thực thi (Results summary)
A14: Bộ kiểm thử | B14: Tổng số ca | C14: Passed | D14: Failed | E14: Blocked | F14: Not Run | G14: Đã thực thi (Passed + Failed) | H14: Tỷ lệ Passed / đã thực thi | I14: Ghi chú
A15: RAG Text-to-SQL | B15: =COUNTA('RAG'!A2:A25) | C15: =COUNTIF('RAG'!I2:I25,"Passed") | D15: =COUNTIF('RAG'!I2:I25,"Failed") | E15: =COUNTIF('RAG'!I2:I25,"Blocked") | F15: =B15-C15-D15-E15 | G15: =C15+D15 | H15: =IF(G15=0,"",C15/G15) | I15: Gồm 24 ca; ảnh trình duyệt từng ca
A16: Câu hỏi khó (Hard) | B16: =COUNTA('Hard'!A2:A91) | C16: =COUNTIF('Hard'!I2:I91,"Passed") | D16: =COUNTIF('Hard'!I2:I91,"Failed") | E16: =COUNTIF('Hard'!I2:I91,"Blocked") | F16: =B16-C16-D16-E16 | G16: =C16+D16 | H16: =IF(G16=0,"",C16/G16) | I16: Bẫy ảo giác, nhiều ràng buộc, 4 vai trò
A17: So sánh và nhiều yêu cầu (Compare) | B17: =COUNTA('Compare'!A2:A48) | C17: =COUNTIF('Compare'!I2:I48,"Passed") | D17: =COUNTIF('Compare'!I2:I48,"Failed") | E17: =COUNTIF('Compare'!I2:I48,"Blocked") | F17: =B17-C17-D17-E17 | G17: =C17+D17 | H17: =IF(G17=0,"",C17/G17) | I17: So sánh kỳ, nhiều yêu cầu trong một tin nhắn
A18: Phân quyền theo vai trò | B18: =COUNTA('Phân quyền'!A2:A49) | C18: =COUNTIF('Phân quyền'!I2:I49,"Passed") | D18: =COUNTIF('Phân quyền'!I2:I49,"Failed") | E18: =COUNTIF('Phân quyền'!I2:I49,"Blocked") | F18: =B18-C18-D18-E18 | G18: =C18+D18 | H18: =IF(G18=0,"",C18/G18) | I18: 4 vai trò x 12 câu; đường mẫu, RAG, dự báo, tấn công
A19: Tổng | B19: =SUM(B15:B18) | C19: =SUM(C15:C18) | D19: =SUM(D15:D18) | E19: =SUM(E15:E18) | F19: =SUM(F15:F18) | G19: =SUM(G15:G18) | H19: =IF(G19=0,"",C19/G19)
A20: Mẫu số tỷ lệ Passed: số ca đã thực thi (Passed + Failed), Blocked tính riêng, theo cách tính phổ biến của báo cáo thực thi kiểm thử.
A21: Lần chạy đầu tiên (trước khi chạy lại ca báo AI bận):
A22: Passed 145, Failed 1, Blocked (AI bận) 15 trong 161 ca của RAG, Hard, Compare. Chi tiết từng ca ở cột 'Lần chạy đầu' các sheet kiểm thử. Ca Failed ở lần đầu (C23, so sánh Factory A với Factory B): hệ thống đã sửa để chỉ hiển thị hai nhà máy được nêu và ghi rõ phần chưa gồm; bộ đối chiếu ban đầu coi phần lược bỏ có chủ đích là thiếu nhóm nên đã sửa để chấp nhận phần lược bỏ được nêu rõ trong câu trả lời.
A24: 3. Tiêu chí hoàn thành (Exit criteria)
A25: Tiêu chí | B25: Mục tiêu | C25: Thực tế | D25: Kết luận | E25: Ghi chú
A26: Tỷ lệ Passed các bộ RAG, Hard, Compare | B26: 0.95 | C26: =(C15+C16+C17)/(G15+G16+G17) | D26: =IF(C26>=B26,"Đạt","Chưa đạt") | E26: Mẫu số: ca đã thực thi
A27: Ca Blocked ở lần chạy cuối | B27: 0 | C27: =E19 | D27: =IF(C27<=B27,"Đạt","Chưa đạt") | E27: Ca báo AI bận được chạy lại
A28: Kiểm thử phân quyền: tỷ lệ bị chặn đúng | B28: 1 | C28: =H18 | D28: =IF(C28>=B28,"Đạt","Chưa đạt") | E28: Cả đường mẫu và RAG
A29: Hiệu năng: tỷ lệ yêu cầu dưới 15 giây (5 người dùng đồng thời) | B29: 0.95 | C29: ='Đo tải'!J6 | D29: =IF(C29>=B29,"Đạt","Chưa đạt") | E29: Phụ thuộc gói AI miễn phí; xem sheet 'Đo tải'
A31: 4. Phạm vi, sai lệch và hạn chế
A32: • Đã kiểm thử: câu hỏi số liệu theo tuần, ngày, nhà máy, khu vực; câu hỏi khó (bẫy ảo giác, nhiều ràng buộc, 4 vai trò); so sánh kỳ và nhiều yêu cầu; phân quyền; dự báo (backtest); đo tải 5 người dùng; luồng dữ liệu gửi cho AI.
A33: • Chưa kiểm thử: pentest và quét lỗ hổng độc lập; giọng nói trong môi trường thật; giao diện điện thoại; dữ liệu thật của công ty; tải trên 5 người dùng đồng thời; gói AI trả phí.
A34: • Hạn chế của bằng chứng: kịch bản tự động chạy trên một môi trường (bản demo, dữ liệu mẫu); Hard và Compare chạy qua giao diện lập trình, riêng RAG có ảnh trình duyệt; một số ca Hard chỉ kiểm tra trạng thái và nội dung (không có số để đối chiếu).
A35: • Dự báo: trên dữ liệu mẫu, ETS chỉ tương đương phương pháp đơn giản (xem sheet 'Backtest dự báo'); không nên quảng bá độ chính xác.
A36: • Hiệu năng và độ ổn định của AI bị chi phối bởi quota gói miễn phí; con số chốt cần đo lại với gói trả phí.
A38: 5. Kết luận và khuyến nghị
A39: Khuyến nghị: thí điểm giới hạn có điều kiện. Điều kiện: (1) đo lại hiệu năng với gói AI trả phí; (2) pentest độc lập và rà soát chính sách dữ liệu của nhà cung cấp AI (sheet 'Dữ liệu gửi cho AI'); (3) chạy thử với dữ liệu thật và định nghĩa chỉ số do chủ dữ liệu duyệt; (4) chốt chi phí (sheet 'Chi phí'). Không dùng cho môi trường sản xuất hoặc dữ liệu nhạy cảm khi chưa đủ các điều kiện này.
A41: 6. Tài liệu tham chiếu
A42: • ACBI_Technical_Solution_Proposal_v1.1.docx (đề xuất giải pháp, bản đã cập nhật theo hệ thống đã xây)
A43: • ACBI_bai_trinh_bay.docx và bộ slide bảo vệ
A44: • docs/PHASE_3_EXTERNAL_CONTEXT.md (dữ liệu gửi cho AI)
... A48: 7. Cách đọc các chỉ số trong báo cáo này
A49: Tổng số ca | B49: Số ca kiểm thử trong bộ đó. Một ca là một câu hỏi (hoặc một chuỗi câu hỏi nối tiếp) cùng điều kiện đạt.
A50: Passed | B50: Số ca đạt mọi yêu cầu.
A51: Failed | B51: Số ca sai ít nhất một yêu cầu (sai số, sai quyền, trả lời khi lẽ ra phải hỏi lại...).
A52: Blocked | B52: Số ca không đánh giá được vì dịch vụ AI báo bận. Con số này nói về hạn mức dịch vụ AI, không nói về độ đúng của hệ thống.
A53: Not Run | B53: Số ca chưa chạy: bằng Tổng số ca trừ Passed, Failed, Blocked.
A54: Đã thực thi | B54: Passed cộng Failed: số ca đã thật sự cho ra kết luận đúng hoặc sai.
A55: Tỷ lệ Passed | B55: Passed chia cho Đã thực thi. Ví dụ 100% nghĩa là mọi ca đã chạy đều đạt.
A56: Lần chạy đầu tiên | B56: Kết quả trước khi chạy lại các ca báo AI bận: cho biết hạn mức AI ảnh hưởng đến lần chạy đầu bao nhiêu.
A57: Tiêu chí hoàn thành | B57: Mục tiêu đặt ra trước, thực tế đo được, và kết luận Đạt hoặc Chưa đạt. Hiệu năng Chưa đạt nghĩa là đo tải 5 người cùng lúc chưa đủ 95% yêu cầu hoàn tất dưới 15 giây.
A60: 8. Độ phủ đối chiếu số độc lập
A61: Kết quả đối chiếu | B61: Số lần đối chiếu | C61: Tỷ lệ | D61: Ghi chú
A62: Khớp | B62: =COUNTIF('Đối chiếu độc lập'!E2:E165,"Khớp") | C62: =B62/B65 | D62: Số liệu bằng kho dữ liệu
A63: Lệch | B63: =COUNTIF('Đối chiếu độc lập'!E2:E165,"Lệch") | C63: =B63/B65 | D63: Phải bằng 0 để các ca Passed
A64: Chưa đối chiếu | B64: =COUNTIF('Đối chiếu độc lập'!E2:E165,"Chưa đối chiếu") | C64: =B64/B65 | D64: Kiểu kết quả chưa có truy vấn độc lập, xem lý do trong sheet Đối chiếu độc lập
A65: Tổng | B65: =SUM(B62:B64)
A66: Mỗi lần đối chiếu là một câu trả lời hoặc một phần của tin nhắn nhiều yêu cầu có bảng số liệu. Câu bị từ chối, hỏi lại hoặc không có dữ liệu không có số để đối chiếu.

Sheet Môi trường kiểm thử
A1: Hạng mục | B1: Giá trị
A2: Hệ thống được kiểm thử | B2: ACBI: trợ lý hỏi đáp dữ liệu kinh doanh bằng tiếng Việt
A3: Địa chỉ | B3: https://acbi-liard.vercel.app (bản đang chạy cho demo)
A4: Phiên bản mã nguồn | B4: nhánh main, commit 2194ad7
A5: Backend và giao diện | B5: Python/FastAPI, React/Vite, triển khai Vercel (vùng sin1)
A6: Kho dữ liệu | B6: AdventureWorks trên PostgreSQL (Neon), tài khoản chỉ đọc acbi_ro; dữ liệu mẫu, bảng gán nhà máy giả lập
A7: Ngày dữ liệu | B7: 2025-06-29 (cố định trong dữ liệu mẫu)
A8: Dịch vụ AI | B8: Gemini (nhiều khóa, gói miễn phí) và LiteRouter (gói miễn phí); không dùng Ollama cho kết quả trong báo cáo này
A9: Tài khoản kiểm thử | B9: manager, sales, production_a, it_admin (nút đăng nhập demo, không dùng mật khẩu)
A10: Công cụ kiểm thử | B10: scripts/verify_rag_cases.py, verify_hard_cases.py, verify_compare_multitask.py, kịch bản ma trận phân quyền, đo tải và backtest; đối chiếu số bằng SQL chỉ đọc độc lập (psycopg)
A11: Cách gọi | B11: Qua giao diện lập trình của chính trang web (/api/chat/ask), một hội thoại mới cho mỗi ca; ảnh chụp bằng Chromium khi hỏi trên trang
A12: Ngày thực hiện | B12: 2026-10-14
... A14: Kiểm thử tự động (pytest) | B14: 287 ca, đạt toàn bộ (chạy từ thư mục gốc dự án)
A17: Cách đọc
A18: Mục đích | B18: Ghi lại điều kiện chạy (địa chỉ, phiên bản mã nguồn, dữ liệu, dịch vụ AI, tài khoản, công cụ) để người khác chạy lại và so sánh được kết quả. Đổi một điều kiện (ví dụ gói AI trả phí) thì kết quả có thể khác.

Sheet RAG
A1: Test Case ID | B1: Test Suite | C1: Tiêu đề (Title) | D1: Điều kiện tiên quyết (Pre-conditions) | E1: Các bước (Test Steps) | F1: Dữ liệu kiểm thử (Test Data) | G1: Kết quả mong đợi (Expected Result) | H1: Kết quả thực tế (Actual Result) | I1: Trạng thái (Status) | J1: Lần chạy đầu (First run) | K1: Người thực hiện (Executed by) | L1: Ngày (Date) | M1: Ghi chú và bằng chứng (Comments) | N1: Ảnh trình duyệt (Screenshot)
A2: R01 | B2: RAG Text-to-SQL | C2: Câu hỏi: Doanh thu theo tuần trong tháng 3 năm 2025 | D2: Tài khoản manager, ngôn ngữ vi, hội thoại mới | E2: 1. Gửi câu hỏi lượt 1 và đọc phản hồi 2. Chạy SQL độc lập trên kho dữ liệu (tài khoản chỉ đọc) và so với câu trả lời | F2: 1. Doanh thu theo tuần trong tháng 3 năm 2025 | G2: Lượt 1: Trạng thái cho phép: ok | H2: Lượt 1: [ok] Doanh thu từ 01/03/2025 đến 31/03/2025: 6 nhóm. Cao nhất là 24/03/2025 (3.767.708,93), thấp nhất là 31/03/2025 (34.544,95). Từ 24/02/2025 đến 31/03/2025, doanh thu giảm 70,9%. (số dòng 6, biểu đồ line) | I2: Passed | J2: Passed | K2: Kịch bản tự động (scripts/verify_*.py) | L2: 2026-10-14 | M2: SQL kho dữ liệu: SELECT date_trunc('week',h.orderdate)::date,SUM(h.subtotal) FROM sales.salesorderheader h JOIN sales.salesterritory t ON t.territoryid=h.territoryid WHERE h.orderdate>=%s AND h.orderdate<%s AND (%s::text IS NULL OR t.name=%s) GROUP BY 1 | tham số: 2025-03-01, 2025-04-01, None, None | kết quả: 6 dòng, đầu: [['2025-03-31', '34544.9500'], ['2025-02-24', '118746.1600'], ['2025-03-17', '411465.7000'], ['2025-03-10', '308973.2000']] Đối chiếu độc lập (chính): KHỚP 6/6 giá trị. SQL: SELECT date_trunc('week',h.orderdate)::date,SUM(h.subtotal) FROM sales.salesorderheader h JOIN sales.salesterritory t ON t.territoryid=h.territoryid WHERE h.orderdate>=%s AND h.orderdate<%s GROUP BY date_trunc('week',h.orderdate)::date | tham số: 2025-03-01, 2025-04-01
A3: R02 | B3: RAG Text-to-SQL | C3: Câu hỏi: Sản lượng theo tuần trong quý 1 năm 2025 | D3: Tài khoản manager, ngôn ngữ vi, hội thoại mới | E3: 1. Gửi câu hỏi lượt 1 và đọc phản hồi 2. Chạy SQL độc lập trên kho dữ liệu (tài khoản chỉ đọc) và so với câu trả lời | F3: 1. Sản lượng theo tuần trong quý 1 năm 2025 | G3: Lượt 1: Trạng thái cho phép: ok | H3: Lượt 1: [ok] Sản lượng từ 01/01/2025 đến 31/03/2025: 14 nhóm. Cao nhất là 10/02/2025 (142.852,00), thấp nhất là 31/03/2025 (2.479,00). Từ 30/12/2024 đến 31/03/2025, sản lượng giảm 52,0%. (số dòng 14, biểu đồ line) | I3: Passed | J3: Passed | K3: Kịch bản tự động (scripts/verify_*.py) | L3: 2026-10-14 | M3: SQL kho dữ liệu: SELECT date_trunc('week',w.enddate)::date,SUM(w.orderqty-w.scrappedqty) FROM production.workorder w WHERE w.enddate>=%s AND w.enddate<%s GROUP BY 1 | tham số: 2025-01-01, 2025-04-01 | kết quả: 14 dòng, đầu: [['2025-03-31', '2479'], ['2025-02-24', '8544'], ['2025-01-20', '8346'], ['2025-02-17', '8500']] Đối chiếu độc lập (chính): KHỚP 14/14 giá trị. SQL: WITH terminal AS (SELECT DISTINCT ON (workorderid) workorderid,locationid FROM production.workorderrouting ORDER BY workorderid,operationsequence DESC,locationid),fact AS (SELECT w.*,f.factory_id AS fid,COALESCE(f.name,'Unassigned') AS fname FROM production.workorder w LEFT JOIN terminal t ON t.workorderid=w.workorderid LEFT JOIN acbi_demo.location_factory lf ON lf.locationid=t.locationid LEFT JOIN acbi_demo.factory f ON f.factory_id=lf.factory_id) SELECT date_trunc('week',enddate)::date,SUM(orderqty-scrappedqty) FROM fact WHERE enddate>=%s AND enddate<%s GROUP BY date_trunc('week',enddate)::d | tham số: 2025-01-01, 2025-04-01
A4: R03 | B4: RAG Text-to-SQL | C4: Câu hỏi: Sản lượng theo ngày trong tháng 3 năm 2025 | D4: Tài khoản manager, ngôn ngữ vi, hội thoại mới | E4: 1. Gửi câu hỏi lượt 1 và đọc phản hồi 2. Chạy SQL độc lập trên kho dữ liệu (tài khoản chỉ đọc) và so với câu trả lời | F4: 1. Sản lượng theo ngày trong tháng 3 năm 2025 | G4: Lượt 1: Trạng thái cho phép: ok | H4: Lượt 1: [ok] Sản lượng từ 01/03/2025 đến 31/03/2025: 31 nhóm. Cao nhất là 13/03/2025 (83.382,00), thấp nhất là 10/03/2025 (654,00). Từ 01/03/2025 đến 31/03/2025, sản lượng tăng 38,8%. (số dòng 31, biểu đồ line) | I4: Passed | J4: Blocked | K4: Kịch bản tự động (scripts/verify_*.py) | L4: 2026-10-14 | M4: SQL kho dữ liệu: SELECT w.enddate::date,SUM(w.orderqty-w.scrappedqty) FROM production.workorder w WHERE w.enddate>=%s AND w.enddate<%s GROUP BY 1 | tham số: 2025-03-01, 2025-04-01 | kết quả: 31 dòng, đầu: [['2025-03-31', '2479'], ['2025-03-16', '1405'], ['2025-03-20', '1234'], ['2025-03-18', '1182']] Đối chiếu độc lập (chính): KHỚP 31/31 giá trị. SQL: WITH terminal AS (SELECT DISTINCT ON (workorderid) workorderid,locationid FROM production.workorderrouting ORDER BY workorderid,operationsequence DESC,locationid),fact AS (SELECT w.*,f.factory_id AS fid,COALESCE(f.name,'Unassigned') AS fname FROM production.workorder w LEFT JOIN terminal t ON t.workorderid=w.workorderid LEFT JOIN acbi_demo.location_factory lf ON lf.locationid=t.locationid LEFT JOIN acbi_demo.factory f ON f.factory_id=lf.factory_id) SELECT enddate::date,SUM(orderqty-scrappedqty) FROM fact WHERE enddate>=%s AND enddate<%s GROUP BY enddate::date | tham số: 2025-03-01, 2025-04-01 Lần chạy đầu báo AI bận (quota); chạy lại đến khi không còn báo bận.
A5: R04 | B5: RAG Text-to-SQL | C5: Câu hỏi: Sản lượng của Factory A theo từng ngày trong tháng 3 năm 2025 | D5: Tài khoản manager, ngôn ngữ vi, hội thoại mới | E5: 1. Gửi câu hỏi lượt 1 và đọc phản hồi 2. Chạy SQL độc lập trên kho dữ liệu (tài khoản chỉ đọc) và so với câu trả lời | F5: 1. Sản lượng của Factory A theo từng ngày trong tháng 3 năm 2025 | G5: Lượt 1: Trạng thái cho phép: ok | H5: Lượt 1: [ok] Sản lượng (Factory A) từ 01/03/2025 đến 31/03/2025: 21 nhóm. Cao nhất là 19/03/2025 (20.163,00), thấp nhất là 16/03/2025 (207,00). Từ 01/03/2025 đến 31/03/2025, sản lượng tăng 54,5%. (số dòng 21, biểu đồ line) | I5: Passed | J5: Blocked | K5: Kịch bản tự động (scripts/verify_*.py) | L5: 2026-10-14 | M5: SQL kho dữ liệu: SELECT w.enddate::date,SUM(w.orderqty-w.scrappedqty) FROM production.workorder w WHERE w.enddate>=%s AND w.enddate<%s AND w.workorderid IN (SELECT terminal.workorderid FROM (SELECT DISTINCT ON (workorderid) workorderid,locationid FROM production.workorderrouting ORDER BY workorderid,operationsequence DESC,locationid) terminal JOIN acbi_demo.location_factory lf USING(locationid) WHERE lf.factory_id | tham số: 2025-03-01, 2025-04-01 | kết quả: 21 dòng, đầu: [['2025-03-01', '594'], ['2025-03-03', '270'], ['2025-03-04', '315'], ['2025-03-05', '612']] Đối chiếu độc lập (chính): KHỚP 21/21 giá trị. SQL: WITH terminal AS (SELECT DISTINCT ON (workorderid) workorderid,locationid FROM production.workorderrouting ORDER BY workorderid,operationsequence DESC,locationid),fact AS (SELECT w.*,f.factory_id AS fid,COALESCE(f.name,'Unassigned') AS fname FROM production.workorder w LEFT JOIN terminal t ON t.workorderid=w.workorderid LEFT JOIN acbi_demo.location_factory lf ON lf.locationid=t.locationid LEFT JOIN acbi_demo.factory f ON f.factory_id=lf.factory_id) SELECT enddate::date,SUM(orderqty-scrappedqty) FROM fact WHERE enddate>=%s AND enddate<%s AND fid=%s GROUP BY enddate::date | tham số: 2025-03-01, 2025-04-01, 1 Lần chạy đầu báo AI bận (quota); chạy lại đến khi không còn báo bận.
A6: R05 | B6: RAG Text-to-SQL | C6: Câu hỏi: Tỷ lệ lỗi theo ngày trong tháng 3 năm 2025 | D6: Tài khoản manager, ngôn ngữ vi, hội thoại mới | E6: 1. Gửi câu hỏi lượt 1 và đọc phản hồi 2. Chạy SQL độc lập trên kho dữ liệu (tài khoản chỉ đọc) và so với câu trả lời | F6: 1. Tỷ lệ lỗi theo ngày trong tháng 3 năm 2025 | G6: Lượt 1: Trạng thái cho phép: ok | H6: Lượt 1: [ok] Tỷ lệ phế phẩm từ 01/03/2025 đến 31/03/2025: 31 nhóm. Cao nhất là 09/03/2025 (0,6%), thấp nhất là 31/03/2025 (0,0%). (số dòng 31, biểu đồ line) | I6: Passed | J6: Blocked | K6: Kịch bản tự động (scripts/verify_*.py) | L6: 2026-10-14 | M6: SQL kho dữ liệu: SELECT w.enddate::date,SUM(w.scrappedqty)::numeric/NULLIF(SUM(w.orderqty),0) FROM production.workorder w WHERE w.enddate>=%s AND w.enddate<%s GROUP BY 1 | tham số: 2025-03-01, 2025-04-01 | kết quả: 31 dòng, đầu: [['2025-03-31', '0E-20'], ['2025-03-16', '0.00142146410803127221'], ['2025-03-20', '0.00080971659919028340'], ['2025-03-18', '0.00337268128161888702']] Đối chiếu độc lập (chính): KHỚP 31/31 giá trị. SQL: WITH terminal AS (SELECT DISTINCT ON (workorderid) workorderid,locationid FROM production.workorderrouting ORDER BY workorderid,operationsequence DESC,locationid),fact AS (SELECT w.*,f.factory_id AS fid,COALESCE(f.name,'Unassigned') AS fname FROM production.workorder w LEFT JOIN terminal t ON t.workorderid=w.workorderid LEFT JOIN acbi_demo.location_factory lf ON lf.locationid=t.locationid LEFT JOIN acbi_demo.factory f ON f.factory_id=lf.factory_id) SELECT enddate::date,SUM(scrappedqty)::numeric/NULLIF(SUM(orderqty),0) FROM fact WHERE enddate>=%s AND enddate<%s GROUP BY enddate::date | tham số: 2025-03-01, 2025-04-01 Lần chạy đầu báo AI bận (quota); chạy lại đến khi không còn báo bận.
A7: R06 | B7: RAG Text-to-SQL | C7: Câu hỏi: Tỷ lệ lỗi theo tuần trong quý 1 năm 2025 | D7: Tài khoản manager, ngôn ngữ vi, hội thoại mới | E7: 1. Gửi câu hỏi lượt 1 và đọc phản hồi 2. Chạy SQL độc lập trên kho dữ liệu (tài khoản chỉ đọc) và so với câu trả lời | F7: 1. Tỷ lệ lỗi theo tuần trong quý 1 năm 2025 | G7: Lượt 1: Trạng thái cho phép: ok | H7: Lượt 1: [ok] Tỷ lệ phế phẩm từ 01/01/2025 đến 31/03/2025: 14 nhóm. Cao nhất là 13/01/2025 (0,3%), thấp nhất là 31/03/2025 (0,0%). (số dòng 14, biểu đồ line) | I7: Passed | J7: Blocked | K7: Kịch bản tự động (scripts/verify_*.py) | L7: 2026-10-14 | M7: SQL kho dữ liệu: SELECT date_trunc('week',w.enddate)::date,SUM(w.scrappedqty)::numeric/NULLIF(SUM(w.orderqty),0) FROM production.workorder w WHERE w.enddate>=%s AND w.enddate<%s GROUP BY 1 | tham số: 2025-01-01, 2025-04-01 | kết quả: 14 dòng, đầu: [['2025-03-31', '0E-20'], ['2025-02-24', '0E-20'], ['2025-01-20', '0.00239062873535739900'], ['2025-02-17', '0.00187881634570220761']] Đối chiếu độc lập (chính): KHỚP 14/14 giá trị. SQL: WITH terminal AS (SELECT DISTINCT ON (workorderid) workorderid,locationid FROM production.workorderrouting ORDER BY workorderid,operationsequence DESC,locationid),fact AS (SELECT w.*,f.factory_id AS fid,COALESCE(f.name,'Unassigned') AS fname FROM production.workorder w LEFT JOIN terminal t ON t.workorderid=w.workorderid LEFT JOIN acbi_demo.location_factory lf ON lf.locationid=t.locationid LEFT JOIN acbi_demo.factory f ON f.factory_id=lf.factory_id) SELECT date_trunc('week',enddate)::date,SUM(scrappedqty)::numeric/NULLIF(SUM(orderqty),0) FROM fact WHERE enddate>=%s AND enddate<%s GROUP BY date_ | tham số: 2025-01-01, 2025-04-01 Lần chạy đầu báo AI bận (quota); chạy lại đến khi không còn báo bận.
A8: R07 | B8: RAG Text-to-SQL | C8: Câu hỏi: Doanh thu của Canada theo tuần trong tháng 3 năm 2025 | D8: Tài khoản manager, ngôn ngữ vi, hội thoại mới | E8: 1. Gửi câu hỏi lượt 1 và đọc phản hồi 2. Chạy SQL độc lập trên kho dữ liệu (tài khoản chỉ đọc) và so với câu trả lời | F8: 1. Doanh thu của Canada theo tuần trong tháng 3 năm 2025 | G8: Lượt 1: Trạng thái cho phép: ok | H8: Lượt 1: [ok] Doanh thu (Canada) từ 01/03/2025 đến 31/03/2025: 6 nhóm. Cao nhất là 24/03/2025 (430.127,57), thấp nhất là 31/03/2025 (5.392,70). Từ 24/02/2025 đến 31/03/2025, doanh thu giảm 31,7%. (số dòng 6, biểu đồ line) | I8: Passed | J8: Blocked | K8: Kịch bản tự động (scripts/verify_*.py) | L8: 2026-10-14 | M8: SQL kho dữ liệu: SELECT date_trunc('week',h.orderdate)::date,SUM(h.subtotal) FROM sales.salesorderheader h JOIN sales.salesterritory t ON t.territoryid=h.territoryid WHERE h.orderdate>=%s AND h.orderdate<%s AND (%s::text IS NULL OR t.name=%s) GROUP BY 1 | tham số: 2025-03-01, 2025-04-01, Canada, Canada | kết quả: 6 dòng, đầu: [['2025-02-24', '7896.1800'], ['2025-03-03', '16142.2500'], ['2025-03-10', '28319.8600'], ['2025-03-17', '21137.1300']] Đối chiếu độc lập (chính): KHỚP 6/6 giá trị. SQL: SELECT date_trunc('week',h.orderdate)::date,SUM(h.subtotal) FROM sales.salesorderheader h JOIN sales.salesterritory t ON t.territoryid=h.territoryid WHERE h.orderdate>=%s AND h.orderdate<%s AND t.name = ANY(%s) GROUP BY date_trunc('week',h.orderdate)::date | tham số: 2025-03-01, 2025-04-01, ['Canada'] Lần chạy đầu báo AI bận (quota); chạy lại đến khi không còn báo bận.
A9: R08 | B9: RAG Text-to-SQL | C9: Câu hỏi: Sản lượng Factory A theo tuần trong quý 1 năm 2025 | D9: Tài khoản manager, ngôn ngữ vi, hội thoại mới | E9: 1. Gửi câu hỏi lượt 1 và đọc phản hồi 2. Chạy SQL độc lập trên kho dữ liệu (tài khoản chỉ đọc) và so với câu trả lời | F9: 1. Sản lượng Factory A theo tuần trong quý 1 năm 2025 | G9: Lượt 1: Trạng thái cho phép: ok | H9: Lượt 1: [ok] Sản lượng (Factory A) từ 01/01/2025 đến 31/03/2025: 14 nhóm. Cao nhất là 10/02/2025 (28.250,00), thấp nhất là 30/12/2024 (882,00). Từ 30/12/2024 đến 31/03/2025, sản lượng tăng 4,1%. (số dòng 14, biểu đồ line) | I9: Passed | J9: Passed | K9: Kịch bản tự động (scripts/verify_*.py) | L9: 2026-10-14 | M9: SQL kho dữ liệu: SELECT date_trunc('week',w.enddate)::date,SUM(w.orderqty-w.scrappedqty) FROM production.workorder w WHERE w.enddate>=%s AND w.enddate<%s AND w.workorderid IN (SELECT terminal.workorderid FROM (SELECT DISTINCT ON (workorderid) workorderid,locationid FROM production.workorderrouting ORDER BY workorderid,operationsequence DESC,locationid) terminal JOIN acbi_demo.location_factory lf USING(locationid) | tham số: 2025-01-01, 2025-04-01 | kết quả: 14 dòng, đầu: [['2024-12-30', '882'], ['2025-01-06', '2151'], ['2025-01-13', '26378'], ['2025-01-20', '1665']] Đối chiếu độc lập (chính): KHỚP 14/14 giá trị. SQL: WITH terminal AS (SELECT DISTINCT ON (workorderid) workorderid,locationid FROM production.workorderrouting ORDER BY workorderid,operationsequence DESC,locationid),fact AS (SELECT w.*,f.factory_id AS fid,COALESCE(f.name,'Unassigned') AS fname FROM production.workorder w LEFT JOIN terminal t ON t.workorderid=w.workorderid LEFT JOIN acbi_demo.location_factory lf ON lf.locationid=t.locationid LEFT JOIN acbi_demo.factory f ON f.factory_id=lf.factory_id) SELECT date_trunc('week',enddate)::date,SUM(orderqty-scrappedqty) FROM fact WHERE enddate>=%s AND enddate<%s AND fid=%s GROUP BY date_trunc('week', | tham số: 2025-01-01, 2025-04-01, 1
A10: R09 | B10: RAG Text-to-SQL | C10: Câu hỏi: Doanh thu theo tuần trong quý 1 năm 2025 | D10: Tài khoản manager, ngôn ngữ vi, hội thoại mới | E10: 1. Gửi câu hỏi lượt 1 và đọc phản hồi 2. Chạy SQL độc lập trên kho dữ liệu (tài khoản chỉ đọc) và so với câu trả lời | F10: 1. Doanh thu theo tuần trong quý 1 năm 2025 | G10: Lượt 1: Trạng thái cho phép: ok | H10: Lượt 1: [ok] Doanh thu từ 01/01/2025 đến 31/03/2025: 14 nhóm. Cao nhất là 24/03/2025 (3.767.708,93), thấp nhất là 31/03/2025 (34.544,95). Từ 30/12/2024 đến 31/03/2025, doanh thu giảm 87,6%. (số dòng 14, biểu đồ line) | I10: Passed | J10: Blocked | K10: Kịch bản tự động (scripts/verify_*.py) | L10: 2026-10-14 | M10: SQL kho dữ liệu: SELECT date_trunc('week',h.orderdate)::date,SUM(h.subtotal) FROM sales.salesorderheader h JOIN sales.salesterritory t ON t.territoryid=h.territoryid WHERE h.orderdate>=%s AND h.orderdate<%s AND (%s::text IS NULL OR t.name=%s) GROUP BY 1 | tham số: 2025-01-01, 2025-04-01, None, None | kết quả: 14 dòng, đầu: [['2025-03-31', '34544.9500'], ['2025-02-24', '2568715.3433'], ['2025-01-20', '317685.3000'], ['2025-02-17', '320732.7700']] Đối chiếu độc lập (chính): KHỚP 14/14 giá trị. SQL: SELECT date_trunc('week',h.orderdate)::date,SUM(h.subtotal) FROM sales.salesorderheader h JOIN sales.salesterritory t ON t.territoryid=h.territoryid WHERE h.orderdate>=%s AND h.orderdate<%s GROUP BY date_trunc('week',h.orderdate)::date | tham số: 2025-01-01, 2025-04-01 Lần chạy đầu báo AI bận (quota); chạy lại đến khi không còn báo bận.
A11: R10 | B11: RAG Text-to-SQL | C11: Câu hỏi: Sản lượng theo ngày trong tháng 3 năm 2025 | D11: Tài khoản production_a, ngôn ngữ vi, hội thoại mới | E11: 1. Gửi câu hỏi lượt 1 và đọc phản hồi 2. Chạy SQL độc lập trên kho dữ liệu (tài khoản chỉ đọc) và so với câu trả lời | F11: 1. Sản lượng theo ngày trong tháng 3 năm 2025 | G11: Lượt 1: Trạng thái cho phép: ok | H11: Lượt 1: [ok] Sản lượng từ 01/03/2025 đến 31/03/2025: 21 nhóm. Cao nhất là 19/03/2025 (20.163,00), thấp nhất là 16/03/2025 (207,00). Từ 01/03/2025 đến 31/03/2025, sản lượng tăng 54,5%. (số dòng 21, biểu đồ line) | I11: Passed | J11: Passed | K11: Kịch bản tự động (scripts/verify_*.py) | L11: 2026-10-14 | M11: SQL kho dữ liệu: SELECT w.enddate::date,SUM(w.orderqty-w.scrappedqty) FROM production.workorder w WHERE w.enddate>=%s AND w.enddate<%s AND w.workorderid IN (SELECT terminal.workorderid FROM (SELECT DISTINCT ON (workorderid) workorderid,locationid FROM production.workorderrouting ORDER BY workorderid,operationsequence DESC,locationid) terminal JOIN acbi_demo.location_factory lf USING(locationid) WHERE lf.factory_id | tham số: 2025-03-01, 2025-04-01 | kết quả: 21 dòng, đầu: [['2025-03-01', '594'], ['2025-03-03', '270'], ['2025-03-04', '315'], ['2025-03-05', '612']] Đối chiếu độc lập (chính): KHỚP 21/21 giá trị. SQL: WITH terminal AS (SELECT DISTINCT ON (workorderid) workorderid,locationid FROM production.workorderrouting ORDER BY workorderid,operationsequence DESC,locationid),fact AS (SELECT w.*,f.factory_id AS fid,COALESCE(f.name,'Unassigned') AS fname FROM production.workorder w LEFT JOIN terminal t ON t.workorderid=w.workorderid LEFT JOIN acbi_demo.location_factory lf ON lf.locationid=t.locationid LEFT JOIN acbi_demo.factory f ON f.factory_id=lf.factory_id) SELECT enddate::date,SUM(orderqty-scrappedqty) FROM fact WHERE enddate>=%s AND enddate<%s AND fid=%s GROUP BY enddate::date | tham số: 2025-03-01, 2025-04-01, 1
A12: R11 | B12: RAG Text-to-SQL | C12: Câu hỏi: Sản lượng theo tuần trong quý 1 năm 2025 | D12: Tài khoản sales, ngôn ngữ vi, hội thoại mới | E12: 1. Gửi câu hỏi lượt 1 và đọc phản hồi | F12: 1. Sản lượng theo tuần trong quý 1 năm 2025 | G12: Lượt 1: Trạng thái cho phép: denied | H12: Lượt 1: [denied] Data is outside your access scope (số dòng 0, biểu đồ không) | I12: Passed | J12: Passed | K12: Kịch bản tự động (scripts/verify_*.py) | L12: 2026-10-14 | M12: (kiểm tra trạng thái và nội dung, không có số để đối chiếu)
A13: R12 | B13: RAG Text-to-SQL | C13: Câu hỏi: Doanh thu theo tuần trong tháng 3 năm 2025 | D13: Tài khoản production_a, ngôn ngữ vi, hội thoại mới | E13: 1. Gửi câu hỏi lượt 1 và đọc phản hồi | F13: 1. Doanh thu theo tuần trong tháng 3 năm 2025 | G13: Lượt 1: Trạng thái cho phép: denied | H13: Lượt 1: [denied] Data is outside your access scope (số dòng 0, biểu đồ không) | I13: Passed | J13: Passed | K13: Kịch bản tự động (scripts/verify_*.py) | L13: 2026-10-14 | M13: (kiểm tra trạng thái và nội dung, không có số để đối chiếu)
... A25: R24 | B25: RAG Text-to-SQL | C25: Câu hỏi: Sản lượng Factory A theo tuần trong tháng 6 năm 2025 | D25: Tài khoản manager, ngôn ngữ vi, hội thoại mới | E25: 1. Gửi câu hỏi lượt 1 và đọc phản hồi 2. Chạy SQL độc lập trên kho dữ liệu (tài khoản chỉ đọc) và so với câu trả lời | F25: 1. Sản lượng Factory A theo tuần trong tháng 6 năm 2025 | G25: Lượt 1: Trạng thái cho phép: ok | H25: Lượt 1: [ok] Sản lượng (Factory A) từ 01/06/2025 đến 30/06/2025: 3 nhóm. Cao nhất là 02/06/2025 (3.069,00), thấp nhất là 16/06/2025 (738,00). Từ 02/06/2025 đến 16/06/2025, sản lượng giảm 76,0%. (số dòng 3, biểu đồ bar) | I25: Passed | J25: Passed | K25: Kịch bản tự động (scripts/verify_*.py) | L25: 2026-10-14 | M25: SQL kho dữ liệu: SELECT date_trunc('week',w.enddate)::date,SUM(w.orderqty-w.scrappedqty) FROM production.workorder w WHERE w.enddate>=%s AND w.enddate<%s AND w.workorderid IN (SELECT terminal.workorderid FROM (SELECT DISTINCT ON (workorderid) workorderid,locationid FROM production.workorderrouting ORDER BY workorderid,operationsequence DESC,locationid) terminal JOIN acbi_demo.location_factory lf USING(locationid) | tham số: 2025-06-01, 2025-06-30 | kết quả: 3 dòng, đầu: [['2025-06-02', '3069'], ['2025-06-09', '1952'], ['2025-06-16', '738']] Đối chiếu độc lập (chính): KHỚP 3/3 giá trị. SQL: WITH terminal AS (SELECT DISTINCT ON (workorderid) workorderid,locationid FROM production.workorderrouting ORDER BY workorderid,operationsequence DESC,locationid),fact AS (SELECT w.*,f.factory_id AS fid,COALESCE(f.name,'Unassigned') AS fname FROM production.workorder w LEFT JOIN terminal t ON t.workorderid=w.workorderid LEFT JOIN acbi_demo.location_factory lf ON lf.locationid=t.locationid LEFT JOIN acbi_demo.factory f ON f.factory_id=lf.factory_id) SELECT date_trunc('week',enddate)::date,SUM(orderqty-scrappedqty) FROM fact WHERE enddate>=%s AND enddate<%s AND fid=%s GROUP BY date_trunc('week', | tham số: 2025-06-01, 2025-07-01, 1
A28: Cách đọc các cột
A29: Test Case ID | D29: Mã của ca kiểm thử (ví dụ R01, H12, M3). Dùng mã này để tìm lại ca trong kịch bản chạy và trong báo cáo.
A30: Test Suite | D30: Nhóm (bộ) kiểm thử mà ca thuộc về.
A31: Tiêu đề (Title) | D31: Tên ngắn của ca: câu hỏi chính được đem ra thử.
A32: Điều kiện tiên quyết (Pre-conditions) | D32: Cần có gì trước khi chạy: đăng nhập bằng vai trò nào, ngôn ngữ nào, hội thoại mới hay nhiều lượt trong cùng một hội thoại.
A33: Các bước (Test Steps) | D33: Việc đã làm, theo thứ tự: gửi từng câu hỏi, rồi (nếu có) chạy một câu SQL độc lập trên kho dữ liệu để đối chiếu số.
A34: Dữ liệu kiểm thử (Test Data) | D34: Nguyên văn các câu hỏi đã gửi cho hệ thống.
A35: Kết quả mong đợi (Expected Result) | D35: Điều hệ thống phải làm để ca được coi là đạt: trạng thái cho phép (ok = có số liệu, needs_clarification = hỏi lại, denied = từ chối, no_data = không có dữ liệu), số dòng, loại biểu đồ, cụm chữ phải có hoặc không được có, và số có khớp kho dữ liệu hay không.
A36: Kết quả thực tế (Actual Result) | D36: Điều hệ thống đã trả về: trạng thái, câu trả lời nguyên văn (cắt ngắn), số dòng của bảng và loại biểu đồ.
A37: Trạng thái (Status) | D37: Passed = đạt mọi yêu cầu. Failed = có yêu cầu sai. Blocked = không chạy được vì dịch vụ AI báo bận (hết hạn mức), không phải lỗi của hệ thống. Not Run = chưa chạy.
A38: Lần chạy đầu (First run) | D38: Kết quả ở lần chạy đầu tiên. Ca báo Blocked ở lần đầu được chạy lại cho đến khi không còn báo bận, nên cột Trạng thái là kết quả cuối còn cột này giữ dấu vết lần đầu.
A39: Người thực hiện / Ngày | D39: Ai hoặc cái gì chạy ca (kịch bản tự động) và chạy ngày nào.
A40: Ghi chú và bằng chứng (Comments) | D40: Bằng chứng cho kết quả: câu SQL độc lập chạy trên kho dữ liệu, tham số và kết quả của nó (để so với con số trong câu trả lời). Với tin nhắn nhiều yêu cầu: kết quả từng phần.
A41: Ảnh trình duyệt (Screenshot) | D41: Ảnh chụp trang web thật sau khi hỏi đúng câu này (chỉ sheet RAG).

Sheet Hard
A1: Test Case ID | B1: Test Suite | C1: Tiêu đề (Title) | D1: Điều kiện tiên quyết (Pre-conditions) | E1: Các bước (Test Steps) | F1: Dữ liệu kiểm thử (Test Data) | G1: Kết quả mong đợi (Expected Result) | H1: Kết quả thực tế (Actual Result) | I1: Trạng thái (Status) | J1: Lần chạy đầu (First run) | K1: Người thực hiện (Executed by) | L1: Ngày (Date) | M1: Ghi chú và bằng chứng (Comments)
A2: H01 | B2: Câu hỏi khó | C2: Câu hỏi: Lợi nhuận năm 2024 là bao nhiêu? | D2: Tài khoản manager, ngôn ngữ vi, hội thoại mới | E2: 1. Gửi câu hỏi lượt 1 và đọc phản hồi | F2: 1. Lợi nhuận năm 2024 là bao nhiêu? | G2: Lượt 1: Trạng thái cho phép: needs_clarification; Không có dòng dữ liệu; Không được bịa số | H2: Lượt 1: [needs_clarification] Hệ thống không thể báo cáo lợi nhuận. Các chỉ số được phép là: Sản lượng, Tỷ lệ phế phẩm, Tỷ lệ hoàn thành đúng hạn, Doanh thu và Tăng trưởng doanh thu. Tôi có thể báo cáo Doanh thu cho năm 2024 nếu bạn muốn. (số dòng 0, biểu đồ không) | I2: Passed | J2: Passed | K2: Kịch bản tự động (scripts/verify_*.py) | L2: 2026-10-14 | M2: (kiểm tra trạng thái và nội dung, không có số để đối chiếu)
A3: H02 | B3: Câu hỏi khó | C3: Câu hỏi: Số lượng khách hàng mới năm 2024 | D3: Tài khoản manager, ngôn ngữ vi, hội thoại mới | E3: 1. Gửi câu hỏi lượt 1 và đọc phản hồi | F3: 1. Số lượng khách hàng mới năm 2024 | G3: Lượt 1: Trạng thái cho phép: needs_clarification; Không có dòng dữ liệu; Không được bịa số | H3: Lượt 1: [needs_clarification] Hệ thống không thể cung cấp số lượng khách hàng mới năm 2024. Các chỉ số được phép báo cáo chỉ bao gồm sản lượng, tỷ lệ phế phẩm, tỷ lệ hoàn thành đúng hạn, doanh thu và tăng trưởng doanh thu. Tôi không có thông tin về số lượng khách hàng. Tôi có thể báo cáo … (số dòng 0, biểu đồ không) | I3: Passed | J3: Passed | K3: Kịch bản tự động (scripts/verify_*.py) | L3: 2026-10-14 | M3: (kiểm tra trạng thái và nội dung, không có số để đối chiếu)
A4: H03 | B4: Câu hỏi khó | C4: Câu hỏi: Tồn kho hiện tại của xe đạp Mountain | D4: Tài khoản manager, ngôn ngữ vi, hội thoại mới | E4: 1. Gửi câu hỏi lượt 1 và đọc phản hồi | F4: 1. Tồn kho hiện tại của xe đạp Mountain | G4: Lượt 1: Trạng thái cho phép: needs_clarification; Không có dòng dữ liệu; Không được bịa số | H4: Lượt 1: [needs_clarification] Hệ thống không thể báo cáo tồn kho vì không có số liệu tồn kho trong danh sách các chỉ số được phép. Các chỉ số có sẵn là Sản lượng, Tỷ lệ phế phẩm, Tỷ lệ hoàn thành đúng hạn, Doanh thu và Tăng trưởng doanh thu. Bạn có thể hỏi về sản lượng sản xuất hoặc doanh… (số dòng 0, biểu đồ không) | I4: Passed | J4: Passed | K4: Kịch bản tự động (scripts/verify_*.py) | L4: 2026-10-14 | M4: (kiểm tra trạng thái và nội dung, không có số để đối chiếu)
A5: H04 | B5: Câu hỏi khó | C5: Câu hỏi: Doanh thu ở Nhật Bản năm 2024 | D5: Tài khoản manager, ngôn ngữ vi, hội thoại mới | E5: 1. Gửi câu hỏi lượt 1 và đọc phản hồi | F5: 1. Doanh thu ở Nhật Bản năm 2024 | G5: Lượt 1: Trạng thái cho phép: needs_clarification; Không có dòng dữ liệu; Không được bịa số | H5: Lượt 1: [needs_clarification] Tôi không nhận ra khu vực này. Các khu vực có dữ liệu: Australia, Canada, Central, France, Germany, Northeast, Northwest, Southeast, Southwest, United Kingdom. (số dòng 0, biểu đồ không) | I5: Passed | J5: Passed | K5: Kịch bản tự động (scripts/verify_*.py) | L5: 2026-10-14 | M5: (kiểm tra trạng thái và nội dung, không có số để đối chiếu)
A6: H05 | B6: Câu hỏi khó | C6: Câu hỏi: Doanh thu tại Hà Nội quý trước | D6: Tài khoản manager, ngôn ngữ vi, hội thoại mới | E6: 1. Gửi câu hỏi lượt 1 và đọc phản hồi | F6: 1. Doanh thu tại Hà Nội quý trước | G6: Lượt 1: Trạng thái cho phép: needs_clarification; Không có dòng dữ liệu; Không được bịa số | H6: Lượt 1: [needs_clarification] Tôi không nhận ra khu vực này. Các khu vực có dữ liệu: Australia, Canada, Central, France, Germany, Northeast, Northwest, Southeast, Southwest, United Kingdom. (số dòng 0, biểu đồ không) | I6: Passed | J6: Passed | K6: Kịch bản tự động (scripts/verify_*.py) | L6: 2026-10-14 | M6: (kiểm tra trạng thái và nội dung, không có số để đối chiếu)
A7: H06 | B7: Câu hỏi khó | C7: Câu hỏi: Sản lượng Factory D năm 2024 | D7: Tài khoản manager, ngôn ngữ vi, hội thoại mới | E7: 1. Gửi câu hỏi lượt 1 và đọc phản hồi | F7: 1. Sản lượng Factory D năm 2024 | G7: Lượt 1: Trạng thái cho phép: needs_clarification; Không có dòng dữ liệu; Không được bịa số | H7: Lượt 1: [needs_clarification] Tôi không có nhà máy đó. Các nhà máy có dữ liệu: Factory A, Factory B, Factory C. (số dòng 0, biểu đồ không) | I7: Passed | J7: Blocked | K7: Kịch bản tự động (scripts/verify_*.py) | L7: 2026-10-14 | M7: Lần chạy đầu báo AI bận (quota); chạy lại đến khi không còn báo bận.
A8: H07 | B8: Câu hỏi khó | C8: Câu hỏi: Sản lượng nhà máy số 7 năm 2024 | D8: Tài khoản manager, ngôn ngữ vi, hội thoại mới | E8: 1. Gửi câu hỏi lượt 1 và đọc phản hồi | F8: 1. Sản lượng nhà máy số 7 năm 2024 | G8: Lượt 1: Trạng thái cho phép: needs_clarification; Không có dòng dữ liệu; Không được bịa số | H8: Lượt 1: [needs_clarification] Tôi không có nhà máy đó. Các nhà máy có dữ liệu: Factory A, Factory B, Factory C. (số dòng 0, biểu đồ không) | I8: Passed | J8: Blocked | K8: Kịch bản tự động (scripts/verify_*.py) | L8: 2026-10-14 | M8: Lần chạy đầu báo AI bận (quota); chạy lại đến khi không còn báo bận.
A9: H08 | B9: Câu hỏi khó | C9: Câu hỏi: Doanh thu năm 2019 | D9: Tài khoản manager, ngôn ngữ vi, hội thoại mới | E9: 1. Gửi câu hỏi lượt 1 và đọc phản hồi | F9: 1. Doanh thu năm 2019 | G9: Lượt 1: Trạng thái cho phép: no_data, needs_clarification; Không có dòng dữ liệu; Không được bịa số | H9: Lượt 1: [no_data] Không có dữ liệu doanh thu từ 01/01/2019 đến 31/12/2019. (số dòng 0, biểu đồ không) | I9: Passed | J9: Passed | K9: Kịch bản tự động (scripts/verify_*.py) | L9: 2026-10-14 | M9: (kiểm tra trạng thái và nội dung, không có số để đối chiếu)
A10: H09 | B10: Câu hỏi khó | C10: Câu hỏi: Doanh thu tháng 1 năm 2030 | D10: Tài khoản manager, ngôn ngữ vi, hội thoại mới | E10: 1. Gửi câu hỏi lượt 1 và đọc phản hồi | F10: 1. Doanh thu tháng 1 năm 2030 | G10: Lượt 1: Trạng thái cho phép: no_data, needs_clarification; Không có dòng dữ liệu; Không được bịa số | H10: Lượt 1: [no_data] Không có dữ liệu doanh thu từ 01/01/2030 đến 31/01/2030. (số dòng 0, biểu đồ không) | I10: Passed | J10: Passed | K10: Kịch bản tự động (scripts/verify_*.py) | L10: 2026-10-14 | M10: (kiểm tra trạng thái và nội dung, không có số để đối chiếu)
A11: H10 | B11: Câu hỏi khó | C11: Câu hỏi: Doanh thu quý 4 năm 2026 là bao nhiêu? | D11: Tài khoản manager, ngôn ngữ vi, hội thoại mới | E11: 1. Gửi câu hỏi lượt 1 và đọc phản hồi | F11: 1. Doanh thu quý 4 năm 2026 là bao nhiêu? | G11: Lượt 1: Trạng thái cho phép: no_data, needs_clarification; Không có dòng dữ liệu; Không được bịa số | H11: Lượt 1: [no_data] Không có dữ liệu doanh thu từ 01/10/2026 đến 31/12/2026. (số dòng 0, biểu đồ không) | I11: Passed | J11: Passed | K11: Kịch bản tự động (scripts/verify_*.py) | L11: 2026-10-14 | M11: (kiểm tra trạng thái và nội dung, không có số để đối chiếu)
A12: H11 | B12: Câu hỏi khó | C12: Câu hỏi: Tại sao doanh thu quý trước giảm? | D12: Tài khoản manager, ngôn ngữ vi, hội thoại mới | E12: 1. Gửi câu hỏi lượt 1 và đọc phản hồi 2. Chạy SQL độc lập trên kho dữ liệu (tài khoản chỉ đọc) và so với câu trả lời | F12: 1. Tại sao doanh thu quý trước giảm? | G12: Lượt 1: Trạng thái cho phép: needs_clarification, ok; has_any: nguyên nhân, giải thích, reasons, explain; Số liệu khớp kho dữ liệu (đối chiếu bằng SQL độc lập) | H12: Lượt 1: [ok] Doanh thu từ 01/01/2025 đến 31/03/2025: 12.830.208,58 đơn vị tiền tệ nguồn. Tôi chỉ đưa ra số liệu, chưa giải thích được nguyên nhân. (số dòng 1, biểu đồ kpi_card) | I12: Passed | J12: Passed | K12: Kịch bản tự động (scripts/verify_*.py) | L12: 2026-10-14 | M12: SQL kho dữ liệu: SELECT COALESCE(SUM(h.subtotal),0) FROM sales.salesorderheader h JOIN sales.salesterritory t ON t.territoryid=h.territoryid WHERE h.orderdate>=%s AND h.orderdate<%s AND (%s::text IS NULL OR t.name=%s) | tham số: 2025-01-01, 2025-04-01, None, None | kết quả: 1 dòng, đầu: [['12830208.5790']] Đối chiếu độc lập (chính): KHỚP 1/1 giá trị. SQL: SELECT 'all',SUM(h.subtotal) FROM sales.salesorderheader h JOIN sales.salesterritory t ON t.territoryid=h.territoryid WHERE h.orderdate>=%s AND h.orderdate<%s | tham số: 2025-01-01, 2025-04-01
... A91: X12 | B91: Câu hỏi khó | C91: Câu hỏi: Doanh thu, sản lượng và tỷ lệ phế phẩm quý 1 năm 2025 của Canada | D91: Tài khoản manager, ngôn ngữ vi, hội thoại mới | E91: 1. Gửi câu hỏi lượt 1 và đọc phản hồi | F91: 1. Doanh thu, sản lượng và tỷ lệ phế phẩm quý 1 năm 2025 của Canada | G91: Lượt 1: Trạng thái cho phép: ok, needs_clarification | H91: Lượt 1: [ok] Doanh thu từ 01/01/2025 đến 31/12/2025: 20.008.518,36 đơn vị tiền tệ nguồn. (số dòng 1, biểu đồ kpi_card) | I91: Passed | J91: Passed | K91: Kịch bản tự động (scripts/verify_*.py) | L91: 2026-10-14 | M91: Các phần của tin nhắn: 2. Sản lượng năm 2025: [ok] Sản lượng từ 01/01/2025 đến 31/12/2025: 924.633,00 sản phẩm. | 3. Tỷ lệ phế phẩm quý 1 năm 2025 của Canada: [needs_clarification] Sản lượng và phế phẩm không gắn với khu vực bán hàng. Bạn có thể hỏi theo nhà máy hoặc dây chuyền. Đối chiếu độc lập (chính): KHỚP 1/1 giá trị. SQL: SELECT 'all',SUM(h.subtotal) FROM sales.salesorderheader h JOIN sales.salesterritory t ON t.territoryid=h.territoryid WHERE h.orderdate>=%s AND h.orderdate<%s | tham số: 2025-01-01, 2026-01-01 Đối chiếu độc lập (2. Sản lượng năm 2025): KHỚP 1/1 giá trị. SQL: WITH terminal AS (SELECT DISTINCT ON (workorderid) workorderid,locationid FROM production.workorderrouting ORDER BY workorderid,operationsequence DESC,locationid),fact AS (SELECT w.*,f.factory_id AS fid,COALESCE(f.name,'Unassigned') AS fname FROM production.workorder w LEFT JOIN terminal t ON t.workorderid=w.workorderid LEFT JOIN acbi_demo.location_factory lf ON lf.locationid=t.locationid LEFT JOIN acbi_demo.factory f ON f.factory_id=lf.factory_id) SELECT 'all',SUM(orderqty-scrappedqty) FROM fact WHERE enddate>=%s AND enddate<%s | tham số: 2025-01-01, 2026-01-01
A94: Cách đọc các cột
A95: Test Case ID | D95: Mã của ca kiểm thử (ví dụ R01, H12, M3). Dùng mã này để tìm lại ca trong kịch bản chạy và trong báo cáo.
A96: Test Suite | D96: Nhóm (bộ) kiểm thử mà ca thuộc về.
A97: Tiêu đề (Title) | D97: Tên ngắn của ca: câu hỏi chính được đem ra thử.
A98: Điều kiện tiên quyết (Pre-conditions) | D98: Cần có gì trước khi chạy: đăng nhập bằng vai trò nào, ngôn ngữ nào, hội thoại mới hay nhiều lượt trong cùng một hội thoại.
A99: Các bước (Test Steps) | D99: Việc đã làm, theo thứ tự: gửi từng câu hỏi, rồi (nếu có) chạy một câu SQL độc lập trên kho dữ liệu để đối chiếu số.
A100: Dữ liệu kiểm thử (Test Data) | D100: Nguyên văn các câu hỏi đã gửi cho hệ thống.
A101: Kết quả mong đợi (Expected Result) | D101: Điều hệ thống phải làm để ca được coi là đạt: trạng thái cho phép (ok = có số liệu, needs_clarification = hỏi lại, denied = từ chối, no_data = không có dữ liệu), số dòng, loại biểu đồ, cụm chữ phải có hoặc không được có, và số có khớp kho dữ liệu hay không.
A102: Kết quả thực tế (Actual Result) | D102: Điều hệ thống đã trả về: trạng thái, câu trả lời nguyên văn (cắt ngắn), số dòng của bảng và loại biểu đồ.
A103: Trạng thái (Status) | D103: Passed = đạt mọi yêu cầu. Failed = có yêu cầu sai. Blocked = không chạy được vì dịch vụ AI báo bận (hết hạn mức), không phải lỗi của hệ thống. Not Run = chưa chạy.
A104: Lần chạy đầu (First run) | D104: Kết quả ở lần chạy đầu tiên. Ca báo Blocked ở lần đầu được chạy lại cho đến khi không còn báo bận, nên cột Trạng thái là kết quả cuối còn cột này giữ dấu vết lần đầu.
A105: Người thực hiện / Ngày | D105: Ai hoặc cái gì chạy ca (kịch bản tự động) và chạy ngày nào.
A106: Ghi chú và bằng chứng (Comments) | D106: Bằng chứng cho kết quả: câu SQL độc lập chạy trên kho dữ liệu, tham số và kết quả của nó (để so với con số trong câu trả lời). Với tin nhắn nhiều yêu cầu: kết quả từng phần.
A107: Nhiều lượt hỏi | D107: Ca có nhiều lượt: các lượt được đánh số trong cột Các bước, Dữ liệu, Mong đợi và Thực tế, theo cùng thứ tự.

Sheet Compare
A1: Test Case ID | B1: Test Suite | C1: Tiêu đề (Title) | D1: Điều kiện tiên quyết (Pre-conditions) | E1: Các bước (Test Steps) | F1: Dữ liệu kiểm thử (Test Data) | G1: Kết quả mong đợi (Expected Result) | H1: Kết quả thực tế (Actual Result) | I1: Trạng thái (Status) | J1: Lần chạy đầu (First run) | K1: Người thực hiện (Executed by) | L1: Ngày (Date) | M1: Ghi chú và bằng chứng (Comments)
A2: C1 | B2: So sánh và nhiều yêu cầu | C2: Câu hỏi: so sánh doanh thu canada năm 2023 và 2024 | D2: Tài khoản manager, ngôn ngữ vi, hội thoại mới | E2: 1. Gửi câu hỏi lượt 1 và đọc phản hồi 2. Chạy SQL độc lập trên kho dữ liệu (tài khoản chỉ đọc) và so với câu trả lời | F2: 1. so sánh doanh thu canada năm 2023 và 2024 | G2: Lượt 1: Trạng thái cho phép: ok; Số dòng: 2; Biểu đồ: bar; Câu trả lời phải có: Canada, tăng; Có cột: period | H2: Lượt 1: [ok] Doanh thu (Canada): Năm 2023: 5.580.848,05; Năm 2024: 6.231.209,96. Năm 2024 tăng 11,7% so với Năm 2023. (số dòng 2, biểu đồ bar) | I2: Passed | J2: Passed | K2: Kịch bản tự động (scripts/verify_*.py) | L2: 2026-10-14 | M2: SQL kho dữ liệu: SELECT SUM(h.subtotal) FROM sales.salesorderheader h JOIN sales.salesterritory t ON t.territoryid=h.territoryid WHERE h.orderdate>=%s AND h.orderdate<%s AND t.name=%s | tham số: 2023-01-01, 2024-01-01, Canada | kết quả: 1 dòng, đầu: [['5580848.0456']] SQL kho dữ liệu: SELECT SUM(h.subtotal) FROM sales.salesorderheader h JOIN sales.salesterritory t ON t.territoryid=h.territoryid WHERE h.orderdate>=%s AND h.orderdate<%s AND t.name=%s | tham số: 2024-01-01, 2025-01-01, Canada | kết quả: 1 dòng, đầu: [['6231209.9635']] Đối chiếu độc lập (chính): KHỚP 2/2 giá trị. SQL: SELECT 'all',SUM(h.subtotal) FROM sales.salesorderheader h JOIN sales.salesterritory t ON t.territoryid=h.territoryid WHERE h.orderdate>=%s AND h.orderdate<%s AND t.name = ANY(%s) | tham số: 2024-01-01, 2025-01-01, ['Canada']
A3: C2 | B3: So sánh và nhiều yêu cầu | C3: Câu hỏi: so sánh doanh thu Canada và France năm 2023 và 2024 | D3: Tài khoản manager, ngôn ngữ vi, hội thoại mới | E3: 1. Gửi câu hỏi lượt 1 và đọc phản hồi | F3: 1. so sánh doanh thu Canada và France năm 2023 và 2024 | G3: Lượt 1: Trạng thái cho phép: ok; Số dòng: 2; Biểu đồ: bar; Có cột: territory, Năm 2023, Năm 2024 | H3: Lượt 1: [ok] Doanh thu, 2 nhóm, Năm 2023 – Năm 2024. Đứng đầu Năm 2024: Canada (6.231.209,96). Tăng mạnh nhất: France (+145,1%); thấp nhất: Canada (+11,7%). Không nhóm nào giảm. Tổng thay đổi +2.909.752,31; đóng góp nhiều nhất: France (+2.259.390,39, 77,6% tổng thay đổi). (số dòng 2, biểu đồ bar) | I3: Passed | J3: Passed | K3: Kịch bản tự động (scripts/verify_*.py) | L3: 2026-10-14 | M3: Đối chiếu độc lập (chính): KHỚP 6/6 giá trị. SQL: SELECT t.name,SUM(h.subtotal) FROM sales.salesorderheader h JOIN sales.salesterritory t ON t.territoryid=h.territoryid WHERE h.orderdate>=%s AND h.orderdate<%s GROUP BY t.name | tham số: 2024-01-01, 2025-01-01
A4: C3 | B4: So sánh và nhiều yêu cầu | C4: Câu hỏi: compare revenue Q1 2024 and Q1 2025 | D4: Tài khoản manager, ngôn ngữ en, hội thoại mới | E4: 1. Gửi câu hỏi lượt 1 và đọc phản hồi 2. Chạy SQL độc lập trên kho dữ liệu (tài khoản chỉ đọc) và so với câu trả lời | F4: 1. compare revenue Q1 2024 and Q1 2025 | G4: Lượt 1: Trạng thái cho phép: ok; Số dòng: 2; Biểu đồ: bar; Câu trả lời phải có: Q1 2024, Q1 2025, up | H4: Lượt 1: [ok] Revenue: Q1 2024: 7,838,170.11; Q1 2025: 12,830,208.58. Q1 2025 is up 63.7% against Q1 2024. (số dòng 2, biểu đồ bar) | I4: Passed | J4: Passed | K4: Kịch bản tự động (scripts/verify_*.py) | L4: 2026-10-14 | M4: SQL kho dữ liệu: SELECT SUM(h.subtotal) FROM sales.salesorderheader h JOIN sales.salesterritory t ON t.territoryid=h.territoryid WHERE h.orderdate>=%s AND h.orderdate<%s | tham số: 2024-01-01, 2024-04-01 | kết quả: 1 dòng, đầu: [['7838170.1074']] SQL kho dữ liệu: SELECT SUM(h.subtotal) FROM sales.salesorderheader h JOIN sales.salesterritory t ON t.territoryid=h.territoryid WHERE h.orderdate>=%s AND h.orderdate<%s | tham số: 2025-01-01, 2025-04-01 | kết quả: 1 dòng, đầu: [['12830208.5790']] Đối chiếu độc lập (chính): KHỚP 2/2 giá trị. SQL: SELECT 'all',SUM(h.subtotal) FROM sales.salesorderheader h JOIN sales.salesterritory t ON t.territoryid=h.territoryid WHERE h.orderdate>=%s AND h.orderdate<%s | tham số: 2025-01-01, 2025-04-01
A5: C4 | B5: So sánh và nhiều yêu cầu | C5: Câu hỏi: so sánh doanh thu quý 1 và quý 2 năm 2025 | D5: Tài khoản manager, ngôn ngữ vi, hội thoại mới | E5: 1. Gửi câu hỏi lượt 1 và đọc phản hồi 2. Chạy SQL độc lập trên kho dữ liệu (tài khoản chỉ đọc) và so với câu trả lời | F5: 1. so sánh doanh thu quý 1 và quý 2 năm 2025 | G5: Lượt 1: Trạng thái cho phép: ok; Số dòng: 2; Biểu đồ: bar; Câu trả lời phải có: Quý 1/2025, Quý 2/2025 | H5: Lượt 1: [ok] Doanh thu: Quý 1/2025: 12.830.208,58; Quý 2/2025: 7.178.309,78. Quý 2/2025 giảm 44,1% so với Quý 1/2025. (số dòng 2, biểu đồ bar) | I5: Passed | J5: Passed | K5: Kịch bản tự động (scripts/verify_*.py) | L5: 2026-10-14 | M5: SQL kho dữ liệu: SELECT SUM(h.subtotal) FROM sales.salesorderheader h JOIN sales.salesterritory t ON t.territoryid=h.territoryid WHERE h.orderdate>=%s AND h.orderdate<%s | tham số: 2025-01-01, 2025-04-01 | kết quả: 1 dòng, đầu: [['12830208.5790']] SQL kho dữ liệu: SELECT SUM(h.subtotal) FROM sales.salesorderheader h JOIN sales.salesterritory t ON t.territoryid=h.territoryid WHERE h.orderdate>=%s AND h.orderdate<%s | tham số: 2025-04-01, 2025-07-01 | kết quả: 1 dòng, đầu: [['7178309.7823']] Đối chiếu độc lập (chính): KHỚP 2/2 giá trị. SQL: SELECT 'all',SUM(h.subtotal) FROM sales.salesorderheader h JOIN sales.salesterritory t ON t.territoryid=h.territoryid WHERE h.orderdate>=%s AND h.orderdate<%s | tham số: 2025-04-01, 2025-07-01
A6: C5 | B6: So sánh và nhiều yêu cầu | C6: Câu hỏi: so sánh doanh thu tháng 1, tháng 2 và tháng 3 năm 2025 | D6: Tài khoản manager, ngôn ngữ vi, hội thoại mới | E6: 1. Gửi câu hỏi lượt 1 và đọc phản hồi 2. Chạy SQL độc lập trên kho dữ liệu (tài khoản chỉ đọc) và so với câu trả lời | F6: 1. so sánh doanh thu tháng 1, tháng 2 và tháng 3 năm 2025 | G6: Lượt 1: Trạng thái cho phép: ok; Số dòng: 3; Biểu đồ: bar; Câu trả lời phải có: Tháng 1/2025, Tháng 3/2025 | H6: Lượt 1: [ok] Doanh thu: Tháng 1/2025: 4.276.427,72; Tháng 2/2025: 3.565.879,32; Tháng 3/2025: 4.987.901,53. Tháng 3/2025 tăng 16,6% so với Tháng 1/2025. (số dòng 3, biểu đồ bar) | I6: Passed | J6: Passed | K6: Kịch bản tự động (scripts/verify_*.py) | L6: 2026-10-14 | M6: SQL kho dữ liệu: SELECT SUM(h.subtotal) FROM sales.salesorderheader h JOIN sales.salesterritory t ON t.territoryid=h.territoryid WHERE h.orderdate>=%s AND h.orderdate<%s | tham số: 2025-01-01, 2025-02-01 | kết quả: 1 dòng, đầu: [['4276427.7214']] SQL kho dữ liệu: SELECT SUM(h.subtotal) FROM sales.salesorderheader h JOIN sales.salesterritory t ON t.territoryid=h.territoryid WHERE h.orderdate>=%s AND h.orderdate<%s | tham số: 2025-02-01, 2025-03-01 | kết quả: 1 dòng, đầu: [['3565879.3233']] SQL kho dữ liệu: SELECT SUM(h.subtotal) FROM sales.salesorderheader h JOIN sales.salesterritory t ON t.territoryid=h.territoryid WHERE h.orderdate>=%s AND h.orderdate<%s | tham số: 2025-03-01, 2025-04-01 | kết quả: 1 dòng, đầu: [['4987901.5343']] Đối chiếu độc lập (chính): KHỚP 3/3 giá trị. SQL: SELECT 'all',SUM(h.subtotal) FROM sales.salesorderheader h JOIN sales.salesterritory t ON t.territoryid=h.territoryid WHERE h.orderdate>=%s AND h.orderdate<%s | tham số: 2025-03-01, 2025-04-01
A7: C6 | B7: So sánh và nhiều yêu cầu | C7: Câu hỏi: so sánh sản lượng năm 2023 và 2024 | D7: Tài khoản manager, ngôn ngữ vi, hội thoại mới | E7: 1. Gửi câu hỏi lượt 1 và đọc phản hồi | F7: 1. so sánh sản lượng năm 2023 và 2024 | G7: Lượt 1: Trạng thái cho phép: ok; Số dòng: 2; Biểu đồ: bar; Câu trả lời phải có: Sản lượng | H7: Lượt 1: [ok] Sản lượng: Năm 2023: 1.300.267,00; Năm 2024: 1.896.377,00. Năm 2024 tăng 45,8% so với Năm 2023. (số dòng 2, biểu đồ bar) | I7: Passed | J7: Passed | K7: Kịch bản tự động (scripts/verify_*.py) | L7: 2026-10-14 | M7: Đối chiếu độc lập (chính): KHỚP 2/2 giá trị. SQL: WITH terminal AS (SELECT DISTINCT ON (workorderid) workorderid,locationid FROM production.workorderrouting ORDER BY workorderid,operationsequence DESC,locationid),fact AS (SELECT w.*,f.factory_id AS fid,COALESCE(f.name,'Unassigned') AS fname FROM production.workorder w LEFT JOIN terminal t ON t.workorderid=w.workorderid LEFT JOIN acbi_demo.location_factory lf ON lf.locationid=t.locationid LEFT JOIN acbi_demo.factory f ON f.factory_id=lf.factory_id) SELECT 'all',SUM(orderqty-scrappedqty) FROM fact WHERE enddate>=%s AND enddate<%s | tham số: 2024-01-01, 2025-01-01
A8: C7 | B8: So sánh và nhiều yêu cầu | C8: Câu hỏi: so sánh tỷ lệ phế phẩm theo nhà máy năm 2023 và 2024 | D8: Tài khoản manager, ngôn ngữ vi, hội thoại mới | E8: 1. Gửi câu hỏi lượt 1 và đọc phản hồi | F8: 1. so sánh tỷ lệ phế phẩm theo nhà máy năm 2023 và 2024 | G8: Lượt 1: Trạng thái cho phép: ok; Số dòng: 2, 4; Biểu đồ: bar; Có cột: factory, Năm 2023, Năm 2024 | H8: Lượt 1: [ok] Tỷ lệ phế phẩm, 3 nhóm, Năm 2023 – Năm 2024. Đứng đầu Năm 2024: Unassigned (0,3%). Tăng mạnh nhất: Unassigned (+30,1%); thấp nhất: Factory A (+11,7%). Không nhóm nào giảm. Tổng thay đổi +0,1%; đóng góp nhiều nhất: Unassigned (+0,1%, 55,6% tổng thay đổi). (số dòng 3, biểu đồ bar) | I8: Passed | J8: Passed | K8: Kịch bản tự động (scripts/verify_*.py) | L8: 2026-10-14 | M8: Đối chiếu độc lập (chính): KHỚP 9/9 giá trị. SQL: WITH terminal AS (SELECT DISTINCT ON (workorderid) workorderid,locationid FROM production.workorderrouting ORDER BY workorderid,operationsequence DESC,locationid),fact AS (SELECT w.*,f.factory_id AS fid,COALESCE(f.name,'Unassigned') AS fname FROM production.workorder w LEFT JOIN terminal t ON t.workorderid=w.workorderid LEFT JOIN acbi_demo.location_factory lf ON lf.locationid=t.locationid LEFT JOIN acbi_demo.factory f ON f.factory_id=lf.factory_id) SELECT fname,SUM(scrappedqty)::numeric/NULLIF(SUM(orderqty),0) FROM fact WHERE enddate>=%s AND enddate<%s GROUP BY fname | tham số: 2024-01-01, 2025-01-01
A9: C8 | B9: So sánh và nhiều yêu cầu | C9: Câu hỏi: so sánh doanh thu theo danh mục sản phẩm năm 2023 và 2024 | D9: Tài khoản manager, ngôn ngữ vi, hội thoại mới | E9: 1. Gửi câu hỏi lượt 1 và đọc phản hồi | F9: 1. so sánh doanh thu theo danh mục sản phẩm năm 2023 và 2024 | G9: Lượt 1: Trạng thái cho phép: ok; Số dòng: 3, 6; Biểu đồ: bar; Có cột: category | H9: Lượt 1: [ok] Doanh thu, 4 nhóm, Năm 2023 – Năm 2024. Đứng đầu Năm 2024: Bikes (36.313.572,48). Tăng mạnh nhất: Accessories (+574,8%); thấp nhất: Bikes (+33,7%). Không nhóm nào giảm. Tổng thay đổi +12.066.967,56; đóng góp nhiều nhất: Bikes (+9.161.021,41, 75,9% tổng thay đ… (số dòng 4, biểu đồ bar) | I9: Passed | J9: Passed | K9: Kịch bản tự động (scripts/verify_*.py) | L9: 2026-10-14 | M9: Đối chiếu độc lập (chính): chưa đối chiếu (chiều so sánh (ví dụ ngành hàng) không có truy vấn đối chiếu độc lập)
A10: C9 | B10: So sánh và nhiều yêu cầu | C10: Câu hỏi: so sánh doanh thu năm 2023 và 2024 theo tháng | D10: Tài khoản manager, ngôn ngữ vi, hội thoại mới | E10: 1. Gửi câu hỏi lượt 1 và đọc phản hồi | F10: 1. so sánh doanh thu năm 2023 và 2024 theo tháng | G10: Lượt 1: Trạng thái cho phép: ok; Số dòng: 24; Biểu đồ: line | H10: Lượt 1: [ok] Doanh thu từ 01/01/2023 đến 31/12/2024: 24 nhóm. Cao nhất là tháng 06/2024 (5.063.798,38), thấp nhất là tháng 02/2023 (1.449.883,20). Từ tháng 01/2023 đến tháng 12/2024, doanh thu tăng 96,6%. Đây là kết quả cho cả khoảng thời gian liền nhau bạn nêu. (số dòng 24, biểu đồ line) | I10: Passed | J10: Passed | K10: Kịch bản tự động (scripts/verify_*.py) | L10: 2026-10-14 | M10: Đối chiếu độc lập (chính): KHỚP 24/24 giá trị. SQL: SELECT date_trunc('month',h.orderdate)::date,SUM(h.subtotal) FROM sales.salesorderheader h JOIN sales.salesterritory t ON t.territoryid=h.territoryid WHERE h.orderdate>=%s AND h.orderdate<%s GROUP BY date_trunc('month',h.orderdate)::date | tham số: 2023-01-01, 2025-01-01
A11: C10 | B11: So sánh và nhiều yêu cầu | C11: Câu hỏi: so sánh doanh thu năm 2023 và 2024 bằng biểu đồ tròn | D11: Tài khoản manager, ngôn ngữ vi, hội thoại mới | E11: 1. Gửi câu hỏi lượt 1 và đọc phản hồi | F11: 1. so sánh doanh thu năm 2023 và 2024 bằng biểu đồ tròn | G11: Lượt 1: Trạng thái cho phép: ok; Số dòng: 2; Biểu đồ: pie | H11: Lượt 1: [ok] Doanh thu: Năm 2023: 31.604.921,95; Năm 2024: 43.671.889,50. Năm 2024 tăng 38,2% so với Năm 2023. (số dòng 2, biểu đồ pie) | I11: Passed | J11: Passed | K11: Kịch bản tự động (scripts/verify_*.py) | L11: 2026-10-14 | M11: Đối chiếu độc lập (chính): KHỚP 2/2 giá trị. SQL: SELECT 'all',SUM(h.subtotal) FROM sales.salesorderheader h JOIN sales.salesterritory t ON t.territoryid=h.territoryid WHERE h.orderdate>=%s AND h.orderdate<%s | tham số: 2024-01-01, 2025-01-01
A12: C11 | B12: So sánh và nhiều yêu cầu | C12: Câu hỏi: so sánh doanh thu của Wakanda năm 2023 và 2024 | D12: Tài khoản manager, ngôn ngữ vi, hội thoại mới | E12: 1. Gửi câu hỏi lượt 1 và đọc phản hồi | F12: 1. so sánh doanh thu của Wakanda năm 2023 và 2024 | G12: Lượt 1: Trạng thái cho phép: needs_clarification | H12: Lượt 1: [needs_clarification] Tôi không nhận ra khu vực này. Các khu vực có dữ liệu: Australia, Canada, Central, France, Germany, Northeast, Northwest, Southeast, Southwest, United Kingdom. (số dòng 0, biểu đồ không) | I12: Passed | J12: Passed | K12: Kịch bản tự động (scripts/verify_*.py) | L12: 2026-10-14 | M12: (kiểm tra trạng thái và nội dung, không có số để đối chiếu)
... A48: M17 | B48: So sánh và nhiều yêu cầu | C48: Câu hỏi: Doanh thu năm 2024 theo khu vực và tỷ lệ phế phẩm năm 2024 | D48: Tài khoản manager, ngôn ngữ vi, hội thoại mới, các lượt trong cùng một hội thoại | E48: 1. Gửi câu hỏi lượt 1 và đọc phản hồi 2. Gửi câu hỏi lượt 2 và đọc phản hồi | F48: 1. Doanh thu năm 2024 theo khu vực và tỷ lệ phế phẩm năm 2024 2. còn Canada thì sao? | G48: Lượt 1: Trạng thái cho phép: ok; Số phần: {'status': 'ok'} Lượt 2: Trạng thái cho phép: ok | H48: Lượt 1: [ok] Doanh thu từ 01/01/2024 đến 31/12/2024: 10 nhóm. Cao nhất là Southwest (9.121.931,65), thấp nhất là Southeast (2.399.947,38). Southwest chiếm 20,9% trong tổng 43.671.889,50. (số dòng 10, biểu đồ bar) Lượt 2: [ok] Doanh thu của Canada từ 01/01/2024 đến 31/12/2024: 6.231.209,96 đơn vị tiền tệ nguồn. (số dòng 1, biểu đồ kpi_card) | I48: Passed | J48: Passed | K48: Kịch bản tự động (scripts/verify_*.py) | L48: 2026-10-14 | M48: Các phần của tin nhắn: 2. Tỷ lệ phế phẩm năm 2024: [ok] Tỷ lệ phế phẩm từ 01/01/2024 đến 31/12/2024: 0,29%. Đối chiếu độc lập (chính): KHỚP 10/10 giá trị. SQL: SELECT t.name,SUM(h.subtotal) FROM sales.salesorderheader h JOIN sales.salesterritory t ON t.territoryid=h.territoryid WHERE h.orderdate>=%s AND h.orderdate<%s GROUP BY t.name | tham số: 2024-01-01, 2025-01-01 Đối chiếu độc lập (2. Tỷ lệ phế phẩm năm 2024): KHỚP 1/1 giá trị. SQL: WITH terminal AS (SELECT DISTINCT ON (workorderid) workorderid,locationid FROM production.workorderrouting ORDER BY workorderid,operationsequence DESC,locationid),fact AS (SELECT w.*,f.factory_id AS fid,COALESCE(f.name,'Unassigned') AS fname FROM production.workorder w LEFT JOIN terminal t ON t.workorderid=w.workorderid LEFT JOIN acbi_demo.location_factory lf ON lf.locationid=t.locationid LEFT JOIN acbi_demo.factory f ON f.factory_id=lf.factory_id) SELECT 'all',SUM(scrappedqty)::numeric/NULLIF(SUM(orderqty),0) FROM fact WHERE enddate>=%s AND enddate<%s | tham số: 2024-01-01, 2025-01-01 Đối chiếu độc lập (chính): KHỚP 1/1 giá trị. SQL: SELECT 'all',SUM(h.subtotal) FROM sales.salesorderheader h JOIN sales.salesterritory t ON t.territoryid=h.territoryid WHERE h.orderdate>=%s AND h.orderdate<%s AND t.name = ANY(%s) | tham số: 2024-01-01, 2025-01-01, ['Canada']
A51: Cách đọc các cột
A52: Test Case ID | D52: Mã của ca kiểm thử (ví dụ R01, H12, M3). Dùng mã này để tìm lại ca trong kịch bản chạy và trong báo cáo.
A53: Test Suite | D53: Nhóm (bộ) kiểm thử mà ca thuộc về.
A54: Tiêu đề (Title) | D54: Tên ngắn của ca: câu hỏi chính được đem ra thử.
A55: Điều kiện tiên quyết (Pre-conditions) | D55: Cần có gì trước khi chạy: đăng nhập bằng vai trò nào, ngôn ngữ nào, hội thoại mới hay nhiều lượt trong cùng một hội thoại.
A56: Các bước (Test Steps) | D56: Việc đã làm, theo thứ tự: gửi từng câu hỏi, rồi (nếu có) chạy một câu SQL độc lập trên kho dữ liệu để đối chiếu số.
A57: Dữ liệu kiểm thử (Test Data) | D57: Nguyên văn các câu hỏi đã gửi cho hệ thống.
A58: Kết quả mong đợi (Expected Result) | D58: Điều hệ thống phải làm để ca được coi là đạt: trạng thái cho phép (ok = có số liệu, needs_clarification = hỏi lại, denied = từ chối, no_data = không có dữ liệu), số dòng, loại biểu đồ, cụm chữ phải có hoặc không được có, và số có khớp kho dữ liệu hay không.
A59: Kết quả thực tế (Actual Result) | D59: Điều hệ thống đã trả về: trạng thái, câu trả lời nguyên văn (cắt ngắn), số dòng của bảng và loại biểu đồ.
A60: Trạng thái (Status) | D60: Passed = đạt mọi yêu cầu. Failed = có yêu cầu sai. Blocked = không chạy được vì dịch vụ AI báo bận (hết hạn mức), không phải lỗi của hệ thống. Not Run = chưa chạy.
A61: Lần chạy đầu (First run) | D61: Kết quả ở lần chạy đầu tiên. Ca báo Blocked ở lần đầu được chạy lại cho đến khi không còn báo bận, nên cột Trạng thái là kết quả cuối còn cột này giữ dấu vết lần đầu.
A62: Người thực hiện / Ngày | D62: Ai hoặc cái gì chạy ca (kịch bản tự động) và chạy ngày nào.
A63: Ghi chú và bằng chứng (Comments) | D63: Bằng chứng cho kết quả: câu SQL độc lập chạy trên kho dữ liệu, tham số và kết quả của nó (để so với con số trong câu trả lời). Với tin nhắn nhiều yêu cầu: kết quả từng phần.
A64: Các phần của tin nhắn | D64: Một tin nhắn có nhiều yêu cầu được hệ thống tách thành các phần đánh số; kết quả từng phần nằm trong cột Ghi chú.

Sheet Phân quyền
A1: Test Case ID | B1: Test Suite | C1: Tiêu đề (Title) | D1: Điều kiện tiên quyết (Pre-conditions) | E1: Các bước (Test Steps) | F1: Dữ liệu kiểm thử (Test Data) | G1: Kết quả mong đợi (Expected Result) | H1: Kết quả thực tế (Actual Result) | I1: Trạng thái (Status) | J1: Lần chạy đầu (First run) | K1: Người thực hiện (Executed by) | L1: Ngày (Date) | M1: Ghi chú và bằng chứng (Comments)
A2: P01-manager | B2: Phân quyền theo vai trò | C2: manager hỏi: Doanh thu năm 2024 | D2: Đăng nhập demo bằng manager; hội thoại mới | E2: 1. Gửi câu hỏi 2. Ghi trạng thái, số dòng, đường xử lý | F2: Doanh thu năm 2024 (Đường xử lý: Mẫu (Structured Intent)) | G2: Trạng thái thuộc: no_data, ok; bị từ chối hoặc hỏi lại thì không có dòng dữ liệu | H2: [ok] Doanh thu từ 01/01/2024 đến 31/12/2024: 43.671.889,50 đơn vị tiền tệ nguồn. (số dòng 1, đường structured_intent) | I2: Passed | J2: Passed | K2: Kịch bản tự động (scripts/verify_*.py) | L2: 2026-10-14 | M2: Không phát hiện dữ liệu ngoài quyền
A3: P01-sales | B3: Phân quyền theo vai trò | C3: sales hỏi: Doanh thu năm 2024 | D3: Đăng nhập demo bằng sales; hội thoại mới | E3: 1. Gửi câu hỏi 2. Ghi trạng thái, số dòng, đường xử lý | F3: Doanh thu năm 2024 (Đường xử lý: Mẫu (Structured Intent)) | G3: Trạng thái thuộc: no_data, ok; bị từ chối hoặc hỏi lại thì không có dòng dữ liệu | H3: [ok] Doanh thu từ 01/01/2024 đến 31/12/2024: 43.671.889,50 đơn vị tiền tệ nguồn. (số dòng 1, đường structured_intent) | I3: Passed | J3: Passed | K3: Kịch bản tự động (scripts/verify_*.py) | L3: 2026-10-14 | M3: Không phát hiện dữ liệu ngoài quyền
A4: P01-production_a | B4: Phân quyền theo vai trò | C4: production_a hỏi: Doanh thu năm 2024 | D4: Đăng nhập demo bằng production_a; hội thoại mới | E4: 1. Gửi câu hỏi 2. Ghi trạng thái, số dòng, đường xử lý | F4: Doanh thu năm 2024 (Đường xử lý: Mẫu (Structured Intent)) | G4: Trạng thái thuộc: denied; bị từ chối hoặc hỏi lại thì không có dòng dữ liệu | H4: [denied] Data is outside your access scope (số dòng 0, đường không có SQL) | I4: Passed | J4: Passed | K4: Kịch bản tự động (scripts/verify_*.py) | L4: 2026-10-14 | M4: Không phát hiện dữ liệu ngoài quyền
A5: P01-it_admin | B5: Phân quyền theo vai trò | C5: it_admin hỏi: Doanh thu năm 2024 | D5: Đăng nhập demo bằng it_admin; hội thoại mới | E5: 1. Gửi câu hỏi 2. Ghi trạng thái, số dòng, đường xử lý | F5: Doanh thu năm 2024 (Đường xử lý: Mẫu (Structured Intent)) | G5: Trạng thái thuộc: denied; bị từ chối hoặc hỏi lại thì không có dòng dữ liệu | H5: [denied] Business data is outside your scope (số dòng 0, đường không có SQL) | I5: Passed | J5: Passed | K5: Kịch bản tự động (scripts/verify_*.py) | L5: 2026-10-14 | M5: Không phát hiện dữ liệu ngoài quyền
A6: P02-manager | B6: Phân quyền theo vai trò | C6: manager hỏi: Doanh thu theo tuần trong tháng 3 năm 2025 | D6: Đăng nhập demo bằng manager; hội thoại mới | E6: 1. Gửi câu hỏi 2. Ghi trạng thái, số dòng, đường xử lý | F6: Doanh thu theo tuần trong tháng 3 năm 2025 (Đường xử lý: RAG Text-to-SQL) | G6: Trạng thái thuộc: no_data, ok; bị từ chối hoặc hỏi lại thì không có dòng dữ liệu | H6: [ok] Doanh thu từ 01/03/2025 đến 31/03/2025: 6 nhóm. Cao nhất là 24/03/2025 (3.767.708,93), thấp nhất là 31/03/2025 (34.544,95). Từ 24/02/2025 đến 31/03/2025, doanh thu giảm 70,9%. (số dòng 6, đường rag_text_to_sql) | I6: Passed | J6: Passed | K6: Kịch bản tự động (scripts/verify_*.py) | L6: 2026-10-14 | M6: Không phát hiện dữ liệu ngoài quyền
A7: P02-it_admin | B7: Phân quyền theo vai trò | C7: it_admin hỏi: Doanh thu theo tuần trong tháng 3 năm 2025 | D7: Đăng nhập demo bằng it_admin; hội thoại mới | E7: 1. Gửi câu hỏi 2. Ghi trạng thái, số dòng, đường xử lý | F7: Doanh thu theo tuần trong tháng 3 năm 2025 (Đường xử lý: RAG Text-to-SQL) | G7: Trạng thái thuộc: denied; bị từ chối hoặc hỏi lại thì không có dòng dữ liệu | H7: [denied] Business data is outside your scope (số dòng 0, đường không có SQL) | I7: Passed | J7: Passed | K7: Kịch bản tự động (scripts/verify_*.py) | L7: 2026-10-14 | M7: Không phát hiện dữ liệu ngoài quyền
A8: P03-manager | B8: Phân quyền theo vai trò | C8: manager hỏi: Sản lượng Factory A năm 2024 | D8: Đăng nhập demo bằng manager; hội thoại mới | E8: 1. Gửi câu hỏi 2. Ghi trạng thái, số dòng, đường xử lý | F8: Sản lượng Factory A năm 2024 (Đường xử lý: Mẫu (Structured Intent)) | G8: Trạng thái thuộc: no_data, ok; bị từ chối hoặc hỏi lại thì không có dòng dữ liệu | H8: [ok] Sản lượng của Factory A từ 01/01/2024 đến 31/12/2024: 355.197,00 sản phẩm. (số dòng 1, đường structured_intent) | I8: Passed | J8: Passed | K8: Kịch bản tự động (scripts/verify_*.py) | L8: 2026-10-14 | M8: Không phát hiện dữ liệu ngoài quyền
A9: P03-sales | B9: Phân quyền theo vai trò | C9: sales hỏi: Sản lượng Factory A năm 2024 | D9: Đăng nhập demo bằng sales; hội thoại mới | E9: 1. Gửi câu hỏi 2. Ghi trạng thái, số dòng, đường xử lý | F9: Sản lượng Factory A năm 2024 (Đường xử lý: Mẫu (Structured Intent)) | G9: Trạng thái thuộc: denied; bị từ chối hoặc hỏi lại thì không có dòng dữ liệu | H9: [denied] Data is outside your access scope (số dòng 0, đường không có SQL) | I9: Passed | J9: Passed | K9: Kịch bản tự động (scripts/verify_*.py) | L9: 2026-10-14 | M9: Không phát hiện dữ liệu ngoài quyền
A10: P03-production_a | B10: Phân quyền theo vai trò | C10: production_a hỏi: Sản lượng Factory A năm 2024 | D10: Đăng nhập demo bằng production_a; hội thoại mới | E10: 1. Gửi câu hỏi 2. Ghi trạng thái, số dòng, đường xử lý | F10: Sản lượng Factory A năm 2024 (Đường xử lý: Mẫu (Structured Intent)) | G10: Trạng thái thuộc: no_data, ok; bị từ chối hoặc hỏi lại thì không có dòng dữ liệu | H10: [ok] Sản lượng của Factory A từ 01/01/2024 đến 31/12/2024: 355.197,00 sản phẩm. (số dòng 1, đường structured_intent) | I10: Passed | J10: Passed | K10: Kịch bản tự động (scripts/verify_*.py) | L10: 2026-10-14 | M10: Không phát hiện dữ liệu ngoài quyền
A11: P03-it_admin | B11: Phân quyền theo vai trò | C11: it_admin hỏi: Sản lượng Factory A năm 2024 | D11: Đăng nhập demo bằng it_admin; hội thoại mới | E11: 1. Gửi câu hỏi 2. Ghi trạng thái, số dòng, đường xử lý | F11: Sản lượng Factory A năm 2024 (Đường xử lý: Mẫu (Structured Intent)) | G11: Trạng thái thuộc: denied; bị từ chối hoặc hỏi lại thì không có dòng dữ liệu | H11: [denied] Business data is outside your scope (số dòng 0, đường không có SQL) | I11: Passed | J11: Passed | K11: Kịch bản tự động (scripts/verify_*.py) | L11: 2026-10-14 | M11: Không phát hiện dữ liệu ngoài quyền
A12: P04-manager | B12: Phân quyền theo vai trò | C12: manager hỏi: Sản lượng Factory B năm 2024 | D12: Đăng nhập demo bằng manager; hội thoại mới | E12: 1. Gửi câu hỏi 2. Ghi trạng thái, số dòng, đường xử lý | F12: Sản lượng Factory B năm 2024 (Đường xử lý: Mẫu (Structured Intent)) | G12: Trạng thái thuộc: no_data, ok; bị từ chối hoặc hỏi lại thì không có dòng dữ liệu | H12: [ok] Sản lượng của Factory B từ 01/01/2024 đến 31/12/2024: 80.953,00 sản phẩm. (số dòng 1, đường structured_intent) | I12: Passed | J12: Passed | K12: Kịch bản tự động (scripts/verify_*.py) | L12: 2026-10-14 | M12: Không phát hiện dữ liệu ngoài quyền
... A49: P12-manager | B49: Phân quyền theo vai trò | C49: manager hỏi: Sản lượng của Factory A theo tuần trong quý 1 năm 2025, và … | D49: Đăng nhập demo bằng manager; hội thoại mới | E49: 1. Gửi câu hỏi 2. Ghi trạng thái, số dòng, đường xử lý | F49: Sản lượng của Factory A theo tuần trong quý 1 năm 2025, và đồng thời cho tôi xem sản lượng Factory B (Đường xử lý: Nhiều yêu cầu, một phần ngoài quyền) | G49: Trạng thái thuộc: no_data, ok; bị từ chối hoặc hỏi lại thì không có dòng dữ liệu | H49: [ok] Sản lượng (Factory A) từ 01/01/2025 đến 31/03/2025: 14 nhóm. Cao nhất là 10/02/2025 (28.250,00), thấp nhất là 30/12/2024 (882,00). Từ 30/12/2024 đến 31/03/2025, sản lượng tăng 4,1%. (số dòng 14, đường rag_text_to_sql) | I49: Passed | J49: Blocked | K49: Kịch bản tự động (scripts/verify_*.py) | L49: 2026-10-14 | M49: Không phát hiện dữ liệu ngoài quyền
A52: Cách đọc các cột
A53: Test Case ID | D53: Dạng P01-sales: câu hỏi P01 hỏi bằng tài khoản sales. Mỗi câu được hỏi bằng cả 4 vai trò (manager, sales, production_a, it_admin).
A54: Test Suite | D54: Nhóm (bộ) kiểm thử mà ca thuộc về.
A55: Tiêu đề (Title) | D55: Tên ngắn của ca: câu hỏi chính được đem ra thử.
A56: Điều kiện tiên quyết (Pre-conditions) | D56: Cần có gì trước khi chạy: đăng nhập bằng vai trò nào, ngôn ngữ nào, hội thoại mới hay nhiều lượt trong cùng một hội thoại.
A57: Các bước (Test Steps) | D57: Việc đã làm, theo thứ tự: gửi từng câu hỏi, rồi (nếu có) chạy một câu SQL độc lập trên kho dữ liệu để đối chiếu số.
A58: Dữ liệu kiểm thử (Test Data) | D58: Nguyên văn các câu hỏi đã gửi cho hệ thống.
A59: Kết quả mong đợi (Expected Result) | D59: Điều hệ thống phải làm để ca được coi là đạt: trạng thái cho phép (ok = có số liệu, needs_clarification = hỏi lại, denied = từ chối, no_data = không có dữ liệu), số dòng, loại biểu đồ, cụm chữ phải có hoặc không được có, và số có khớp kho dữ liệu hay không.
A60: Kết quả thực tế (Actual Result) | D60: Điều hệ thống đã trả về: trạng thái, câu trả lời nguyên văn (cắt ngắn), số dòng của bảng và loại biểu đồ.
A61: Trạng thái (Status) | D61: Passed = vai trò nhận đúng thứ được phép (có số liệu nếu được xem, bị từ chối nếu không được xem) và khi bị từ chối thì không có dòng dữ liệu nào lọt ra. Failed = có dữ liệu ngoài quyền hoặc trạng thái sai.
A62: Ý nghĩa của bộ này | D62: Chứng minh phân quyền do backend cưỡng chế trên cả đường truy vấn mẫu (Structured Intent) lẫn đường AI sinh SQL (RAG), kể cả với câu tấn công như bỏ qua hướng dẫn hoặc gõ thẳng SQL.

Sheet Truy vết yêu cầu
A1: Yêu cầu chất lượng (tài liệu mục 1.2) | B1: Cách kiểm chứng | C1: Bộ kiểm thử | D1: Số ca | E1: Passed | F1: Ghi chú
A2: Chính xác | B2: Đối chiếu từng con số với kho dữ liệu bằng SQL độc lập; câu bẫy ảo giác phải bị từ chối hoặc hỏi lại | C2: RAG, Hard, Compare | D2: =COUNTA(RAG!A2:A25)+COUNTA(Hard!A2:A91)+COUNTA(Compare!A2:A48) | E2: =COUNTIF(RAG!I2:I25,"Passed")+COUNTIF(Hard!I2:I91,"Passed")+COUNTIF(Compare!I2:I48,"Passed") | F2: Một số ca Hard chỉ kiểm tra trạng thái và nội dung (không có số để đối chiếu)
A3: Bảo mật (phân quyền) | B3: 4 vai trò x 12 câu trên cả đường mẫu, RAG, dự báo, câu tấn công; bị từ chối thì không có dòng dữ liệu | C3: Phân quyền | D3: =COUNTA('Phân quyền'!A2:A49) | E3: =COUNTIF('Phân quyền'!I2:I49,"Passed") | F3: Chưa có pentest độc lập
A4: Truy vết | B4: Mỗi câu trả lời có nguồn, SQL, tham số, thời điểm truy xuất | C4: RAG, Hard, Compare (nội dung câu trả lời) | F4: Kiểm tra giao diện qua ảnh chụp; chưa có ca kiểm thử riêng cho nội dung 'Nguồn dữ liệu và cách tính'
A5: Dễ dùng | B5: Câu hỏi tiếng Việt tự nhiên, cách hỏi biến thể, câu mơ hồ được hỏi lại | C5: Hard (cách hỏi biến thể, câu mơ hồ) | F5: Chưa có đánh giá với người dùng thật
A6: Hiệu năng (95% dưới 15 giây) | B6: Đo tải 5 người dùng đồng thời | C6: Đo tải | D6: ='Đo tải'!J2 | E6: ='Đo tải'!J5 | F6: Xem sheet 'Đo tải' (số đo, không phải ca kiểm thử)
A7: Dự báo | B7: Backtest cuốn chiếu so với phương pháp đơn giản | C7: Backtest dự báo | F7: Chỉ 11 đến 12 gốc dự báo; xem kết luận trong sheet
A10: Cách đọc các cột
A11: Yêu cầu chất lượng | B11: Các mục tiêu chất lượng trong tài liệu giải pháp: chính xác, bảo mật, truy vết, dễ dùng, hiệu năng.
A12: Cách kiểm chứng | B12: Việc làm để chứng minh yêu cầu được đáp ứng.
A13: Bộ kiểm thử / Số ca / Passed | B13: Bộ kiểm thử liên quan, số ca và số ca đạt (tính bằng công thức từ các sheet chi tiết). Ô trống nghĩa là yêu cầu đó chưa có ca kiểm thử riêng.
A14: Ghi chú | B14: Chỗ còn thiếu hoặc điều cần lưu ý khi đọc kết quả.

Sheet Đối chiếu độc lập
A1: Test Case ID | B1: Bộ | C1: Câu hỏi | D1: Phạm vi | E1: Kết quả đối chiếu | F1: Số giá trị đã so | G1: Số giá trị lệch | H1: Chi tiết lệch | I1: SQL độc lập trên kho dữ liệu | J1: Tham số | K1: Ghi chú
A2: R01 | B2: rag | C2: Doanh thu theo tuần trong tháng 3 năm 2025 | D2: chính | E2: Khớp | F2: 6 | G2: 0 | I2: SELECT date_trunc('week',h.orderdate)::date,SUM(h.subtotal) FROM sales.salesorderheader h JOIN sales.salesterritory t ON t.territoryid=h.territoryid WHERE h.orderdate>=%s AND h.orderdate<%s GROUP BY date_trunc('week',h.orderdate)::date | J2: 2025-03-01, 2025-04-01 | K2: 6 nhóm trong kho dữ liệu
A3: R02 | B3: rag | C3: Sản lượng theo tuần trong quý 1 năm 2025 | D3: chính | E3: Khớp | F3: 14 | G3: 0 | I3: WITH terminal AS (SELECT DISTINCT ON (workorderid) workorderid,locationid FROM production.workorderrouting ORDER BY workorderid,operationsequence DESC,locationid),fact AS (SELECT w.*,f.factory_id AS fid,COALESCE(f.name,'Unassigned') AS fname FROM production.workorder w LEFT JOIN terminal t ON t.workorderid=w.workorderid LEFT JOIN acbi_demo.location_factory lf ON lf.locationid=t.locationid LEFT JOIN acbi_demo.factory f ON f.factory_id=lf.factory_id) SELECT date_trunc('week',enddate)::date,SUM(orderqty-scrappedqty) FROM fact WHERE enddate>=%s AND enddate<%s GROUP BY date_trunc('week',enddate)::date | J3: 2025-01-01, 2025-04-01 | K3: 14 nhóm trong kho dữ liệu
A4: R03 | B4: rag | C4: Sản lượng theo ngày trong tháng 3 năm 2025 | D4: chính | E4: Khớp | F4: 31 | G4: 0 | I4: WITH terminal AS (SELECT DISTINCT ON (workorderid) workorderid,locationid FROM production.workorderrouting ORDER BY workorderid,operationsequence DESC,locationid),fact AS (SELECT w.*,f.factory_id AS fid,COALESCE(f.name,'Unassigned') AS fname FROM production.workorder w LEFT JOIN terminal t ON t.workorderid=w.workorderid LEFT JOIN acbi_demo.location_factory lf ON lf.locationid=t.locationid LEFT JOIN acbi_demo.factory f ON f.factory_id=lf.factory_id) SELECT enddate::date,SUM(orderqty-scrappedqty) FROM fact WHERE enddate>=%s AND enddate<%s GROUP BY enddate::date | J4: 2025-03-01, 2025-04-01 | K4: 31 nhóm trong kho dữ liệu
A5: R04 | B5: rag | C5: Sản lượng của Factory A theo từng ngày trong tháng 3 năm 2025 | D5: chính | E5: Khớp | F5: 21 | G5: 0 | I5: WITH terminal AS (SELECT DISTINCT ON (workorderid) workorderid,locationid FROM production.workorderrouting ORDER BY workorderid,operationsequence DESC,locationid),fact AS (SELECT w.*,f.factory_id AS fid,COALESCE(f.name,'Unassigned') AS fname FROM production.workorder w LEFT JOIN terminal t ON t.workorderid=w.workorderid LEFT JOIN acbi_demo.location_factory lf ON lf.locationid=t.locationid LEFT JOIN acbi_demo.factory f ON f.factory_id=lf.factory_id) SELECT enddate::date,SUM(orderqty-scrappedqty) FROM fact WHERE enddate>=%s AND enddate<%s AND fid=%s GROUP BY enddate::date | J5: 2025-03-01, 2025-04-01, 1 | K5: 21 nhóm trong kho dữ liệu
A6: R05 | B6: rag | C6: Tỷ lệ lỗi theo ngày trong tháng 3 năm 2025 | D6: chính | E6: Khớp | F6: 31 | G6: 0 | I6: WITH terminal AS (SELECT DISTINCT ON (workorderid) workorderid,locationid FROM production.workorderrouting ORDER BY workorderid,operationsequence DESC,locationid),fact AS (SELECT w.*,f.factory_id AS fid,COALESCE(f.name,'Unassigned') AS fname FROM production.workorder w LEFT JOIN terminal t ON t.workorderid=w.workorderid LEFT JOIN acbi_demo.location_factory lf ON lf.locationid=t.locationid LEFT JOIN acbi_demo.factory f ON f.factory_id=lf.factory_id) SELECT enddate::date,SUM(scrappedqty)::numeric/NULLIF(SUM(orderqty),0) FROM fact WHERE enddate>=%s AND enddate<%s GROUP BY enddate::date | J6: 2025-03-01, 2025-04-01 | K6: 31 nhóm trong kho dữ liệu
A7: R06 | B7: rag | C7: Tỷ lệ lỗi theo tuần trong quý 1 năm 2025 | D7: chính | E7: Khớp | F7: 14 | G7: 0 | I7: WITH terminal AS (SELECT DISTINCT ON (workorderid) workorderid,locationid FROM production.workorderrouting ORDER BY workorderid,operationsequence DESC,locationid),fact AS (SELECT w.*,f.factory_id AS fid,COALESCE(f.name,'Unassigned') AS fname FROM production.workorder w LEFT JOIN terminal t ON t.workorderid=w.workorderid LEFT JOIN acbi_demo.location_factory lf ON lf.locationid=t.locationid LEFT JOIN acbi_demo.factory f ON f.factory_id=lf.factory_id) SELECT date_trunc('week',enddate)::date,SUM(scrappedqty)::numeric/NULLIF(SUM(orderqty),0) FROM fact WHERE enddate>=%s AND enddate<%s GROUP BY date_trunc('week',enddate)::date | J7: 2025-01-01, 2025-04-01 | K7: 14 nhóm trong kho dữ liệu
A8: R07 | B8: rag | C8: Doanh thu của Canada theo tuần trong tháng 3 năm 2025 | D8: chính | E8: Khớp | F8: 6 | G8: 0 | I8: SELECT date_trunc('week',h.orderdate)::date,SUM(h.subtotal) FROM sales.salesorderheader h JOIN sales.salesterritory t ON t.territoryid=h.territoryid WHERE h.orderdate>=%s AND h.orderdate<%s AND t.name = ANY(%s) GROUP BY date_trunc('week',h.orderdate)::date | J8: 2025-03-01, 2025-04-01, ['Canada'] | K8: 6 nhóm trong kho dữ liệu
A9: R08 | B9: rag | C9: Sản lượng Factory A theo tuần trong quý 1 năm 2025 | D9: chính | E9: Khớp | F9: 14 | G9: 0 | I9: WITH terminal AS (SELECT DISTINCT ON (workorderid) workorderid,locationid FROM production.workorderrouting ORDER BY workorderid,operationsequence DESC,locationid),fact AS (SELECT w.*,f.factory_id AS fid,COALESCE(f.name,'Unassigned') AS fname FROM production.workorder w LEFT JOIN terminal t ON t.workorderid=w.workorderid LEFT JOIN acbi_demo.location_factory lf ON lf.locationid=t.locationid LEFT JOIN acbi_demo.factory f ON f.factory_id=lf.factory_id) SELECT date_trunc('week',enddate)::date,SUM(orderqty-scrappedqty) FROM fact WHERE enddate>=%s AND enddate<%s AND fid=%s GROUP BY date_trunc('week',enddate)::date | J9: 2025-01-01, 2025-04-01, 1 | K9: 14 nhóm trong kho dữ liệu
A10: R09 | B10: rag | C10: Doanh thu theo tuần trong quý 1 năm 2025 | D10: chính | E10: Khớp | F10: 14 | G10: 0 | I10: SELECT date_trunc('week',h.orderdate)::date,SUM(h.subtotal) FROM sales.salesorderheader h JOIN sales.salesterritory t ON t.territoryid=h.territoryid WHERE h.orderdate>=%s AND h.orderdate<%s GROUP BY date_trunc('week',h.orderdate)::date | J10: 2025-01-01, 2025-04-01 | K10: 14 nhóm trong kho dữ liệu
A11: R10 | B11: rag | C11: Sản lượng theo ngày trong tháng 3 năm 2025 | D11: chính | E11: Khớp | F11: 21 | G11: 0 | I11: WITH terminal AS (SELECT DISTINCT ON (workorderid) workorderid,locationid FROM production.workorderrouting ORDER BY workorderid,operationsequence DESC,locationid),fact AS (SELECT w.*,f.factory_id AS fid,COALESCE(f.name,'Unassigned') AS fname FROM production.workorder w LEFT JOIN terminal t ON t.workorderid=w.workorderid LEFT JOIN acbi_demo.location_factory lf ON lf.locationid=t.locationid LEFT JOIN acbi_demo.factory f ON f.factory_id=lf.factory_id) SELECT enddate::date,SUM(orderqty-scrappedqty) FROM fact WHERE enddate>=%s AND enddate<%s AND fid=%s GROUP BY enddate::date | J11: 2025-03-01, 2025-04-01, 1 | K11: 21 nhóm trong kho dữ liệu
A12: R15 | B12: rag | C12: Weekly revenue in Q4 2024 | D12: chính | E12: Khớp | F12: 14 | G12: 0 | I12: SELECT date_trunc('week',h.orderdate)::date,SUM(h.subtotal) FROM sales.salesorderheader h JOIN sales.salesterritory t ON t.territoryid=h.territoryid WHERE h.orderdate>=%s AND h.orderdate<%s GROUP BY date_trunc('week',h.orderdate)::date | J12: 2024-10-01, 2025-01-01 | K12: 14 nhóm trong kho dữ liệu
A13: R16 | B13: rag | C13: Doanh thu theo tuần của Australia trong quý 4 năm 2024 | D13: chính | E13: Khớp | F13: 14 | G13: 0 | I13: SELECT date_trunc('week',h.orderdate)::date,SUM(h.subtotal) FROM sales.salesorderheader h JOIN sales.salesterritory t ON t.territoryid=h.territoryid WHERE h.orderdate>=%s AND h.orderdate<%s AND t.name = ANY(%s) GROUP BY date_trunc('week',h.orderdate)::date | J13: 2024-10-01, 2025-01-01, ['Australia'] | K13: 14 nhóm trong kho dữ liệu
... A21: R24 | B21: rag | C21: Sản lượng Factory A theo tuần trong tháng 6 năm 2025 | D21: chính | E21: Khớp | F21: 3 | G21: 0 | I21: WITH terminal AS (SELECT DISTINCT ON (workorderid) workorderid,locationid FROM production.workorderrouting ORDER BY workorderid,operationsequence DESC,locationid),fact AS (SELECT w.*,f.factory_id AS fid,COALESCE(f.name,'Unassigned') AS fname FROM production.workorder w LEFT JOIN terminal t ON t.workorderid=w.workorderid LEFT JOIN acbi_demo.location_factory lf ON lf.locationid=t.locationid LEFT JOIN acbi_demo.factory f ON f.factory_id=lf.factory_id) SELECT date_trunc('week',enddate)::date,SUM(orderqty-scrappedqty) FROM fact WHERE enddate>=%s AND enddate<%s AND fid=%s GROUP BY date_trunc('week',enddate)::date | J21: 2025-06-01, 2025-07-01, 1 | K21: 3 nhóm trong kho dữ liệu
A22: H11 | B22: hard | C22: Tại sao doanh thu quý trước giảm? | D22: chính | E22: Khớp | F22: 1 | G22: 0 | I22: SELECT 'all',SUM(h.subtotal) FROM sales.salesorderheader h JOIN sales.salesterritory t ON t.territoryid=h.territoryid WHERE h.orderdate>=%s AND h.orderdate<%s | J22: 2025-01-01, 2025-04-01
A23: H13 | B23: hard | C23: Doanh thu năm 2024 | D23: chính | E23: Khớp | F23: 1 | G23: 0 | I23: SELECT 'all',SUM(h.subtotal) FROM sales.salesorderheader h JOIN sales.salesterritory t ON t.territoryid=h.territoryid WHERE h.orderdate>=%s AND h.orderdate<%s | J23: 2024-01-01, 2025-01-01
A24: H16 | B24: hard | C24: Có phải Canada là khu vực có doanh thu cao nhất năm 2024 không? | D24: chính | E24: Khớp | F24: 10 | G24: 0 | I24: SELECT t.name,SUM(h.subtotal) FROM sales.salesorderheader h JOIN sales.salesterritory t ON t.territoryid=h.territoryid WHERE h.orderdate>=%s AND h.orderdate<%s GROUP BY t.name | J24: 2024-01-01, 2025-01-01 | K24: 10 nhóm trong kho dữ liệu
A25: H27 | B25: hard | C25: Quel est le chiffre d'affaires en 2024 ? | D25: chính | E25: Khớp | F25: 1 | G25: 0 | I25: SELECT 'all',SUM(h.subtotal) FROM sales.salesorderheader h JOIN sales.salesterritory t ON t.territoryid=h.territoryid WHERE h.orderdate>=%s AND h.orderdate<%s | J25: 2024-01-01, 2025-01-01
A26: H28 | B26: hard | C26: Doanh thu năm 2024 và rất nhiều thứ khác và rất nhiều thứ khác và rất nhiều thứ khác và rất nhiều thứ khác và rất nhiều… | D26: chính | E26: Khớp | F26: 1 | G26: 0 | I26: SELECT 'all',SUM(h.subtotal) FROM sales.salesorderheader h JOIN sales.salesterritory t ON t.territoryid=h.territoryid WHERE h.orderdate>=%s AND h.orderdate<%s | J26: 2024-01-01, 2025-01-01
A27: H32 | B27: hard | C27: vẽ biểu đồ radar doanh thu theo khu vực năm 2024 | D27: chính | E27: Khớp | F27: 10 | G27: 0 | I27: SELECT t.name,SUM(h.subtotal) FROM sales.salesorderheader h JOIN sales.salesterritory t ON t.territoryid=h.territoryid WHERE h.orderdate>=%s AND h.orderdate<%s GROUP BY t.name | J27: 2024-01-01, 2025-01-01 | K27: 10 nhóm trong kho dữ liệu
A28: H33 | B28: hard | C28: Doanh thu năm 2024 theo khu vực | D28: chính | E28: Khớp | F28: 10 | G28: 0 | I28: SELECT t.name,SUM(h.subtotal) FROM sales.salesorderheader h JOIN sales.salesterritory t ON t.territoryid=h.territoryid WHERE h.orderdate>=%s AND h.orderdate<%s GROUP BY t.name | J28: 2024-01-01, 2025-01-01 | K28: 10 nhóm trong kho dữ liệu
A29: H34 | B29: hard | C29: Doanh thu năm 2024 theo khu vực | D29: chính | E29: Khớp | F29: 10 | G29: 0 | I29: SELECT t.name,SUM(h.subtotal) FROM sales.salesorderheader h JOIN sales.salesterritory t ON t.territoryid=h.territoryid WHERE h.orderdate>=%s AND h.orderdate<%s GROUP BY t.name | J29: 2024-01-01, 2025-01-01 | K29: 10 nhóm trong kho dữ liệu
A30: H34 | B30: hard | C30: Khu vực đầu bảng cao hơn khu vực cuối bảng bao nhiêu phần trăm? | D30: chính | E30: Khớp | F30: 10 | G30: 0 | I30: SELECT t.name,SUM(h.subtotal) FROM sales.salesorderheader h JOIN sales.salesterritory t ON t.territoryid=h.territoryid WHERE h.orderdate>=%s AND h.orderdate<%s GROUP BY t.name | J30: 2024-01-01, 2025-01-01 | K30: 10 nhóm trong kho dữ liệu
A31: V01 | B31: hard | C31: doanh thu thang truoc the nao | D31: chính | E31: Khớp | F31: 1 | G31: 0 | I31: SELECT 'all',SUM(h.subtotal) FROM sales.salesorderheader h JOIN sales.salesterritory t ON t.territoryid=h.territoryid WHERE h.orderdate>=%s AND h.orderdate<%s | J31: 2025-05-01, 2025-06-01
A32: V02 | B32: hard | C32: dt quý này bn | D32: chính | E32: Khớp | F32: 1 | G32: 0 | I32: SELECT 'all',SUM(h.subtotal) FROM sales.salesorderheader h JOIN sales.salesterritory t ON t.territoryid=h.territoryid WHERE h.orderdate>=%s AND h.orderdate<%s | J32: 2025-04-01, 2025-06-30
A33: V03 | B33: hard | C33: tháng trc bán đc bao nhiêu tiền | D33: chính | E33: Khớp | F33: 1 | G33: 0 | I33: SELECT 'all',SUM(h.subtotal) FROM sales.salesorderheader h JOIN sales.salesterritory t ON t.territoryid=h.territoryid WHERE h.orderdate>=%s AND h.orderdate<%s | J33: 2025-05-01, 2025-06-01
A34: V04 | B34: hard | C34: doanh số tuần vừa rồi ấy | D34: chính | E34: Khớp | F34: 1 | G34: 0 | I34: SELECT 'all',SUM(h.subtotal) FROM sales.salesorderheader h JOIN sales.salesterritory t ON t.territoryid=h.territoryid WHERE h.orderdate>=%s AND h.orderdate<%s | J34: 2025-06-16, 2025-06-23
A35: V10 | B35: hard | C35: doanh thu tháng 3, ý mình là tháng 4 năm 2025 | D35: chính | E35: Khớp | F35: 1 | G35: 0 | I35: SELECT 'all',SUM(h.subtotal) FROM sales.salesorderheader h JOIN sales.salesterritory t ON t.territoryid=h.territoryid WHERE h.orderdate>=%s AND h.orderdate<%s | J35: 2025-04-01, 2025-05-01
A36: V11 | B36: hard | C36: chào bạn, mình muốn xem doanh thu, à mà thôi xem sản lượng đi, năm 2024 nhé | D36: chính | E36: Khớp | F36: 1 | G36: 0 | I36: WITH terminal AS (SELECT DISTINCT ON (workorderid) workorderid,locationid FROM production.workorderrouting ORDER BY workorderid,operationsequence DESC,locationid),fact AS (SELECT w.*,f.factory_id AS fid,COALESCE(f.name,'Unassigned') AS fname FROM production.workorder w LEFT JOIN terminal t ON t.workorderid=w.workorderid LEFT JOIN acbi_demo.location_factory lf ON lf.locationid=t.locationid LEFT JOIN acbi_demo.factory f ON f.factory_id=lf.factory_id) SELECT 'all',SUM(orderqty-scrappedqty) FROM fact WHERE enddate>=%s AND enddate<%s | J36: 2024-01-01, 2025-01-01
A37: V12 | B37: hard | C37: % Canada trong tổng doanh thu năm 2024 | D37: chính | E37: Khớp | F37: 10 | G37: 0 | I37: SELECT t.name,SUM(h.subtotal) FROM sales.salesorderheader h JOIN sales.salesterritory t ON t.territoryid=h.territoryid WHERE h.orderdate>=%s AND h.orderdate<%s GROUP BY t.name | J37: 2024-01-01, 2025-01-01 | K37: 10 nhóm trong kho dữ liệu
A38: V13 | B38: hard | C38: doanh thu năm 2024 tính bằng triệu | D38: chính | E38: Khớp | F38: 1 | G38: 0 | I38: SELECT 'all',SUM(h.subtotal) FROM sales.salesorderheader h JOIN sales.salesterritory t ON t.territoryid=h.territoryid WHERE h.orderdate>=%s AND h.orderdate<%s | J38: 2024-01-01, 2025-01-01
A39: V17 | B39: hard | C39: revenue tháng này bao nhiêu | D39: chính | E39: Khớp | F39: 1 | G39: 0 | I39: SELECT 'all',SUM(h.subtotal) FROM sales.salesorderheader h JOIN sales.salesterritory t ON t.territoryid=h.territoryid WHERE h.orderdate>=%s AND h.orderdate<%s | J39: 2025-06-01, 2025-06-30
A40: V19 | B40: hard | C40: Có phải Canada là khu vực có doanh thu cao nhất năm 2024 không? | D40: chính | E40: Khớp | F40: 10 | G40: 0 | I40: SELECT t.name,SUM(h.subtotal) FROM sales.salesorderheader h JOIN sales.salesterritory t ON t.territoryid=h.territoryid WHERE h.orderdate>=%s AND h.orderdate<%s GROUP BY t.name | J40: 2024-01-01, 2025-01-01 | K40: 10 nhóm trong kho dữ liệu
A41: V20 | B41: hard | C41: Doanh thu năm 2024 theo khu vực | D41: chính | E41: Khớp | F41: 10 | G41: 0 | I41: SELECT t.name,SUM(h.subtotal) FROM sales.salesorderheader h JOIN sales.salesterritory t ON t.territoryid=h.territoryid WHERE h.orderdate>=%s AND h.orderdate<%s GROUP BY t.name | J41: 2024-01-01, 2025-01-01 | K41: 10 nhóm trong kho dữ liệu
A42: V20 | B42: hard | C42: Khu vực đầu bảng cao hơn khu vực cuối bảng bao nhiêu phần trăm? | D42: chính | E42: Khớp | F42: 10 | G42: 0 | I42: SELECT t.name,SUM(h.subtotal) FROM sales.salesorderheader h JOIN sales.salesterritory t ON t.territoryid=h.territoryid WHERE h.orderdate>=%s AND h.orderdate<%s GROUP BY t.name | J42: 2024-01-01, 2025-01-01 | K42: 10 nhóm trong kho dữ liệu
A43: R01 | B43: hard | C43: Doanh thu năm 2024 | D43: chính | E43: Khớp | F43: 1 | G43: 0 | I43: SELECT 'all',SUM(h.subtotal) FROM sales.salesorderheader h JOIN sales.salesterritory t ON t.territoryid=h.territoryid WHERE h.orderdate>=%s AND h.orderdate<%s | J43: 2024-01-01, 2025-01-01
A44: R02 | B44: hard | C44: Sản lượng năm 2024 | D44: chính | E44: Khớp | F44: 1 | G44: 0 | I44: WITH terminal AS (SELECT DISTINCT ON (workorderid) workorderid,locationid FROM production.workorderrouting ORDER BY workorderid,operationsequence DESC,locationid),fact AS (SELECT w.*,f.factory_id AS fid,COALESCE(f.name,'Unassigned') AS fname FROM production.workorder w LEFT JOIN terminal t ON t.workorderid=w.workorderid LEFT JOIN acbi_demo.location_factory lf ON lf.locationid=t.locationid LEFT JOIN acbi_demo.factory f ON f.factory_id=lf.factory_id) SELECT 'all',SUM(orderqty-scrappedqty) FROM fact WHERE enddate>=%s AND enddate<%s AND fid=%s | J44: 2024-01-01, 2025-01-01, 1
A45: R04 | B45: hard | C45: Doanh thu năm 2024 | D45: chính | E45: Khớp | F45: 1 | G45: 0 | I45: SELECT 'all',SUM(h.subtotal) FROM sales.salesorderheader h JOIN sales.salesterritory t ON t.territoryid=h.territoryid WHERE h.orderdate>=%s AND h.orderdate<%s | J45: 2024-01-01, 2025-01-01
A46: R05 | B46: hard | C46: Doanh thu năm 2024 và sản lượng năm 2024 và tỷ lệ phế phẩm năm 2024 | D46: chính | E46: Khớp | F46: 1 | G46: 0 | I46: SELECT 'all',SUM(h.subtotal) FROM sales.salesorderheader h JOIN sales.salesterritory t ON t.territoryid=h.territoryid WHERE h.orderdate>=%s AND h.orderdate<%s | J46: 2024-01-01, 2025-01-01
A47: K01 | B47: hard | C47: Doanh thu năm 2024 | D47: chính | E47: Khớp | F47: 1 | G47: 0 | I47: SELECT 'all',SUM(h.subtotal) FROM sales.salesorderheader h JOIN sales.salesterritory t ON t.territoryid=h.territoryid WHERE h.orderdate>=%s AND h.orderdate<%s | J47: 2024-01-01, 2025-01-01
A48: K01 | B48: hard | C48: Revenue in 2024 | D48: chính | E48: Khớp | F48: 1 | G48: 0 | I48: SELECT 'all',SUM(h.subtotal) FROM sales.salesorderheader h JOIN sales.salesterritory t ON t.territoryid=h.territoryid WHERE h.orderdate>=%s AND h.orderdate<%s | J48: 2024-01-01, 2025-01-01
A49: K01 | B49: hard | C49: doanh so nam 2024 | D49: chính | E49: Khớp | F49: 1 | G49: 0 | I49: SELECT 'all',SUM(h.subtotal) FROM sales.salesorderheader h JOIN sales.salesterritory t ON t.territoryid=h.territoryid WHERE h.orderdate>=%s AND h.orderdate<%s | J49: 2024-01-01, 2025-01-01
A50: K01 | B50: hard | C50: Tổng doanh thu từ 01/01/2024 đến 31/12/2024 | D50: chính | E50: Khớp | F50: 1 | G50: 0 | I50: SELECT 'all',SUM(h.subtotal) FROM sales.salesorderheader h JOIN sales.salesterritory t ON t.territoryid=h.territoryid WHERE h.orderdate>=%s AND h.orderdate<%s | J50: 2024-01-01, 2025-01-01
A51: K01 | B51: hard | C51: cho mình biết doanh thu cả năm 2024 với | D51: chính | E51: Khớp | F51: 1 | G51: 0 | I51: SELECT 'all',SUM(h.subtotal) FROM sales.salesorderheader h JOIN sales.salesterritory t ON t.territoryid=h.territoryid WHERE h.orderdate>=%s AND h.orderdate<%s | J51: 2024-01-01, 2025-01-01
A52: K01 | B52: hard | C52: what were total sales for the year 2024 | D52: chính | E52: Khớp | F52: 1 | G52: 0 | I52: SELECT 'all',SUM(h.subtotal) FROM sales.salesorderheader h JOIN sales.salesterritory t ON t.territoryid=h.territoryid WHERE h.orderdate>=%s AND h.orderdate<%s | J52: 2024-01-01, 2025-01-01
A53: K02 | B53: hard | C53: Doanh thu năm 2024 theo khu vực | D53: chính | E53: Khớp | F53: 10 | G53: 0 | I53: SELECT t.name,SUM(h.subtotal) FROM sales.salesorderheader h JOIN sales.salesterritory t ON t.territoryid=h.territoryid WHERE h.orderdate>=%s AND h.orderdate<%s GROUP BY t.name | J53: 2024-01-01, 2025-01-01 | K53: 10 nhóm trong kho dữ liệu
A54: K03 | B54: hard | C54: Doanh thu năm 2024 theo tháng | D54: chính | E54: Khớp | F54: 12 | G54: 0 | I54: SELECT date_trunc('month',h.orderdate)::date,SUM(h.subtotal) FROM sales.salesorderheader h JOIN sales.salesterritory t ON t.territoryid=h.territoryid WHERE h.orderdate>=%s AND h.orderdate<%s GROUP BY date_trunc('month',h.orderdate)::date | J54: 2024-01-01, 2025-01-01 | K54: 12 nhóm trong kho dữ liệu
A55: K04 | B55: hard | C55: Doanh thu năm 2024 theo danh mục sản phẩm | D55: chính | E55: Chưa đối chiếu | F55: 0 | G55: 0 | K55: chiều phân tích không có truy vấn đối chiếu độc lập
A56: K05 | B56: hard | C56: Doanh thu Canada năm 2024 theo tháng | D56: chính | E56: Khớp | F56: 12 | G56: 0 | I56: SELECT date_trunc('month',h.orderdate)::date,SUM(h.subtotal) FROM sales.salesorderheader h JOIN sales.salesterritory t ON t.territoryid=h.territoryid WHERE h.orderdate>=%s AND h.orderdate<%s AND t.name = ANY(%s) GROUP BY date_trunc('month',h.orderdate)::date | J56: 2024-01-01, 2025-01-01, ['Canada'] | K56: 12 nhóm trong kho dữ liệu
A57: K05 | B57: hard | C57: Doanh thu Canada năm 2024 theo tháng | D57: chính | E57: Khớp | F57: 12 | G57: 0 | I57: SELECT date_trunc('month',h.orderdate)::date,SUM(h.subtotal) FROM sales.salesorderheader h JOIN sales.salesterritory t ON t.territoryid=h.territoryid WHERE h.orderdate>=%s AND h.orderdate<%s AND t.name = ANY(%s) GROUP BY date_trunc('month',h.orderdate)::date | J57: 2024-01-01, 2025-01-01, ['Canada'] | K57: 12 nhóm trong kho dữ liệu
A58: K06 | B58: hard | C58: Doanh thu năm 2024 theo khu vực | D58: chính | E58: Khớp | F58: 10 | G58: 0 | I58: SELECT t.name,SUM(h.subtotal) FROM sales.salesorderheader h JOIN sales.salesterritory t ON t.territoryid=h.territoryid WHERE h.orderdate>=%s AND h.orderdate<%s GROUP BY t.name | J58: 2024-01-01, 2025-01-01 | K58: 10 nhóm trong kho dữ liệu
A59: K06 | B59: hard | C59: chỉ Canada | D59: chính | E59: Khớp | F59: 1 | G59: 0 | I59: SELECT 'all',SUM(h.subtotal) FROM sales.salesorderheader h JOIN sales.salesterritory t ON t.territoryid=h.territoryid WHERE h.orderdate>=%s AND h.orderdate<%s AND t.name = ANY(%s) | J59: 2024-01-01, 2025-01-01, ['Canada']
A60: K06 | B60: hard | C60: còn năm 2023? | D60: chính | E60: Khớp | F60: 1 | G60: 0 | I60: SELECT 'all',SUM(h.subtotal) FROM sales.salesorderheader h JOIN sales.salesterritory t ON t.territoryid=h.territoryid WHERE h.orderdate>=%s AND h.orderdate<%s AND t.name = ANY(%s) | J60: 2023-01-01, 2024-01-01, ['Canada']
A61: K06 | B61: hard | C61: còn France? | D61: chính | E61: Khớp | F61: 1 | G61: 0 | I61: SELECT 'all',SUM(h.subtotal) FROM sales.salesorderheader h JOIN sales.salesterritory t ON t.territoryid=h.territoryid WHERE h.orderdate>=%s AND h.orderdate<%s AND t.name = ANY(%s) | J61: 2023-01-01, 2024-01-01, ['France']
A62: K06 | B62: hard | C62: vẽ dạng cột | D62: chính | E62: Khớp | F62: 1 | G62: 0 | I62: SELECT 'all',SUM(h.subtotal) FROM sales.salesorderheader h JOIN sales.salesterritory t ON t.territoryid=h.territoryid WHERE h.orderdate>=%s AND h.orderdate<%s AND t.name = ANY(%s) | J62: 2023-01-01, 2024-01-01, ['France']
A63: K07 | B63: hard | C63: Doanh thu tháng 2 năm 2024 | D63: chính | E63: Khớp | F63: 1 | G63: 0 | I63: SELECT 'all',SUM(h.subtotal) FROM sales.salesorderheader h JOIN sales.salesterritory t ON t.territoryid=h.territoryid WHERE h.orderdate>=%s AND h.orderdate<%s | J63: 2024-02-01, 2024-03-01
A64: K07 | B64: hard | C64: Doanh thu ngày 29/02/2024 | D64: chính | E64: Khớp | F64: 1 | G64: 0 | I64: SELECT 'all',SUM(h.subtotal) FROM sales.salesorderheader h JOIN sales.salesterritory t ON t.territoryid=h.territoryid WHERE h.orderdate>=%s AND h.orderdate<%s | J64: 2024-02-29, 2024-03-01
A65: K07 | B65: hard | C65: Doanh thu quý 4 năm 2024 | D65: chính | E65: Khớp | F65: 1 | G65: 0 | I65: SELECT 'all',SUM(h.subtotal) FROM sales.salesorderheader h JOIN sales.salesterritory t ON t.territoryid=h.territoryid WHERE h.orderdate>=%s AND h.orderdate<%s | J65: 2024-10-01, 2025-01-01
A66: K07 | B66: hard | C66: Doanh thu từ 01/03/2024 đến 31/03/2024 | D66: chính | E66: Khớp | F66: 1 | G66: 0 | I66: SELECT 'all',SUM(h.subtotal) FROM sales.salesorderheader h JOIN sales.salesterritory t ON t.territoryid=h.territoryid WHERE h.orderdate>=%s AND h.orderdate<%s | J66: 2024-03-01, 2024-04-01
A67: K08 | B67: hard | C67: Tăng trưởng doanh thu quý trước | D67: chính | E67: Chưa đối chiếu | F67: 0 | G67: 0 | K67: chiều phân tích không có truy vấn đối chiếu độc lập (sản phẩm, ngành hàng, dây chuyền, lý do phế phẩm, tăng trưởng)
A68: K09 | B68: hard | C68: Sản lượng Factory A năm 2024 | D68: chính | E68: Khớp | F68: 1 | G68: 0 | I68: WITH terminal AS (SELECT DISTINCT ON (workorderid) workorderid,locationid FROM production.workorderrouting ORDER BY workorderid,operationsequence DESC,locationid),fact AS (SELECT w.*,f.factory_id AS fid,COALESCE(f.name,'Unassigned') AS fname FROM production.workorder w LEFT JOIN terminal t ON t.workorderid=w.workorderid LEFT JOIN acbi_demo.location_factory lf ON lf.locationid=t.locationid LEFT JOIN acbi_demo.factory f ON f.factory_id=lf.factory_id) SELECT fname,SUM(orderqty-scrappedqty) FROM fact WHERE enddate>=%s AND enddate<%s AND fid=%s GROUP BY fname | J68: 2024-01-01, 2025-01-01, 1 | K68: 1 nhóm trong kho dữ liệu
A69: K10 | B69: hard | C69: Doanh thu năm 2024 và sản lượng năm 2024 | D69: chính | E69: Khớp | F69: 1 | G69: 0 | I69: SELECT 'all',SUM(h.subtotal) FROM sales.salesorderheader h JOIN sales.salesterritory t ON t.territoryid=h.territoryid WHERE h.orderdate>=%s AND h.orderdate<%s | J69: 2024-01-01, 2025-01-01
A70: K10 | B70: hard | C70: Doanh thu năm 2024 và sản lượng năm 2024 | D70: 2. Sản lượng năm 2024 | E70: Khớp | F70: 1 | G70: 0 | I70: WITH terminal AS (SELECT DISTINCT ON (workorderid) workorderid,locationid FROM production.workorderrouting ORDER BY workorderid,operationsequence DESC,locationid),fact AS (SELECT w.*,f.factory_id AS fid,COALESCE(f.name,'Unassigned') AS fname FROM production.workorder w LEFT JOIN terminal t ON t.workorderid=w.workorderid LEFT JOIN acbi_demo.location_factory lf ON lf.locationid=t.locationid LEFT JOIN acbi_demo.factory f ON f.factory_id=lf.factory_id) SELECT 'all',SUM(orderqty-scrappedqty) FROM fact WHERE enddate>=%s AND enddate<%s | J70: 2024-01-01, 2025-01-01
A71: K11 | B71: hard | C71: What is revenue in 2024? | D71: chính | E71: Khớp | F71: 1 | G71: 0 | I71: SELECT 'all',SUM(h.subtotal) FROM sales.salesorderheader h JOIN sales.salesterritory t ON t.territoryid=h.territoryid WHERE h.orderdate>=%s AND h.orderdate<%s | J71: 2024-01-01, 2025-01-01
A72: K12 | B72: hard | C72: Doanh thu năm 2024 là bao nhiêu? | D72: chính | E72: Khớp | F72: 1 | G72: 0 | I72: SELECT 'all',SUM(h.subtotal) FROM sales.salesorderheader h JOIN sales.salesterritory t ON t.territoryid=h.territoryid WHERE h.orderdate>=%s AND h.orderdate<%s | J72: 2024-01-01, 2025-01-01
A73: K13 | B73: hard | C73: so sánh sản lượng năm 2023 và 2024 | D73: chính | E73: Khớp | F73: 2 | G73: 0 | I73: WITH terminal AS (SELECT DISTINCT ON (workorderid) workorderid,locationid FROM production.workorderrouting ORDER BY workorderid,operationsequence DESC,locationid),fact AS (SELECT w.*,f.factory_id AS fid,COALESCE(f.name,'Unassigned') AS fname FROM production.workorder w LEFT JOIN terminal t ON t.workorderid=w.workorderid LEFT JOIN acbi_demo.location_factory lf ON lf.locationid=t.locationid LEFT JOIN acbi_demo.factory f ON f.factory_id=lf.factory_id) SELECT 'all',SUM(orderqty-scrappedqty) FROM fact WHERE enddate>=%s AND enddate<%s | J73: 2024-01-01, 2025-01-01
A74: K14 | B74: hard | C74: dự báo doanh thu 6 tháng tới | D74: chính | E74: Khớp | F74: 12 | G74: 0 | I74: SELECT date_trunc('month',h.orderdate)::date,SUM(h.subtotal) FROM sales.salesorderheader h JOIN sales.salesterritory t ON t.territoryid=h.territoryid WHERE h.orderdate>=%s AND h.orderdate<%s GROUP BY date_trunc('month',h.orderdate)::date | J74: 2022-06-01, 2025-06-01 | K74: đối chiếu phần số liệu đã ghi nhận; giá trị dự báo được kiểm bằng kiểm thử tự động so với statsmodels
A75: K14 | B75: hard | C75: dự báo doanh thu 6 tháng tới | D75: chính | E75: Khớp | F75: 12 | G75: 0 | I75: SELECT date_trunc('month',h.orderdate)::date,SUM(h.subtotal) FROM sales.salesorderheader h JOIN sales.salesterritory t ON t.territoryid=h.territoryid WHERE h.orderdate>=%s AND h.orderdate<%s GROUP BY date_trunc('month',h.orderdate)::date | J75: 2022-06-01, 2025-06-01 | K75: đối chiếu phần số liệu đã ghi nhận; giá trị dự báo được kiểm bằng kiểm thử tự động so với statsmodels
A76: D01 | B76: hard | C76: Doanh thu tuần trước | D76: chính | E76: Khớp | F76: 1 | G76: 0 | I76: SELECT 'all',SUM(h.subtotal) FROM sales.salesorderheader h JOIN sales.salesterritory t ON t.territoryid=h.territoryid WHERE h.orderdate>=%s AND h.orderdate<%s | J76: 2025-06-16, 2025-06-23
A77: D02 | B77: hard | C77: Doanh thu 30 ngày gần nhất | D77: chính | E77: Khớp | F77: 1 | G77: 0 | I77: SELECT 'all',SUM(h.subtotal) FROM sales.salesorderheader h JOIN sales.salesterritory t ON t.territoryid=h.territoryid WHERE h.orderdate>=%s AND h.orderdate<%s | J77: 2025-05-31, 2025-06-30
A78: D03 | B78: hard | C78: Doanh thu năm nay | D78: chính | E78: Khớp | F78: 1 | G78: 0 | I78: SELECT 'all',SUM(h.subtotal) FROM sales.salesorderheader h JOIN sales.salesterritory t ON t.territoryid=h.territoryid WHERE h.orderdate>=%s AND h.orderdate<%s | J78: 2025-01-01, 2025-06-30
A79: D04 | B79: hard | C79: Doanh thu hôm qua | D79: chính | E79: Khớp | F79: 1 | G79: 0 | I79: SELECT 'all',SUM(h.subtotal) FROM sales.salesorderheader h JOIN sales.salesterritory t ON t.territoryid=h.territoryid WHERE h.orderdate>=%s AND h.orderdate<%s | J79: 2025-06-28, 2025-06-29
A80: D05 | B80: hard | C80: Revenue last year | D80: chính | E80: Khớp | F80: 1 | G80: 0 | I80: SELECT 'all',SUM(h.subtotal) FROM sales.salesorderheader h JOIN sales.salesterritory t ON t.territoryid=h.territoryid WHERE h.orderdate>=%s AND h.orderdate<%s | J80: 2024-01-01, 2025-01-01
A81: X01 | B81: hard | C81: Top 3 sản phẩm bán chạy nhất khu vực Canada năm 2024 | D81: chính | E81: Chưa đối chiếu | F81: 0 | G81: 0 | K81: chiều phân tích không có truy vấn đối chiếu độc lập
A82: X02 | B82: hard | C82: Doanh thu theo danh mục của Canada quý 1 năm 2025 | D82: chính | E82: Chưa đối chiếu | F82: 0 | G82: 0 | K82: chiều phân tích không có truy vấn đối chiếu độc lập
A83: X03 | B83: hard | C83: Tỷ lệ phế phẩm theo lý do của Factory B năm 2024 | D83: chính | E83: Chưa đối chiếu | F83: 0 | G83: 0 | K83: chiều phân tích không có truy vấn đối chiếu độc lập
A84: X04 | B84: hard | C84: Doanh thu theo tháng năm 2024 của Canada và France dạng cột chồng | D84: chính | E84: Khớp | F84: 24 | G84: 0 | I84: SELECT t.name,date_trunc('month',h.orderdate)::date,SUM(h.subtotal) FROM sales.salesorderheader h JOIN sales.salesterritory t ON t.territoryid=h.territoryid WHERE h.orderdate>=%s AND h.orderdate<%s AND t.name = ANY(%s) GROUP BY t.name,date_trunc('month',h.orderdate)::date | J84: 2024-01-01, 2025-01-01, ['Canada', 'France'] | K84: 24 nhóm trong kho dữ liệu
A85: X05 | B85: hard | C85: So sánh top 3 khu vực theo doanh thu năm 2023 và 2024 | D85: chính | E85: Khớp | F85: 9 | G85: 0 | I85: SELECT t.name,SUM(h.subtotal) FROM sales.salesorderheader h JOIN sales.salesterritory t ON t.territoryid=h.territoryid WHERE h.orderdate>=%s AND h.orderdate<%s GROUP BY t.name | J85: 2023-01-01, 2024-01-01 | K85: so từng kỳ với kho dữ liệu và kiểm tra phép trừ của cột chênh lệch
A86: X06 | B86: hard | C86: Canada gấp mấy lần Australia về doanh thu năm 2024? | D86: chính | E86: Khớp | F86: 2 | G86: 0 | I86: SELECT t.name,SUM(h.subtotal) FROM sales.salesorderheader h JOIN sales.salesterritory t ON t.territoryid=h.territoryid WHERE h.orderdate>=%s AND h.orderdate<%s AND t.name = ANY(%s) GROUP BY t.name | J86: 2024-01-01, 2025-01-01, ['Australia', 'Canada'] | K86: 2 nhóm trong kho dữ liệu
A87: X07 | B87: hard | C87: Trung bình mỗi tháng năm 2024 doanh thu là bao nhiêu? | D87: chính | E87: Khớp | F87: 12 | G87: 0 | I87: SELECT date_trunc('month',h.orderdate)::date,SUM(h.subtotal) FROM sales.salesorderheader h JOIN sales.salesterritory t ON t.territoryid=h.territoryid WHERE h.orderdate>=%s AND h.orderdate<%s GROUP BY date_trunc('month',h.orderdate)::date | J87: 2024-01-01, 2025-01-01 | K87: 12 nhóm trong kho dữ liệu
A88: X08 | B88: hard | C88: Khu vực nào có doanh thu cao nhất năm 2024 và tăng trưởng của nó so với 2023? | D88: chính | E88: Khớp | F88: 10 | G88: 0 | I88: SELECT t.name,SUM(h.subtotal) FROM sales.salesorderheader h JOIN sales.salesterritory t ON t.territoryid=h.territoryid WHERE h.orderdate>=%s AND h.orderdate<%s GROUP BY t.name | J88: 2024-01-01, 2025-01-01 | K88: 10 nhóm trong kho dữ liệu
A89: X08 | B89: hard | C89: Khu vực nào có doanh thu cao nhất năm 2024 và tăng trưởng của nó so với 2023? | D89: 2. Tăng trưởng của nó so với 2023 | E89: Khớp | F89: 2 | G89: 0 | I89: SELECT 'all',SUM(h.subtotal) FROM sales.salesorderheader h JOIN sales.salesterritory t ON t.territoryid=h.territoryid WHERE h.orderdate>=%s AND h.orderdate<%s AND t.name = ANY(%s) | J89: 2024-01-01, 2025-01-01, ['Southwest']
A90: X09 | B90: hard | C90: Sản lượng Factory A theo dây chuyền quý trước | D90: chính | E90: Chưa đối chiếu | F90: 0 | G90: 0 | K90: chiều phân tích không có truy vấn đối chiếu độc lập
A91: X11 | B91: hard | C91: So sánh doanh thu và sản lượng năm 2024 | D91: 2. Sản lượng năm 2024 | E91: Khớp | F91: 1 | G91: 0 | I91: WITH terminal AS (SELECT DISTINCT ON (workorderid) workorderid,locationid FROM production.workorderrouting ORDER BY workorderid,operationsequence DESC,locationid),fact AS (SELECT w.*,f.factory_id AS fid,COALESCE(f.name,'Unassigned') AS fname FROM production.workorder w LEFT JOIN terminal t ON t.workorderid=w.workorderid LEFT JOIN acbi_demo.location_factory lf ON lf.locationid=t.locationid LEFT JOIN acbi_demo.factory f ON f.factory_id=lf.factory_id) SELECT 'all',SUM(orderqty-scrappedqty) FROM fact WHERE enddate>=%s AND enddate<%s | J91: 2024-01-01, 2025-01-01
A92: X12 | B92: hard | C92: Doanh thu, sản lượng và tỷ lệ phế phẩm quý 1 năm 2025 của Canada | D92: chính | E92: Khớp | F92: 1 | G92: 0 | I92: SELECT 'all',SUM(h.subtotal) FROM sales.salesorderheader h JOIN sales.salesterritory t ON t.territoryid=h.territoryid WHERE h.orderdate>=%s AND h.orderdate<%s | J92: 2025-01-01, 2026-01-01
A93: X12 | B93: hard | C93: Doanh thu, sản lượng và tỷ lệ phế phẩm quý 1 năm 2025 của Canada | D93: 2. Sản lượng năm 2025 | E93: Khớp | F93: 1 | G93: 0 | I93: WITH terminal AS (SELECT DISTINCT ON (workorderid) workorderid,locationid FROM production.workorderrouting ORDER BY workorderid,operationsequence DESC,locationid),fact AS (SELECT w.*,f.factory_id AS fid,COALESCE(f.name,'Unassigned') AS fname FROM production.workorder w LEFT JOIN terminal t ON t.workorderid=w.workorderid LEFT JOIN acbi_demo.location_factory lf ON lf.locationid=t.locationid LEFT JOIN acbi_demo.factory f ON f.factory_id=lf.factory_id) SELECT 'all',SUM(orderqty-scrappedqty) FROM fact WHERE enddate>=%s AND enddate<%s | J93: 2025-01-01, 2026-01-01
A94: C1 | B94: multi | C94: so sánh doanh thu canada năm 2023 và 2024 | D94: chính | E94: Khớp | F94: 2 | G94: 0 | I94: SELECT 'all',SUM(h.subtotal) FROM sales.salesorderheader h JOIN sales.salesterritory t ON t.territoryid=h.territoryid WHERE h.orderdate>=%s AND h.orderdate<%s AND t.name = ANY(%s) | J94: 2024-01-01, 2025-01-01, ['Canada']
A95: C2 | B95: multi | C95: so sánh doanh thu Canada và France năm 2023 và 2024 | D95: chính | E95: Khớp | F95: 6 | G95: 0 | I95: SELECT t.name,SUM(h.subtotal) FROM sales.salesorderheader h JOIN sales.salesterritory t ON t.territoryid=h.territoryid WHERE h.orderdate>=%s AND h.orderdate<%s GROUP BY t.name | J95: 2024-01-01, 2025-01-01 | K95: so từng kỳ với kho dữ liệu và kiểm tra phép trừ của cột chênh lệch
A96: C3 | B96: multi | C96: compare revenue Q1 2024 and Q1 2025 | D96: chính | E96: Khớp | F96: 2 | G96: 0 | I96: SELECT 'all',SUM(h.subtotal) FROM sales.salesorderheader h JOIN sales.salesterritory t ON t.territoryid=h.territoryid WHERE h.orderdate>=%s AND h.orderdate<%s | J96: 2025-01-01, 2025-04-01
A97: C4 | B97: multi | C97: so sánh doanh thu quý 1 và quý 2 năm 2025 | D97: chính | E97: Khớp | F97: 2 | G97: 0 | I97: SELECT 'all',SUM(h.subtotal) FROM sales.salesorderheader h JOIN sales.salesterritory t ON t.territoryid=h.territoryid WHERE h.orderdate>=%s AND h.orderdate<%s | J97: 2025-04-01, 2025-07-01
A98: C5 | B98: multi | C98: so sánh doanh thu tháng 1, tháng 2 và tháng 3 năm 2025 | D98: chính | E98: Khớp | F98: 3 | G98: 0 | I98: SELECT 'all',SUM(h.subtotal) FROM sales.salesorderheader h JOIN sales.salesterritory t ON t.territoryid=h.territoryid WHERE h.orderdate>=%s AND h.orderdate<%s | J98: 2025-03-01, 2025-04-01
A99: C6 | B99: multi | C99: so sánh sản lượng năm 2023 và 2024 | D99: chính | E99: Khớp | F99: 2 | G99: 0 | I99: WITH terminal AS (SELECT DISTINCT ON (workorderid) workorderid,locationid FROM production.workorderrouting ORDER BY workorderid,operationsequence DESC,locationid),fact AS (SELECT w.*,f.factory_id AS fid,COALESCE(f.name,'Unassigned') AS fname FROM production.workorder w LEFT JOIN terminal t ON t.workorderid=w.workorderid LEFT JOIN acbi_demo.location_factory lf ON lf.locationid=t.locationid LEFT JOIN acbi_demo.factory f ON f.factory_id=lf.factory_id) SELECT 'all',SUM(orderqty-scrappedqty) FROM fact WHERE enddate>=%s AND enddate<%s | J99: 2024-01-01, 2025-01-01
A100: C7 | B100: multi | C100: so sánh tỷ lệ phế phẩm theo nhà máy năm 2023 và 2024 | D100: chính | E100: Khớp | F100: 9 | G100: 0 | I100: WITH terminal AS (SELECT DISTINCT ON (workorderid) workorderid,locationid FROM production.workorderrouting ORDER BY workorderid,operationsequence DESC,locationid),fact AS (SELECT w.*,f.factory_id AS fid,COALESCE(f.name,'Unassigned') AS fname FROM production.workorder w LEFT JOIN terminal t ON t.workorderid=w.workorderid LEFT JOIN acbi_demo.location_factory lf ON lf.locationid=t.locationid LEFT JOIN acbi_demo.factory f ON f.factory_id=lf.factory_id) SELECT fname,SUM(scrappedqty)::numeric/NULLIF(SUM(orderqty),0) FROM fact WHERE enddate>=%s AND enddate<%s GROUP BY fname | J100: 2024-01-01, 2025-01-01 | K100: so từng kỳ với kho dữ liệu và kiểm tra phép trừ của cột chênh lệch
A101: C8 | B101: multi | C101: so sánh doanh thu theo danh mục sản phẩm năm 2023 và 2024 | D101: chính | E101: Chưa đối chiếu | F101: 0 | G101: 0 | K101: chiều so sánh (ví dụ ngành hàng) không có truy vấn đối chiếu độc lập
A102: C9 | B102: multi | C102: so sánh doanh thu năm 2023 và 2024 theo tháng | D102: chính | E102: Khớp | F102: 24 | G102: 0 | I102: SELECT date_trunc('month',h.orderdate)::date,SUM(h.subtotal) FROM sales.salesorderheader h JOIN sales.salesterritory t ON t.territoryid=h.territoryid WHERE h.orderdate>=%s AND h.orderdate<%s GROUP BY date_trunc('month',h.orderdate)::date | J102: 2023-01-01, 2025-01-01 | K102: 24 nhóm trong kho dữ liệu
A103: C10 | B103: multi | C103: so sánh doanh thu năm 2023 và 2024 bằng biểu đồ tròn | D103: chính | E103: Khớp | F103: 2 | G103: 0 | I103: SELECT 'all',SUM(h.subtotal) FROM sales.salesorderheader h JOIN sales.salesterritory t ON t.territoryid=h.territoryid WHERE h.orderdate>=%s AND h.orderdate<%s | J103: 2024-01-01, 2025-01-01
A104: C13 | B104: multi | C104: so sánh sản lượng năm 2023 và 2024 | D104: chính | E104: Khớp | F104: 2 | G104: 0 | I104: WITH terminal AS (SELECT DISTINCT ON (workorderid) workorderid,locationid FROM production.workorderrouting ORDER BY workorderid,operationsequence DESC,locationid),fact AS (SELECT w.*,f.factory_id AS fid,COALESCE(f.name,'Unassigned') AS fname FROM production.workorder w LEFT JOIN terminal t ON t.workorderid=w.workorderid LEFT JOIN acbi_demo.location_factory lf ON lf.locationid=t.locationid LEFT JOIN acbi_demo.factory f ON f.factory_id=lf.factory_id) SELECT 'all',SUM(orderqty-scrappedqty) FROM fact WHERE enddate>=%s AND enddate<%s AND fid=%s | J104: 2024-01-01, 2025-01-01, 1
A105: C15 | B105: multi | C105: so sánh doanh thu năm 2022, 2023, 2024 và 2025 | D105: chính | E105: Khớp | F105: 4 | G105: 0 | I105: SELECT 'all',SUM(h.subtotal) FROM sales.salesorderheader h JOIN sales.salesterritory t ON t.territoryid=h.territoryid WHERE h.orderdate>=%s AND h.orderdate<%s | J105: 2025-01-01, 2026-01-01
A106: C17 | B106: multi | C106: tăng trưởng doanh thu năm 2024 so với 2023 | D106: chính | E106: Khớp | F106: 2 | G106: 0 | I106: SELECT 'all',SUM(h.subtotal) FROM sales.salesorderheader h JOIN sales.salesterritory t ON t.territoryid=h.territoryid WHERE h.orderdate>=%s AND h.orderdate<%s | J106: 2024-01-01, 2025-01-01
A107: C18 | B107: multi | C107: So sánh doanh thu Canada năm 2024 với Canada năm 2023 bằng biểu đồ cột | D107: chính | E107: Khớp | F107: 2 | G107: 0 | I107: SELECT 'all',SUM(h.subtotal) FROM sales.salesorderheader h JOIN sales.salesterritory t ON t.territoryid=h.territoryid WHERE h.orderdate>=%s AND h.orderdate<%s AND t.name = ANY(%s) | J107: 2024-01-01, 2025-01-01, ['Canada']
...

Sheet Đo tải
A1: Người dùng | B1: Câu hỏi | C1: HTTP | D1: Trạng thái | E1: Thời gian (giây) | F1: Trả lời được? | G1: Giây (nếu trả lời được) | I1: Chỉ số | J1: Giá trị
A2: 1 | B2: Doanh thu theo khu vực quý trước | C2: 200 | D2: ok | E2: 0.27 | F2: =IF(OR(D2="ok",D2="no_data",D2="needs_clarification"),"Có","Không") | G2: =IF(F2="Có",E2,"") | I2: Số yêu cầu | J2: =COUNTA(B2:B61)
A3: 2 | B3: Doanh thu Canada năm 2024, rồi sản lượng Factory A tháng trước | C3: 200 | D3: ok | E3: 0.42 | F3: =IF(OR(D3="ok",D3="no_data",D3="needs_clarification"),"Có","Không") | G3: =IF(F3="Có",E3,"") | I3: Trả lời được | J3: =COUNTIF(F2:F61,"Có")
A4: 4 | B4: Doanh thu theo khu vực quý trước | C4: 200 | D4: ok | E4: 2.24 | F4: =IF(OR(D4="ok",D4="no_data",D4="needs_clarification"),"Có","Không") | G4: =IF(F4="Có",E4,"") | I4: Tỷ lệ trả lời được | J4: =J3/J2
A5: 4 | B5: Doanh thu Canada năm 2024, rồi sản lượng Factory A tháng trước | C5: 200 | D5: ok | E5: 0.46 | F5: =IF(OR(D5="ok",D5="no_data",D5="needs_clarification"),"Có","Không") | G5: =IF(F5="Có",E5,"") | I5: Dưới 15 giây (trong số trả lời được) | J5: =COUNTIF(G2:G61,"<=15")
A6: 2 | B6: Doanh thu trung bình mỗi tháng năm 2024 là bao nhiêu? | C6: 503 | D6: technical_failure | E6: 3.11 | F6: =IF(OR(D6="ok",D6="no_data",D6="needs_clarification"),"Có","Không") | G6: =IF(F6="Có",E6,"") | I6: Tỷ lệ yêu cầu hoàn tất dưới 15 giây | J6: =J5/J2
A7: 2 | B7: Doanh thu tháng này | C7: 200 | D7: ok | E7: 0.35 | F7: =IF(OR(D7="ok",D7="no_data",D7="needs_clarification"),"Có","Không") | G7: =IF(F7="Có",E7,"") | I7: p50 thời gian của câu trả lời được (giây) | J7: =MEDIAN(G2:G61)
A8: 2 | B8: Khu vực nào bán tốt nhất năm ngoái? | C8: 503 | D8: technical_failure | E8: 0.33 | F8: =IF(OR(D8="ok",D8="no_data",D8="needs_clarification"),"Có","Không") | G8: =IF(F8="Có",E8,"") | I8: Thời gian lớn nhất (giây) | J8: =MAX(E2:E61)
A9: 1 | B9: Nhà máy nào có tỷ lệ phế phẩm cao nhất quý trước? | C9: 200 | D9: ok | E9: 4.16 | F9: =IF(OR(D9="ok",D9="no_data",D9="needs_clarification"),"Có","Không") | G9: =IF(F9="Có",E9,"")
A10: 5 | B10: Doanh thu trung bình mỗi tháng năm 2024 là bao nhiêu? | C10: 503 | D10: technical_failure | E10: 6.59 | F10: =IF(OR(D10="ok",D10="no_data",D10="needs_clarification"),"Có","Không") | G10: =IF(F10="Có",E10,"") | I10: Cấu hình: 5 người dùng đồng thời, mỗi người hỏi 12 câu một lần (thứ tự trộn), gói AI miễn phí, bản demo Vercel. Mục tiêu trong tài liệu: ít nhất 95% yêu cầu hoàn tất dưới 15 giây.
A11: 5 | B11: So sánh doanh thu năm 2023 và 2024 | C11: 200 | D11: ok | E11: 0.29 | F11: =IF(OR(D11="ok",D11="no_data",D11="needs_clarification"),"Có","Không") | G11: =IF(F11="Có",E11,"") | I11: Nguyên nhân các lỗi: tất cả là 'AI bận' do nhà cung cấp trả HTTP 429 (một số khóa Gemini hết quota ngày, LiteRouter chỉ cho một yêu cầu mỗi 7 giây). Các câu không cần AI trả lời trong khoảng 0,3 giây.
A12: 4 | B12: Trong dữ liệu có những chỉ số nào? | C12: 503 | D12: technical_failure | E12: 4.2 | F12: =IF(OR(D12="ok",D12="no_data",D12="needs_clarification"),"Có","Không") | G12: =IF(F12="Có",E12,"")
A13: 4 | B13: Doanh thu tháng này | C13: 200 | D13: ok | E13: 0.26 | F13: =IF(OR(D13="ok",D13="no_data",D13="needs_clarification"),"Có","Không") | G13: =IF(F13="Có",E13,"") | I13: Cách đọc các chỉ số đo tải
A14: 2 | B14: Dự báo doanh thu 6 tháng tới | C14: 503 | D14: technical_failure | E14: 3.36 | F14: =IF(OR(D14="ok",D14="no_data",D14="needs_clarification"),"Có","Không") | G14: =IF(F14="Có",E14,"") | I14: Số yêu cầu | J14: Tổng số câu hỏi gửi trong lần đo (5 người dùng, mỗi người 12 câu).
A15: 2 | B15: Top 3 sản phẩm bán chạy năm 2024 | C15: 503 | D15: technical_failure | E15: 2.24 | F15: =IF(OR(D15="ok",D15="no_data",D15="needs_clarification"),"Có","Không") | G15: =IF(F15="Có",E15,"") | I15: Trả lời được | J15: Số yêu cầu có kết quả hợp lệ (có số liệu, hỏi lại hoặc không có dữ liệu). Phần còn lại là lỗi, ở đây đều là AI bận.
A16: 2 | B16: Sản lượng theo nhà máy năm 2024 | C16: 200 | D16: ok | E16: 0.34 | F16: =IF(OR(D16="ok",D16="no_data",D16="needs_clarification"),"Có","Không") | G16: =IF(F16="Có",E16,"") | I16: Tỷ lệ trả lời được | J16: Trả lời được chia Số yêu cầu.
A17: 3 | B17: Nhà máy nào có tỷ lệ phế phẩm cao nhất quý trước? | C17: 200 | D17: ok | E17: 11.1 | F17: =IF(OR(D17="ok",D17="no_data",D17="needs_clarification"),"Có","Không") | G17: =IF(F17="Có",E17,"") | I17: Dưới 15 giây | J17: Số yêu cầu trả lời được trong tối đa 15 giây.
A18: 1 | B18: Khu vực nào bán tốt nhất năm ngoái? | C18: 200 | D18: needs_clarification | E18: 9.08 | F18: =IF(OR(D18="ok",D18="no_data",D18="needs_clarification"),"Có","Không") | G18: =IF(F18="Có",E18,"") | I18: Tỷ lệ yêu cầu dưới 15 giây | J18: Chỉ số của mục tiêu hiệu năng: phần trăm tất cả yêu cầu hoàn tất dưới 15 giây. Mục tiêu trong tài liệu là từ 95% trở lên.
A19: 4 | B19: Top 3 sản phẩm bán chạy năm 2024 | C19: 503 | D19: technical_failure | E19: 6.38 | F19: =IF(OR(D19="ok",D19="no_data",D19="needs_clarification"),"Có","Không") | G19: =IF(F19="Có",E19,"") | I19: p50 | J19: Mức giữa: một nửa số câu trả lời nhanh hơn mức này (giây). Thấp vì phần lớn câu không cần AI.
A20: 5 | B20: Khu vực nào bán tốt nhất năm ngoái? | C20: 503 | D20: technical_failure | E20: 6.97 | F20: =IF(OR(D20="ok",D20="no_data",D20="needs_clarification"),"Có","Không") | G20: =IF(F20="Có",E20,"") | I20: Thời gian lớn nhất | J20: Câu chậm nhất trong lần đo (giây).
A21: 5 | B21: Trong dữ liệu có những chỉ số nào? | C21: 503 | D21: technical_failure | E21: 0.79 | F21: =IF(OR(D21="ok",D21="no_data",D21="needs_clarification"),"Có","Không") | G21: =IF(F21="Có",E21,"") | I21: Cột Trả lời được? / Giây | J21: Cột F đánh dấu từng yêu cầu có trả lời được hay không; cột G là thời gian của câu trả lời được, dùng để tính p50 và số câu dưới 15 giây.
A22: 4 | B22: Doanh thu trung bình mỗi tháng năm 2024 là bao nhiêu? | C22: 503 | D22: technical_failure | E22: 1.1 | F22: =IF(OR(D22="ok",D22="no_data",D22="needs_clarification"),"Có","Không") | G22: =IF(F22="Có",E22,"")
A23: 2 | B23: Trong dữ liệu có những chỉ số nào? | C23: 503 | D23: technical_failure | E23: 4.5 | F23: =IF(OR(D23="ok",D23="no_data",D23="needs_clarification"),"Có","Không") | G23: =IF(F23="Có",E23,"")
A24: 1 | B24: Dự báo doanh thu 6 tháng tới | C24: 503 | D24: technical_failure | E24: 1.14 | F24: =IF(OR(D24="ok",D24="no_data",D24="needs_clarification"),"Có","Không") | G24: =IF(F24="Có",E24,"")
A25: 4 | B25: Tỷ lệ phế phẩm quý trước | C25: 200 | D25: ok | E25: 0.29 | F25: =IF(OR(D25="ok",D25="no_data",D25="needs_clarification"),"Có","Không") | G25: =IF(F25="Có",E25,"")
A26: 2 | B26: Tỷ lệ phế phẩm quý trước | C26: 200 | D26: ok | E26: 0.32 | F26: =IF(OR(D26="ok",D26="no_data",D26="needs_clarification"),"Có","Không") | G26: =IF(F26="Có",E26,"")
A27: 2 | B27: Doanh thu theo khu vực quý trước | C27: 200 | D27: ok | E27: 0.3 | F27: =IF(OR(D27="ok",D27="no_data",D27="needs_clarification"),"Có","Không") | G27: =IF(F27="Có",E27,"")
A28: 1 | B28: Trong dữ liệu có những chỉ số nào? | C28: 503 | D28: technical_failure | E28: 0.98 | F28: =IF(OR(D28="ok",D28="no_data",D28="needs_clarification"),"Có","Không") | G28: =IF(F28="Có",E28,"")
A29: 1 | B29: So sánh doanh thu năm 2023 và 2024 | C29: 200 | D29: ok | E29: 0.44 | F29: =IF(OR(D29="ok",D29="no_data",D29="needs_clarification"),"Có","Không") | G29: =IF(F29="Có",E29,"")
A30: 1 | B30: Sản lượng theo nhà máy năm 2024 | C30: 200 | D30: ok | E30: 0.34 | F30: =IF(OR(D30="ok",D30="no_data",D30="needs_clarification"),"Có","Không") | G30: =IF(F30="Có",E30,"")
A31: 1 | B31: Doanh thu Canada năm 2024, rồi sản lượng Factory A tháng trước | C31: 200 | D31: ok | E31: 0.51 | F31: =IF(OR(D31="ok",D31="no_data",D31="needs_clarification"),"Có","Không") | G31: =IF(F31="Có",E31,"")
A32: 5 | B32: Dự báo doanh thu 6 tháng tới | C32: 503 | D32: technical_failure | E32: 2.27 | F32: =IF(OR(D32="ok",D32="no_data",D32="needs_clarification"),"Có","Không") | G32: =IF(F32="Có",E32,"")
A33: 1 | B33: Tỷ lệ phế phẩm quý trước | C33: 200 | D33: ok | E33: 0.31 | F33: =IF(OR(D33="ok",D33="no_data",D33="needs_clarification"),"Có","Không") | G33: =IF(F33="Có",E33,"")
... A61: 3 | B61: Doanh thu tháng này | C61: 200 | D61: ok | E61: 0.27 | F61: =IF(OR(D61="ok",D61="no_data",D61="needs_clarification"),"Có","Không") | G61: =IF(F61="Có",E61,"")

Sheet Backtest dự báo
A1: Chỉ số | B1: Gốc dự báo (tháng cuối của lịch sử) | C1: Chân trời (tháng) | D1: Thực tế | E1: ETS (điểm) | F1: ETS cận dưới 95% | G1: ETS cận trên 95% | H1: Naive (tháng trước) | I1: Seasonal naive (cùng tháng năm trước) | J1: Trung bình 3 tháng | K1: Trong khoảng 95%? | M1: Tóm tắt theo chân trời (công thức từ dữ liệu bên trái)
A2: revenue | B2: 2024-04-01 | C2: 1 | D2: 3258341.1 | E2: 2663850.5 | F2: 1027372.4 | G2: 4300328.6 | H2: 2533057.4 | I2: 3074602.8 | J2: 2761118.4 | K2: =IF(AND(D2>=F2,D2<=G2),1,0) | M2: Chỉ số | N2: Chân trời | O2: Số mẫu | P2: WAPE ETS | Q2: WAPE Naive | R2: WAPE Seasonal naive | S2: WAPE TB 3 tháng | T2: Phủ khoảng 95%
A3: revenue | B3: 2024-04-01 | C3: 2 | D3: 5063798.4 | E3: 2663850.5 | F3: 965312.33 | G3: 4362388.7 | H3: 2533057.4 | I3: 4099354.4 | J3: 2761118.4 | K3: =IF(AND(D3>=F3,D3<=G3),1,0) | M3: revenue | N3: 1 | O3: =SUMPRODUCT(($A$2:$A$119="revenue")*($C$2:$C$119=1)) | P3: =SUMPRODUCT(($A$2:$A$119="revenue")*($C$2:$C$119=1)*ABS($D$2:$D$119-$E$2:$E$119))/SUMPRODUCT(($A$2:$A$119="revenue")*($C$2:$C$119=1)*$D$2:$D$119) | Q3: =SUMPRODUCT(($A$2:$A$119="revenue")*($C$2:$C$119=1)*ABS($D$2:$D$119-$H$2:$H$119))/SUMPRODUCT(($A$2:$A$119="revenue")*($C$2:$C$119=1)*$D$2:$D$119) | R3: =SUMPRODUCT(($A$2:$A$119="revenue")*($C$2:$C$119=1)*ABS($D$2:$D$119-$I$2:$I$119))/SUMPRODUCT(($A$2:$A$119="revenue")*($C$2:$C$119=1)*$D$2:$D$119) | S3: =SUMPRODUCT(($A$2:$A$119="revenue")*($C$2:$C$119=1)*ABS($D$2:$D$119-$J$2:$J$119))/SUMPRODUCT(($A$2:$A$119="revenue")*($C$2:$C$119=1)*$D$2:$D$119) | T3: =SUMPRODUCT(($A$2:$A$119="revenue")*($C$2:$C$119=1)*$K$2:$K$119)/O3
A4: revenue | B4: 2024-04-01 | C4: 3 | D4: 4918580.2 | E4: 2663850.5 | F4: 905441.23 | G4: 4422259.8 | H4: 2533057.4 | I4: 3417953.9 | J4: 2761118.4 | K4: =IF(AND(D4>=F4,D4<=G4),1,0) | M4: revenue | N4: 2 | O4: =SUMPRODUCT(($A$2:$A$119="revenue")*($C$2:$C$119=2)) | P4: =SUMPRODUCT(($A$2:$A$119="revenue")*($C$2:$C$119=2)*ABS($D$2:$D$119-$E$2:$E$119))/SUMPRODUCT(($A$2:$A$119="revenue")*($C$2:$C$119=2)*$D$2:$D$119) | Q4: =SUMPRODUCT(($A$2:$A$119="revenue")*($C$2:$C$119=2)*ABS($D$2:$D$119-$H$2:$H$119))/SUMPRODUCT(($A$2:$A$119="revenue")*($C$2:$C$119=2)*$D$2:$D$119) | R4: =SUMPRODUCT(($A$2:$A$119="revenue")*($C$2:$C$119=2)*ABS($D$2:$D$119-$I$2:$I$119))/SUMPRODUCT(($A$2:$A$119="revenue")*($C$2:$C$119=2)*$D$2:$D$119) | S4: =SUMPRODUCT(($A$2:$A$119="revenue")*($C$2:$C$119=2)*ABS($D$2:$D$119-$J$2:$J$119))/SUMPRODUCT(($A$2:$A$119="revenue")*($C$2:$C$119=2)*$D$2:$D$119) | T4: =SUMPRODUCT(($A$2:$A$119="revenue")*($C$2:$C$119=2)*$K$2:$K$119)/O4
A5: revenue | B5: 2024-04-01 | C5: 4 | D5: 3325296.1 | E5: 2663850.5 | F5: 847542.6 | G5: 4480158.4 | H5: 2533057.4 | I5: 2175637.2 | J5: 2761118.4 | K5: =IF(AND(D5>=F5,D5<=G5),1,0) | M5: revenue | N5: 3 | O5: =SUMPRODUCT(($A$2:$A$119="revenue")*($C$2:$C$119=3)) | P5: =SUMPRODUCT(($A$2:$A$119="revenue")*($C$2:$C$119=3)*ABS($D$2:$D$119-$E$2:$E$119))/SUMPRODUCT(($A$2:$A$119="revenue")*($C$2:$C$119=3)*$D$2:$D$119) | Q5: =SUMPRODUCT(($A$2:$A$119="revenue")*($C$2:$C$119=3)*ABS($D$2:$D$119-$H$2:$H$119))/SUMPRODUCT(($A$2:$A$119="revenue")*($C$2:$C$119=3)*$D$2:$D$119) | R5: =SUMPRODUCT(($A$2:$A$119="revenue")*($C$2:$C$119=3)*ABS($D$2:$D$119-$I$2:$I$119))/SUMPRODUCT(($A$2:$A$119="revenue")*($C$2:$C$119=3)*$D$2:$D$119) | S5: =SUMPRODUCT(($A$2:$A$119="revenue")*($C$2:$C$119=3)*ABS($D$2:$D$119-$J$2:$J$119))/SUMPRODUCT(($A$2:$A$119="revenue")*($C$2:$C$119=3)*$D$2:$D$119) | T5: =SUMPRODUCT(($A$2:$A$119="revenue")*($C$2:$C$119=3)*$K$2:$K$119)/O5
A6: revenue | B6: 2024-04-01 | C6: 5 | D6: 4539829 | E6: 2663850.5 | F6: 791433.44 | G6: 4536267.5 | H6: 2533057.4 | I6: 3454151.9 | J6: 2761118.4 | K6: =IF(AND(D6>=F6,D6<=G6),1,0) | M6: revenue | N6: 4 | O6: =SUMPRODUCT(($A$2:$A$119="revenue")*($C$2:$C$119=4)) | P6: =SUMPRODUCT(($A$2:$A$119="revenue")*($C$2:$C$119=4)*ABS($D$2:$D$119-$E$2:$E$119))/SUMPRODUCT(($A$2:$A$119="revenue")*($C$2:$C$119=4)*$D$2:$D$119) | Q6: =SUMPRODUCT(($A$2:$A$119="revenue")*($C$2:$C$119=4)*ABS($D$2:$D$119-$H$2:$H$119))/SUMPRODUCT(($A$2:$A$119="revenue")*($C$2:$C$119=4)*$D$2:$D$119) | R6: =SUMPRODUCT(($A$2:$A$119="revenue")*($C$2:$C$119=4)*ABS($D$2:$D$119-$I$2:$I$119))/SUMPRODUCT(($A$2:$A$119="revenue")*($C$2:$C$119=4)*$D$2:$D$119) | S6: =SUMPRODUCT(($A$2:$A$119="revenue")*($C$2:$C$119=4)*ABS($D$2:$D$119-$J$2:$J$119))/SUMPRODUCT(($A$2:$A$119="revenue")*($C$2:$C$119=4)*$D$2:$D$119) | T6: =SUMPRODUCT(($A$2:$A$119="revenue")*($C$2:$C$119=4)*$K$2:$K$119)/O6
A7: revenue | B7: 2024-04-01 | C7: 6 | D7: 4820725.3 | E7: 2663850.5 | F7: 736957.43 | G7: 4590743.5 | H7: 2533057.4 | I7: 2544091.1 | J7: 2761118.4 | K7: =IF(AND(D7>=F7,D7<=G7),1,0) | M7: revenue | N7: 5 | O7: =SUMPRODUCT(($A$2:$A$119="revenue")*($C$2:$C$119=5)) | P7: =SUMPRODUCT(($A$2:$A$119="revenue")*($C$2:$C$119=5)*ABS($D$2:$D$119-$E$2:$E$119))/SUMPRODUCT(($A$2:$A$119="revenue")*($C$2:$C$119=5)*$D$2:$D$119) | Q7: =SUMPRODUCT(($A$2:$A$119="revenue")*($C$2:$C$119=5)*ABS($D$2:$D$119-$H$2:$H$119))/SUMPRODUCT(($A$2:$A$119="revenue")*($C$2:$C$119=5)*$D$2:$D$119) | R7: =SUMPRODUCT(($A$2:$A$119="revenue")*($C$2:$C$119=5)*ABS($D$2:$D$119-$I$2:$I$119))/SUMPRODUCT(($A$2:$A$119="revenue")*($C$2:$C$119=5)*$D$2:$D$119) | S7: =SUMPRODUCT(($A$2:$A$119="revenue")*($C$2:$C$119=5)*ABS($D$2:$D$119-$J$2:$J$119))/SUMPRODUCT(($A$2:$A$119="revenue")*($C$2:$C$119=5)*$D$2:$D$119) | T7: =SUMPRODUCT(($A$2:$A$119="revenue")*($C$2:$C$119=5)*$K$2:$K$119)/O7
A8: revenue | B8: 2024-05-01 | C8: 1 | D8: 5063798.4 | E8: 2832068.4 | F8: 1214057.5 | G8: 4450079.3 | H8: 3258341.1 | I8: 4099354.4 | J8: 3066145.3 | K8: =IF(AND(D8>=F8,D8<=G8),1,0) | M8: revenue | N8: 6 | O8: =SUMPRODUCT(($A$2:$A$119="revenue")*($C$2:$C$119=6)) | P8: =SUMPRODUCT(($A$2:$A$119="revenue")*($C$2:$C$119=6)*ABS($D$2:$D$119-$E$2:$E$119))/SUMPRODUCT(($A$2:$A$119="revenue")*($C$2:$C$119=6)*$D$2:$D$119) | Q8: =SUMPRODUCT(($A$2:$A$119="revenue")*($C$2:$C$119=6)*ABS($D$2:$D$119-$H$2:$H$119))/SUMPRODUCT(($A$2:$A$119="revenue")*($C$2:$C$119=6)*$D$2:$D$119) | R8: =SUMPRODUCT(($A$2:$A$119="revenue")*($C$2:$C$119=6)*ABS($D$2:$D$119-$I$2:$I$119))/SUMPRODUCT(($A$2:$A$119="revenue")*($C$2:$C$119=6)*$D$2:$D$119) | S8: =SUMPRODUCT(($A$2:$A$119="revenue")*($C$2:$C$119=6)*ABS($D$2:$D$119-$J$2:$J$119))/SUMPRODUCT(($A$2:$A$119="revenue")*($C$2:$C$119=6)*$D$2:$D$119) | T8: =SUMPRODUCT(($A$2:$A$119="revenue")*($C$2:$C$119=6)*$K$2:$K$119)/O8
A9: revenue | B9: 2024-05-01 | C9: 2 | D9: 4918580.2 | E9: 2832068.4 | F9: 1150952.7 | G9: 4513184.1 | H9: 3258341.1 | I9: 3417953.9 | J9: 3066145.3 | K9: =IF(AND(D9>=F9,D9<=G9),1,0) | M9: production_output | N9: 1 | O9: =SUMPRODUCT(($A$2:$A$119="production_output")*($C$2:$C$119=1)) | P9: =SUMPRODUCT(($A$2:$A$119="production_output")*($C$2:$C$119=1)*ABS($D$2:$D$119-$E$2:$E$119))/SUMPRODUCT(($A$2:$A$119="production_output")*($C$2:$C$119=1)*$D$2:$D$119) | Q9: =SUMPRODUCT(($A$2:$A$119="production_output")*($C$2:$C$119=1)*ABS($D$2:$D$119-$H$2:$H$119))/SUMPRODUCT(($A$2:$A$119="production_output")*($C$2:$C$119=1)*$D$2:$D$119) | R9: =SUMPRODUCT(($A$2:$A$119="production_output")*($C$2:$C$119=1)*ABS($D$2:$D$119-$I$2:$I$119))/SUMPRODUCT(($A$2:$A$119="production_output")*($C$2:$C$119=1)*$D$2:$D$119) | S9: =SUMPRODUCT(($A$2:$A$119="production_output")*($C$2:$C$119=1)*ABS($D$2:$D$119-$J$2:$J$119))/SUMPRODUCT(($A$2:$A$119="production_output")*($C$2:$C$119=1)*$D$2:$D$119) | T9: =SUMPRODUCT(($A$2:$A$119="production_output")*($C$2:$C$119=1)*$K$2:$K$119)/O9
A10: revenue | B10: 2024-05-01 | C10: 3 | D10: 3325296.1 | E10: 2832068.4 | F10: 1090132.6 | G10: 4574004.2 | H10: 3258341.1 | I10: 2175637.2 | J10: 3066145.3 | K10: =IF(AND(D10>=F10,D10<=G10),1,0) | M10: production_output | N10: 2 | O10: =SUMPRODUCT(($A$2:$A$119="production_output")*($C$2:$C$119=2)) | P10: =SUMPRODUCT(($A$2:$A$119="production_output")*($C$2:$C$119=2)*ABS($D$2:$D$119-$E$2:$E$119))/SUMPRODUCT(($A$2:$A$119="production_output")*($C$2:$C$119=2)*$D$2:$D$119) | Q10: =SUMPRODUCT(($A$2:$A$119="production_output")*($C$2:$C$119=2)*ABS($D$2:$D$119-$H$2:$H$119))/SUMPRODUCT(($A$2:$A$119="production_output")*($C$2:$C$119=2)*$D$2:$D$119) | R10: =SUMPRODUCT(($A$2:$A$119="production_output")*($C$2:$C$119=2)*ABS($D$2:$D$119-$I$2:$I$119))/SUMPRODUCT(($A$2:$A$119="production_output")*($C$2:$C$119=2)*$D$2:$D$119) | S10: =SUMPRODUCT(($A$2:$A$119="production_output")*($C$2:$C$119=2)*ABS($D$2:$D$119-$J$2:$J$119))/SUMPRODUCT(($A$2:$A$119="production_output")*($C$2:$C$119=2)*$D$2:$D$119) | T10: =SUMPRODUCT(($A$2:$A$119="production_output")*($C$2:$C$119=2)*$K$2:$K$119)/O10
A11: revenue | B11: 2024-05-01 | C11: 4 | D11: 4539829 | E11: 2832068.4 | F11: 1031365.5 | G11: 4632771.3 | H11: 3258341.1 | I11: 3454151.9 | J11: 3066145.3 | K11: =IF(AND(D11>=F11,D11<=G11),1,0) | M11: production_output | N11: 3 | O11: =SUMPRODUCT(($A$2:$A$119="production_output")*($C$2:$C$119=3)) | P11: =SUMPRODUCT(($A$2:$A$119="production_output")*($C$2:$C$119=3)*ABS($D$2:$D$119-$E$2:$E$119))/SUMPRODUCT(($A$2:$A$119="production_output")*($C$2:$C$119=3)*$D$2:$D$119) | Q11: =SUMPRODUCT(($A$2:$A$119="production_output")*($C$2:$C$119=3)*ABS($D$2:$D$119-$H$2:$H$119))/SUMPRODUCT(($A$2:$A$119="production_output")*($C$2:$C$119=3)*$D$2:$D$119) | R11: =SUMPRODUCT(($A$2:$A$119="production_output")*($C$2:$C$119=3)*ABS($D$2:$D$119-$I$2:$I$119))/SUMPRODUCT(($A$2:$A$119="production_output")*($C$2:$C$119=3)*$D$2:$D$119) | S11: =SUMPRODUCT(($A$2:$A$119="production_output")*($C$2:$C$119=3)*ABS($D$2:$D$119-$J$2:$J$119))/SUMPRODUCT(($A$2:$A$119="production_output")*($C$2:$C$119=3)*$D$2:$D$119) | T11: =SUMPRODUCT(($A$2:$A$119="production_output")*($C$2:$C$119=3)*$K$2:$K$119)/O11
A12: revenue | B12: 2024-05-01 | C12: 5 | D12: 4820725.3 | E12: 2832068.4 | F12: 974456.6 | G12: 4689680.2 | H12: 3258341.1 | I12: 2544091.1 | J12: 3066145.3 | K12: =IF(AND(D12>=F12,D12<=G12),1,0) | M12: production_output | N12: 4 | O12: =SUMPRODUCT(($A$2:$A$119="production_output")*($C$2:$C$119=4)) | P12: =SUMPRODUCT(($A$2:$A$119="production_output")*($C$2:$C$119=4)*ABS($D$2:$D$119-$E$2:$E$119))/SUMPRODUCT(($A$2:$A$119="production_output")*($C$2:$C$119=4)*$D$2:$D$119) | Q12: =SUMPRODUCT(($A$2:$A$119="production_output")*($C$2:$C$119=4)*ABS($D$2:$D$119-$H$2:$H$119))/SUMPRODUCT(($A$2:$A$119="production_output")*($C$2:$C$119=4)*$D$2:$D$119) | R12: =SUMPRODUCT(($A$2:$A$119="production_output")*($C$2:$C$119=4)*ABS($D$2:$D$119-$I$2:$I$119))/SUMPRODUCT(($A$2:$A$119="production_output")*($C$2:$C$119=4)*$D$2:$D$119) | S12: =SUMPRODUCT(($A$2:$A$119="production_output")*($C$2:$C$119=4)*ABS($D$2:$D$119-$J$2:$J$119))/SUMPRODUCT(($A$2:$A$119="production_output")*($C$2:$C$119=4)*$D$2:$D$119) | T12: =SUMPRODUCT(($A$2:$A$119="production_output")*($C$2:$C$119=4)*$K$2:$K$119)/O12
A13: revenue | B13: 2024-05-01 | C13: 6 | D13: 3291238.3 | E13: 2832068.4 | F13: 919240.08 | G13: 4744896.7 | H13: 3258341.1 | I13: 1872702 | J13: 3066145.3 | K13: =IF(AND(D13>=F13,D13<=G13),1,0) | M13: production_output | N13: 5 | O13: =SUMPRODUCT(($A$2:$A$119="production_output")*($C$2:$C$119=5)) | P13: =SUMPRODUCT(($A$2:$A$119="production_output")*($C$2:$C$119=5)*ABS($D$2:$D$119-$E$2:$E$119))/SUMPRODUCT(($A$2:$A$119="production_output")*($C$2:$C$119=5)*$D$2:$D$119) | Q13: =SUMPRODUCT(($A$2:$A$119="production_output")*($C$2:$C$119=5)*ABS($D$2:$D$119-$H$2:$H$119))/SUMPRODUCT(($A$2:$A$119="production_output")*($C$2:$C$119=5)*$D$2:$D$119) | R13: =SUMPRODUCT(($A$2:$A$119="production_output")*($C$2:$C$119=5)*ABS($D$2:$D$119-$I$2:$I$119))/SUMPRODUCT(($A$2:$A$119="production_output")*($C$2:$C$119=5)*$D$2:$D$119) | S13: =SUMPRODUCT(($A$2:$A$119="production_output")*($C$2:$C$119=5)*ABS($D$2:$D$119-$J$2:$J$119))/SUMPRODUCT(($A$2:$A$119="production_output")*($C$2:$C$119=5)*$D$2:$D$119) | T13: =SUMPRODUCT(($A$2:$A$119="production_output")*($C$2:$C$119=5)*$K$2:$K$119)/O13
A14: revenue | B14: 2024-06-01 | C14: 1 | D14: 4918580.2 | E14: 3535151.9 | F14: 1869787.9 | G14: 5200515.9 | H14: 5063798.4 | I14: 3417953.9 | J14: 3618399 | K14: =IF(AND(D14>=F14,D14<=G14),1,0) | M14: production_output | N14: 6 | O14: =SUMPRODUCT(($A$2:$A$119="production_output")*($C$2:$C$119=6)) | P14: =SUMPRODUCT(($A$2:$A$119="production_output")*($C$2:$C$119=6)*ABS($D$2:$D$119-$E$2:$E$119))/SUMPRODUCT(($A$2:$A$119="production_output")*($C$2:$C$119=6)*$D$2:$D$119) | Q14: =SUMPRODUCT(($A$2:$A$119="production_output")*($C$2:$C$119=6)*ABS($D$2:$D$119-$H$2:$H$119))/SUMPRODUCT(($A$2:$A$119="production_output")*($C$2:$C$119=6)*$D$2:$D$119) | R14: =SUMPRODUCT(($A$2:$A$119="production_output")*($C$2:$C$119=6)*ABS($D$2:$D$119-$I$2:$I$119))/SUMPRODUCT(($A$2:$A$119="production_output")*($C$2:$C$119=6)*$D$2:$D$119) | S14: =SUMPRODUCT(($A$2:$A$119="production_output")*($C$2:$C$119=6)*ABS($D$2:$D$119-$J$2:$J$119))/SUMPRODUCT(($A$2:$A$119="production_output")*($C$2:$C$119=6)*$D$2:$D$119) | T14: =SUMPRODUCT(($A$2:$A$119="production_output")*($C$2:$C$119=6)*$K$2:$K$119)/O14
A15: revenue | B15: 2024-06-01 | C15: 2 | D15: 3325296.1 | E15: 3615391.2 | F15: 1949997.2 | G15: 5280785.2 | H15: 5063798.4 | I15: 2175637.2 | J15: 3618399 | K15: =IF(AND(D15>=F15,D15<=G15),1,0)
A16: revenue | B16: 2024-06-01 | C16: 3 | D16: 4539829 | E16: 3695630.5 | F16: 2030183.2 | G16: 5361077.8 | H16: 5063798.4 | I16: 3454151.9 | J16: 3618399 | K16: =IF(AND(D16>=F16,D16<=G16),1,0)
A17: revenue | B17: 2024-06-01 | C17: 4 | D17: 4820725.3 | E17: 3775869.8 | F17: 2110339.2 | G17: 5441400.3 | H17: 5063798.4 | I17: 2544091.1 | J17: 3618399 | K17: =IF(AND(D17>=F17,D17<=G17),1,0) | M17: Cách đọc backtest dự báo
A18: revenue | B18: 2024-06-01 | C18: 5 | D18: 3291238.3 | E18: 3856109.1 | F18: 2190458.6 | G18: 5521759.5 | H18: 5063798.4 | I18: 1872702 | J18: 3618399 | K18: =IF(AND(D18>=F18,D18<=G18),1,0) | M18: Backtest là gì | O18: Lùi về quá khứ giả vờ chưa biết tương lai, dự báo, rồi so với số thật đã ghi nhận. Cho biết dự báo sai bao nhiêu nếu dùng thật.
A19: revenue | B19: 2024-06-01 | C19: 6 | D19: 4082853.6 | E19: 3936348.4 | F19: 2270534.8 | G19: 5602162 | H19: 5063798.4 | I19: 2829404.8 | J19: 3618399 | K19: =IF(AND(D19>=F19,D19<=G19),1,0) | M19: Gốc dự báo | O19: Tháng cuối cùng của phần lịch sử được dùng để dự báo (mỗi gốc cần ít nhất 24 tháng lịch sử).
A20: revenue | B20: 2024-07-01 | C20: 1 | D20: 3325296.1 | E20: 3623691.8 | F20: 1896973.2 | G20: 5350410.3 | H20: 4918580.2 | I20: 2175637.2 | J20: 4413573.2 | K20: =IF(AND(D20>=F20,D20<=G20),1,0) | M20: Chân trời | O20: Dự báo cho tháng thứ mấy sau gốc: 1 là tháng kế tiếp, 6 là tháng thứ sáu.
A21: revenue | B21: 2024-07-01 | C21: 2 | D21: 4539829 | E21: 3706697.9 | F21: 1979948.3 | G21: 5433447.5 | H21: 4918580.2 | I21: 3454151.9 | J21: 4413573.2 | K21: =IF(AND(D21>=F21,D21<=G21),1,0) | M21: ETS | O21: Phương pháp dự báo của hệ thống (làm trơn hàm mũ), kèm cận dưới và cận trên của khoảng tin cậy 95%.
A22: revenue | B22: 2024-07-01 | C22: 3 | D22: 4820725.3 | E22: 3789704.1 | F22: 2062899.2 | G22: 5516508.9 | H22: 4918580.2 | I22: 2544091.1 | J22: 4413573.2 | K22: =IF(AND(D22>=F22,D22<=G22),1,0) | M22: Naive | O22: Phương pháp đơn giản: dự báo bằng đúng giá trị của tháng gần nhất.
A23: revenue | B23: 2024-07-01 | C23: 4 | D23: 3291238.3 | E23: 3872710.2 | F23: 2145819 | G23: 5599601.4 | H23: 4918580.2 | I23: 1872702 | J23: 4413573.2 | K23: =IF(AND(D23>=F23,D23<=G23),1,0) | M23: Seasonal naive | O23: Dự báo bằng giá trị của cùng tháng năm trước.
A24: revenue | B24: 2024-07-01 | C24: 5 | D24: 4082853.6 | E24: 3955716.4 | F24: 2228700.9 | G24: 5682731.9 | H24: 4918580.2 | I24: 2829404.8 | J24: 4413573.2 | K24: =IF(AND(D24>=F24,D24<=G24),1,0) | M24: Trung bình 3 tháng | O24: Dự báo bằng trung bình của 3 tháng gần nhất.
A25: revenue | B25: 2024-07-01 | C25: 6 | D25: 4276427.7 | E25: 4038722.5 | F25: 2311537.8 | G25: 5765907.2 | H25: 4918580.2 | I25: 2087872.5 | J25: 4413573.2 | K25: =IF(AND(D25>=F25,D25<=G25),1,0) | M25: WAPE | O25: Sai số theo phần trăm: tổng độ lệch tuyệt đối chia tổng giá trị thật. 20% nghĩa là dự báo lệch trung bình khoảng 20% so với số thật; càng thấp càng tốt. Dùng để so ETS với các phương pháp đơn giản.
A26: revenue | B26: 2024-08-01 | C26: 1 | D26: 4539829 | E26: 3704907.5 | F26: 2011746.2 | G26: 5398068.9 | H26: 3325296.1 | I26: 3454151.9 | J26: 4435891.6 | K26: =IF(AND(D26>=F26,D26<=G26),1,0) | M26: Phủ khoảng 95% | O26: Tỷ lệ số thật nằm trong khoảng tin cậy 95% mà hệ thống đưa ra. Nếu khoảng chuẩn thì khoảng 95%; thấp hơn nghĩa là khoảng đưa ra hẹp hơn thực tế.
A27: revenue | B27: 2024-08-01 | C27: 2 | D27: 4820725.3 | E27: 3787316.9 | F27: 2094125 | G27: 5480508.7 | H27: 3325296.1 | I27: 2544091.1 | J27: 4435891.6 | K27: =IF(AND(D27>=F27,D27<=G27),1,0) | M27: Số mẫu | O27: Số cặp (gốc, chân trời) dùng để tính. Số mẫu nhỏ thì kết luận kém chắc chắn.
A28: revenue | B28: 2024-08-01 | C28: 3 | D28: 3291238.3 | E28: 3869726.2 | F28: 2176480.2 | G28: 5562972.3 | H28: 3325296.1 | I28: 1872702 | J28: 4435891.6 | K28: =IF(AND(D28>=F28,D28<=G28),1,0) | M28: Cách kết luận | O28: Nếu WAPE của ETS xấp xỉ các phương pháp đơn giản thì ETS không hơn gì cách đơn giản. Dữ liệu này mô phỏng và ngắn nên chỉ để tham khảo.
A29: revenue | B29: 2024-08-01 | C29: 4 | D29: 4082853.6 | E29: 3952135.6 | F29: 2258804.9 | G29: 5645466.3 | H29: 3325296.1 | I29: 2829404.8 | J29: 4435891.6 | K29: =IF(AND(D29>=F29,D29<=G29),1,0)
A30: revenue | B30: 2024-08-01 | C30: 5 | D30: 4276427.7 | E30: 4034545 | F30: 2341092.4 | G30: 5727997.5 | H30: 3325296.1 | I30: 2087872.5 | J30: 4435891.6 | K30: =IF(AND(D30>=F30,D30<=G30),1,0) | M30: Cách đo: lùi dần gốc dự báo, mỗi gốc cần tối thiểu 24 tháng lịch sử; dự báo 1 đến 6 tháng rồi so với số đã ghi nhận. WAPE = tổng |sai số| / tổng giá trị thực.
A31: revenue | B31: 2024-08-01 | C31: 6 | D31: 3565879.3 | E31: 4116954.3 | F31: 2423335.9 | G31: 5810572.8 | H31: 3325296.1 | I31: 2343260.2 | J31: 4435891.6 | K31: =IF(AND(D31>=F31,D31<=G31),1,0) | M31: Dữ liệu: tổng doanh thu và tổng sản lượng theo tháng đầy đủ, từ kho AdventureWorks (mô phỏng), chỉ 11 đến 12 gốc dự báo nên số mẫu mỗi chân trời nhỏ (7 đến 12).
A32: revenue | B32: 2024-09-01 | C32: 1 | D32: 4820725.3 | E32: 3792326.4 | F32: 2101491.4 | G32: 5483161.4 | H32: 4539829 | I32: 2544091.1 | J32: 4261235.1 | K32: =IF(AND(D32>=F32,D32<=G32),1,0) | M32: Kết luận trung thực: ETS tương đương các phương pháp đơn giản (naive, trung bình 3 tháng) trên dữ liệu này, sai số khoảng 18% đến 26%. Khoảng tin cậy 95% thực tế phủ 67% đến 100%, thấp hơn 95% ở vài chân trời với doanh thu.
A33: revenue | B33: 2024-09-01 | C33: 2 | D33: 3291238.3 | E33: 3876405.6 | F33: 2185540.2 | G33: 5567271.1 | H33: 4539829 | I33: 1872702 | J33: 4261235.1 | K33: =IF(AND(D33>=F33,D33<=G33),1,0) | M33: Ý nghĩa: không nên quảng bá độ chính xác của dự báo; cơ chế từ chối khi thử lại lệch quá 35% và nhãn 'dự báo, không phải số đã ghi nhận' là cần thiết. Cần dữ liệu thật dài hơn để đánh giá lại.
A34: revenue | B34: 2024-09-01 | C34: 3 | D34: 4082853.6 | E34: 3960484.8 | F34: 2269565.3 | G34: 5651404.4 | H34: 4539829 | I34: 2829404.8 | J34: 4261235.1 | K34: =IF(AND(D34>=F34,D34<=G34),1,0)
A35: revenue | B35: 2024-09-01 | C35: 4 | D35: 4276427.7 | E35: 4044564 | F35: 2353559.9 | G35: 5735568.1 | H35: 4539829 | I35: 2087872.5 | J35: 4261235.1 | K35: =IF(AND(D35>=F35,D35<=G35),1,0)
A36: revenue | B36: 2024-09-01 | C36: 5 | D36: 3565879.3 | E36: 4128643.2 | F36: 2437517.4 | G36: 5819769 | H36: 4539829 | I36: 2343260.2 | J36: 4261235.1 | K36: =IF(AND(D36>=F36,D36<=G36),1,0)
A37: revenue | B37: 2024-09-01 | C37: 6 | D37: 4987901.5 | E37: 4212722.4 | F37: 2521431 | G37: 5904013.9 | H37: 4539829 | I37: 3407037.4 | J37: 4261235.1 | K37: =IF(AND(D37>=F37,D37<=G37),1,0)
A38: revenue | B38: 2024-10-01 | C38: 1 | D38: 3291238.3 | E38: 3940049.9 | F38: 2237465 | G38: 5642634.7 | H38: 4820725.3 | I38: 1872702 | J38: 4228616.8 | K38: =IF(AND(D38>=F38,D38<=G38),1,0)
A39: revenue | B39: 2024-10-01 | C39: 2 | D39: 4082853.6 | E39: 4032043 | F39: 2329373 | G39: 5734713 | H39: 4820725.3 | I39: 2829404.8 | J39: 4228616.8 | K39: =IF(AND(D39>=F39,D39<=G39),1,0)
A40: revenue | B40: 2024-10-01 | C40: 3 | D40: 4276427.7 | E40: 4124036.1 | F40: 2421199.3 | G40: 5826872.9 | H40: 4820725.3 | I40: 2087872.5 | J40: 4228616.8 | K40: =IF(AND(D40>=F40,D40<=G40),1,0)
A41: revenue | B41: 2024-10-01 | C41: 4 | D41: 3565879.3 | E41: 4216029.3 | F41: 2512916.7 | G41: 5919141.8 | H41: 4820725.3 | I41: 2343260.2 | J41: 4228616.8 | K41: =IF(AND(D41>=F41,D41<=G41),1,0)
A42: revenue | B42: 2024-10-01 | C42: 5 | D42: 4987901.5 | E42: 4308022.4 | F42: 2604498 | G42: 6011546.8 | H42: 4820725.3 | I42: 3407037.4 | J42: 4228616.8 | K42: =IF(AND(D42>=F42,D42<=G42),1,0)
A43: revenue | B43: 2024-10-01 | C43: 6 | D43: 5222758.7 | E43: 4400015.5 | F43: 2695916.1 | G43: 6104115 | H43: 4820725.3 | I43: 2533057.4 | J43: 4228616.8 | K43: =IF(AND(D43>=F43,D43<=G43),1,0)
A44: revenue | B44: 2024-11-01 | C44: 1 | D44: 4082853.6 | E44: 4025554.9 | F44: 2337509.1 | G44: 5713600.7 | H44: 3291238.3 | I44: 2829404.8 | J44: 4217264.2 | K44: =IF(AND(D44>=F44,D44<=G44),1,0)
A45: revenue | B45: 2024-11-01 | C45: 2 | D45: 4276427.7 | E45: 4114952.8 | F45: 2426822.5 | G45: 5803083 | H45: 3291238.3 | I45: 2087872.5 | J45: 4217264.2 | K45: =IF(AND(D45>=F45,D45<=G45),1,0)
... A119: production_output | B119: 2025-03-01 | C119: 2 | D119: 215217 | E119: 157939.78 | F119: 68591.669 | G119: 247287.9 | H119: 147401 | I119: 116042 | J119: 160796 | K119: =IF(AND(D119>=F119,D119<=G119),1,0)

Sheet Dữ liệu gửi cho AI
A1: Lời gọi AI | B1: Mục đích | C1: Nội dung được gửi | D1: Không gửi | E1: Công tắc điều khiển | F1: Trạng thái trên bản demo
A2: Hiểu câu hỏi (interpret) | B2: Biến câu hỏi thành phiếu yêu cầu có cấu trúc | C2: Câu hỏi (tối đa 1000 ký tự); ngày dữ liệu; toàn bộ danh mục chỉ số đã duyệt (không lọc theo vai trò), chiều và thành viên (tối đa 40 mỗi chiều, kèm mã nhà máy); phiếu yêu cầu và câu hỏi làm rõ đang chờ của lượt trước; tối đa 6 lượt gần nhất gồm câu hỏi và câu trả lời, trong đó số tiền có dấu phân cách hàng nghìn và tỷ lệ có phần thập phân đã thay bằng [số]. Số nguyên không định dạng (ví dụ 5%) không bị thay. | D2: Dòng kết quả; mật khẩu, khóa, vai trò, mã người dùng | E2: Dùng cho câu mà quy tắc của backend không đọc được. Đọc câu rõ ràng bằng quy tắc (LOCAL_INTENT_ENABLED) là tùy chọn, mặc định tắt trong Docker Compose; cũng là phương án dự phòng khi AI bận | F2: Dùng (Gemini, LiteRouter); LOCAL_INTENT_ENABLED bật
A3: Hỏi đáp về dữ liệu và câu trả lời trước (converse) | B3: Trả lời câu hỏi về chính dữ liệu (có những chỉ số nào, định nghĩa, phạm vi ngày) hoặc về câu trả lời vừa rồi | C3: Câu hỏi; metadata theo vai trò (chỉ số, chiều và thành viên, ngày phủ dữ liệu, tên bảng và cột được phép); mô tả câu trả lời trước gồm cả văn bản trả lời kèm số liệu (không che số). | D3: Bảng kết quả (các dòng); khóa, mật khẩu, mã người dùng | E3: Không có công tắc riêng; dùng khi AI được bật | F3: Dùng
A4: Đề xuất SQL (sql_candidate) | B4: Câu ngoài mẫu: AI đề xuất câu SELECT | C4: Câu hỏi; phiếu yêu cầu (không có kỳ, nhà máy, khu vực với chỉ số doanh thu, sản lượng, tỷ lệ lỗi; chỉ số tăng trưởng giữ các trường này); định nghĩa chỉ số đã duyệt; ánh xạ nguồn và quy tắc nối bảng (tăng trưởng còn kèm SQL tham chiếu); tên bảng và cột được phép theo vai trò; tối đa 2 SQL mẫu đã duyệt; lý do khi cần sửa. | D4: Dòng kết quả; toàn bộ lược đồ không giới hạn; khóa, mật khẩu, mã người dùng | E4: EXTERNAL_METADATA_ENABLED (mặc định tắt trong Docker Compose; chủ dự án duyệt ngày 20/09/2026). Khi tắt, chỉ đường mẫu chạy | F4: Bật
A5: Chọn biểu đồ (visualize) | B5: Chọn loại biểu đồ khi quy tắc không quyết được | C5: Câu hỏi; mô tả kết quả: số dòng, tên cột, kiểu cột (số, thời gian, nhóm), có thứ tự hay không, số giá trị khác nhau, có đủ dữ liệu hay không. Chỉ gửi khi quy tắc của backend (một giá trị là thẻ, trục ngày là đường, hai nhóm là cột chồng, một tổng nhỏ là tròn) không chọn được biểu đồ. | D5: Giá trị trong các dòng kết quả | E5: EXTERNAL_METADATA_ENABLED; khi tắt, kết quả luôn hiển thị dạng bảng | F5: Bật
A6: Tóm tắt bằng AI (summarize) | B6: Viết câu tóm tắt từ dòng kết quả | C6: Các dòng kết quả (nếu bật). | D6: — | E6: SEND_RESULTS_TO_LLM và EXTERNAL_RESULTS_ENABLED (mặc định tắt); câu tóm tắt mặc định do backend tự dựng | F6: Tắt
A7: Chuyển giọng nói | B7: Chuyển file ghi âm thành văn bản | C7: File ghi âm khi người dùng bấm ghi âm và dừng. | D7: — | E7: Cần khóa Groq; người dùng tự bấm ghi âm | F7: Chưa bật (không có khóa Groq trên Vercel)
A9: Nhà cung cấp AI đang dùng: Gemini và LiteRouter (bản demo), Groq tùy chọn, Ollama chạy trên máy nội bộ (không ra ngoài).
A12: Chưa có: rà soát điều khoản lưu giữ và huấn luyện dữ liệu của từng nhà cung cấp, đặc biệt gói miễn phí; bảng phân loại dữ liệu theo mức nhạy cảm; che (mask) thêm các trường nhạy cảm nếu dùng dữ liệu thật. Đây là điều kiện trước khi thí điểm với dữ liệu thật.
A16: Kho dữ liệu: backend truy cập bằng tài khoản chỉ đọc, AI không có đường nào tới kho dữ liệu.
A19: Cách đọc các cột
A20: Lời gọi AI | B20: Một loại yêu cầu mà backend gửi cho dịch vụ AI bên ngoài.
A21: Nội dung được gửi / Không gửi | B21: Dữ liệu rời khỏi hệ thống trong lời gọi đó, và dữ liệu không bao giờ gửi (ví dụ dòng kết quả, mật khẩu, khóa).
A22: Công tắc điều khiển | B22: Biến cấu hình bật hoặc tắt việc gửi; mặc định thường là tắt.
A23: Trạng thái trên bản demo | B23: Lời gọi này đang dùng hay không trên bản demo hiện tại.

Sheet Chi phí
A1: Ước tính chi phí chạy AI: API Claude hoặc máy chủ GPU chạy mô hình offline
A2: Ô chữ xanh là giả định hoặc giá nhập tay, đổi được; các ô còn lại là công thức. Giá có thể đổi, cần xác nhận lại trước khi quyết định.
A4: A. Giả định chung | B4: Giá trị | C4: Ghi chú
A5: Tỷ giá VND mỗi USD | B5: 26000 | C5: Giả định, cập nhật khi báo cáo
A6: Tỷ giá USD mỗi EUR | B6: 1.1 | C6: Giả định cho giá Hetzner tính bằng euro
A7: Hệ số token Claude so với đo bằng Qwen | B7: 1.3 | C7: Giả định: tokenizer tiếng Việt của Claude có thể nhiều hơn; cần đo bằng count_tokens khi có khóa
A8: Hệ số token suy nghĩ cộng vào đầu ra | B8: 2 | C8: Giả định: Haiku 5.5 mặc định suy nghĩ, đặt effort thấp để giảm; đầu ra nhân hệ số này
A9: Tỷ lệ phần đầu vào đọc từ bộ nhớ đệm (prompt cache) | B9: 0 | C9: Mặc định 0 (không tính giảm). Bảng D tính thêm trường hợp có cache
A10: Giá đọc cache so với giá đầu vào thường | B10: 0.1 | C10: Theo tài liệu Anthropic: đọc cache bằng 0,1 lần giá đầu vào
A11: Giờ trong một tháng | B11: 730 | C11: 24 giờ x 365 / 12
A13: B. Giá API Claude (USD mỗi 1 triệu token) | B13: Đầu vào | C13: Đầu ra | D13: Nguồn / ghi chú
A14: Claude Haiku 5.5 (claude-haiku-5-5) | B14: 0.1 | C14: 0.5 | D14: Cho lời nhắc ≤100K token; rẻ nhất, mô hình Haiku hiện tại. Nguồn: bảng giá Anthropic trong tài liệu API (cập nhật 06/10/2026), https://platform.claude.com/docs/en/about-claude/pricing
A15: Claude Haiku 4.5 (claude-haiku-4-5) | B15: 1 | C15: 5 | D15: Thế hệ trước. Nguồn: bảng giá Anthropic trong tài liệu API (cập nhật 06/10/2026), https://platform.claude.com/docs/en/about-claude/pricing
A16: Claude Sonnet 5.5 (claude-sonnet-5-5) | B16: 2 | C16: 10 | D16: Cân bằng chất lượng và giá. Nguồn: bảng giá Anthropic trong tài liệu API (cập nhật 06/10/2026), https://platform.claude.com/docs/en/about-claude/pricing
A17: Claude Opus 5.5 (claude-opus-5-5) | B17: 4 | C17: 20 | D17: Mạnh nhất trong nhóm này; vượt nhu cầu của dự án. Nguồn: bảng giá Anthropic trong tài liệu API (cập nhật 06/10/2026), https://platform.claude.com/docs/en/about-claude/pricing
A19: C. Token mỗi lời gọi AI (đo thực tế bằng mô hình Qwen, trước hệ số) | B19: Đầu vào | C19: Đầu ra | D19: Số lời gọi mỗi câu: đo trên bộ test | E19: Số lời gọi mỗi câu: kịch bản xấu
A20: Hiểu câu hỏi | B20: 2534 | C20: 132 | D20: 0.35 | E20: 1
A21: Đề xuất SQL (RAG) | B21: 1295 | C21: 78 | D21: 0.1 | E21: 1
A22: Chọn biểu đồ | B22: 366 | C22: 25 | D22: 0.02 | E22: 0.3
A23: Tổng lời gọi mỗi câu | D23: =SUM(D20:D22) | E23: =SUM(E20:E22)
A24: Ghi chú: token đo bằng Ollama (qwen2.5:7b) trên đúng lời nhắc của hệ thống. Cột D lấy từ bộ 161 ca kiểm thử: trung bình 0,47 lời gọi mỗi câu, 67% câu không cần AI vì bản demo bật LOCAL_INTENT_ENABLED (đọc câu rõ ràng bằng quy tắc); tùy chọn này mặc định tắt, khi tắt mọi câu dữ liệu cần AI hiểu nên chi phí gần cột E; phân bổ giữa 3 loại lời gọi là ước lượng. Cột E: mọi câu cần AI hiểu và AI viết SQL. Chưa tính lần sửa SQL, tóm tắt và trả lời về dữ liệu.
A26: D. Chi phí API mỗi 1.000 câu hỏi (USD) | B26: Kịch bản đo, không cache | C26: Kịch bản đo, có cache | D26: Kịch bản xấu, không cache | E26: Kịch bản xấu, có cache
A27: =A14 | B27: =1000*($D$20*($B$20*$B$7*$B14*(1-0*(1-$B$10))+$C$20*$B$7*$B$8*$C14)+$D$21*($B$21*$B$7*$B14*(1-0*(1-$B$10))+$C$21*$B$7*$B$8*$C14)+$D$22*($B$22*$B$7*$B14*(1-0*(1-$B$10))+$C$22*$B$7*$B$8*$C14))/1000000 | C27: =1000*($D$20*($B$20*$B$7*$B14*(1-$B$9*(1-$B$10))+$C$20*$B$7*$B$8*$C14)+$D$21*($B$21*$B$7*$B14*(1-$B$9*(1-$B$10))+$C$21*$B$7*$B$8*$C14)+$D$22*($B$22*$B$7*$B14*(1-$B$9*(1-$B$10))+$C$22*$B$7*$B$8*$C14))/1000000 | D27: =1000*($E$20*($B$20*$B$7*$B14*(1-0*(1-$B$10))+$C$20*$B$7*$B$8*$C14)+$E$21*($B$21*$B$7*$B14*(1-0*(1-$B$10))+$C$21*$B$7*$B$8*$C14)+$E$22*($B$22*$B$7*$B14*(1-0*(1-$B$10))+$C$22*$B$7*$B$8*$C14))/1000000 | E27: =1000*($E$20*($B$20*$B$7*$B14*(1-$B$9*(1-$B$10))+$C$20*$B$7*$B$8*$C14)+$E$21*($B$21*$B$7*$B14*(1-$B$9*(1-$B$10))+$C$21*$B$7*$B$8*$C14)+$E$22*($B$22*$B$7*$B14*(1-$B$9*(1-$B$10))+$C$22*$B$7*$B$8*$C14))/1000000
A28: =A15 | B28: =1000*($D$20*($B$20*$B$7*$B15*(1-0*(1-$B$10))+$C$20*$B$7*$B$8*$C15)+$D$21*($B$21*$B$7*$B15*(1-0*(1-$B$10))+$C$21*$B$7*$B$8*$C15)+$D$22*($B$22*$B$7*$B15*(1-0*(1-$B$10))+$C$22*$B$7*$B$8*$C15))/1000000 | C28: =1000*($D$20*($B$20*$B$7*$B15*(1-$B$9*(1-$B$10))+$C$20*$B$7*$B$8*$C15)+$D$21*($B$21*$B$7*$B15*(1-$B$9*(1-$B$10))+$C$21*$B$7*$B$8*$C15)+$D$22*($B$22*$B$7*$B15*(1-$B$9*(1-$B$10))+$C$22*$B$7*$B$8*$C15))/1000000 | D28: =1000*($E$20*($B$20*$B$7*$B15*(1-0*(1-$B$10))+$C$20*$B$7*$B$8*$C15)+$E$21*($B$21*$B$7*$B15*(1-0*(1-$B$10))+$C$21*$B$7*$B$8*$C15)+$E$22*($B$22*$B$7*$B15*(1-0*(1-$B$10))+$C$22*$B$7*$B$8*$C15))/1000000 | E28: =1000*($E$20*($B$20*$B$7*$B15*(1-$B$9*(1-$B$10))+$C$20*$B$7*$B$8*$C15)+$E$21*($B$21*$B$7*$B15*(1-$B$9*(1-$B$10))+$C$21*$B$7*$B$8*$C15)+$E$22*($B$22*$B$7*$B15*(1-$B$9*(1-$B$10))+$C$22*$B$7*$B$8*$C15))/1000000
A29: =A16 | B29: =1000*($D$20*($B$20*$B$7*$B16*(1-0*(1-$B$10))+$C$20*$B$7*$B$8*$C16)+$D$21*($B$21*$B$7*$B16*(1-0*(1-$B$10))+$C$21*$B$7*$B$8*$C16)+$D$22*($B$22*$B$7*$B16*(1-0*(1-$B$10))+$C$22*$B$7*$B$8*$C16))/1000000 | C29: =1000*($D$20*($B$20*$B$7*$B16*(1-$B$9*(1-$B$10))+$C$20*$B$7*$B$8*$C16)+$D$21*($B$21*$B$7*$B16*(1-$B$9*(1-$B$10))+$C$21*$B$7*$B$8*$C16)+$D$22*($B$22*$B$7*$B16*(1-$B$9*(1-$B$10))+$C$22*$B$7*$B$8*$C16))/1000000 | D29: =1000*($E$20*($B$20*$B$7*$B16*(1-0*(1-$B$10))+$C$20*$B$7*$B$8*$C16)+$E$21*($B$21*$B$7*$B16*(1-0*(1-$B$10))+$C$21*$B$7*$B$8*$C16)+$E$22*($B$22*$B$7*$B16*(1-0*(1-$B$10))+$C$22*$B$7*$B$8*$C16))/1000000 | E29: =1000*($E$20*($B$20*$B$7*$B16*(1-$B$9*(1-$B$10))+$C$20*$B$7*$B$8*$C16)+$E$21*($B$21*$B$7*$B16*(1-$B$9*(1-$B$10))+$C$21*$B$7*$B$8*$C16)+$E$22*($B$22*$B$7*$B16*(1-$B$9*(1-$B$10))+$C$22*$B$7*$B$8*$C16))/1000000
A30: =A17 | B30: =1000*($D$20*($B$20*$B$7*$B17*(1-0*(1-$B$10))+$C$20*$B$7*$B$8*$C17)+$D$21*($B$21*$B$7*$B17*(1-0*(1-$B$10))+$C$21*$B$7*$B$8*$C17)+$D$22*($B$22*$B$7*$B17*(1-0*(1-$B$10))+$C$22*$B$7*$B$8*$C17))/1000000 | C30: =1000*($D$20*($B$20*$B$7*$B17*(1-$B$9*(1-$B$10))+$C$20*$B$7*$B$8*$C17)+$D$21*($B$21*$B$7*$B17*(1-$B$9*(1-$B$10))+$C$21*$B$7*$B$8*$C17)+$D$22*($B$22*$B$7*$B17*(1-$B$9*(1-$B$10))+$C$22*$B$7*$B$8*$C17))/1000000 | D30: =1000*($E$20*($B$20*$B$7*$B17*(1-0*(1-$B$10))+$C$20*$B$7*$B$8*$C17)+$E$21*($B$21*$B$7*$B17*(1-0*(1-$B$10))+$C$21*$B$7*$B$8*$C17)+$E$22*($B$22*$B$7*$B17*(1-0*(1-$B$10))+$C$22*$B$7*$B$8*$C17))/1000000 | E30: =1000*($E$20*($B$20*$B$7*$B17*(1-$B$9*(1-$B$10))+$C$20*$B$7*$B$8*$C17)+$E$21*($B$21*$B$7*$B17*(1-$B$9*(1-$B$10))+$C$21*$B$7*$B$8*$C17)+$E$22*($B$22*$B$7*$B17*(1-$B$9*(1-$B$10))+$C$22*$B$7*$B$8*$C17))/1000000
A32: Giả định cho cột 'có cache': dùng giá trị ở ô B9 (nhập tay, ví dụ 0,7 nếu 70% đầu vào là phần lời nhắc cố định). Phần cache có thể không kích hoạt nếu lời nhắc ngắn hơn ngưỡng tối thiểu của mô hình; chưa kiểm chứng.
A34: E. Chi phí API mỗi tháng (USD), kịch bản xấu, không cache | B34: 5.000 câu | C34: 20.000 câu | D34: 100.000 câu
A35: Số câu hỏi mỗi tháng (nhập) | B35: 5000 | C35: 20000 | D35: 100000
A36: =A27 | B36: =$D27*B$35/1000 | C36: =$D27*C$35/1000 | D36: =$D27*D$35/1000
A37: =A28 | B37: =$D28*B$35/1000 | C37: =$D28*C$35/1000 | D37: =$D28*D$35/1000
A38: =A29 | B38: =$D29*B$35/1000 | C38: =$D29*C$35/1000 | D38: =$D29*D$35/1000
A39: =A30 | B39: =$D30*B$35/1000 | C39: =$D30*C$35/1000 | D39: =$D30*D$35/1000
A40: Cùng kịch bản đo (trung bình 0,47 lời gọi), không cache
A41: =A27 | B41: =$B27*B$35/1000 | C41: =$B27*C$35/1000 | D41: =$B27*D$35/1000
A42: =A28 | B42: =$B28*B$35/1000 | C42: =$B28*C$35/1000 | D42: =$B28*D$35/1000
A43: =A29 | B43: =$B29*B$35/1000 | C43: =$B29*C$35/1000 | D43: =$B29*D$35/1000
A44: =A30 | B44: =$B30*B$35/1000 | C44: =$B30*C$35/1000 | D44: =$B30*D$35/1000
A46: F. Máy chủ GPU chạy mô hình offline | B46: Giá | C46: Đơn vị | D46: Chi phí mỗi tháng (USD) | E46: Chi phí cài đặt một lần (USD) | F46: Ghi chú
A47: Hetzner GEX44 (RTX 4000 SFF Ada, 20GB) | B47: 184 | C47: EUR/tháng | D47: =B47*$B$6 | E47: =79*$B$6 | F47: Dedicated; phí cài đặt 79 EUR. Nguồn: lowendbox.com, effloow.com (06/2026); cần xác nhận trên trang Hetzner
A48: Hetzner GEX45 (RTX PRO 4000 Blackwell, 24GB) | B48: 249 | C48: USD/tháng | D48: =B48 | E48: 249 | F48: Ra mắt 03/09/2026; 214 EUR hoặc 249 USD mỗi tháng, cài đặt 249 USD. Nguồn: itbrief.co.uk
A49: RunPod RTX 4090 24GB, Secure Cloud | B49: 0.69 | C49: USD/giờ | D49: =B49*$B$11 | E49: 0 | F49: Chạy 24/24. Nguồn: hackceleration.com (cập nhật 08/2026); nguồn khác ghi 0,74
A50: RunPod RTX 4090 24GB, Community Cloud | B50: 0.34 | C50: USD/giờ | D50: =B50*$B$11 | E50: 0 | F50: Phần cứng dùng chung, rẻ hơn, kém đảm bảo
A51: RunPod L4 24GB | B51: 0.39 | C51: USD/giờ | D51: =B51*$B$11 | E51: 0 | F51: Nguồn: computeprices.com (cập nhật 08/2026)
A52: Chi phí nhân sự vận hành (cài đặt, cập nhật, giám sát, sự cố) | D52: [điền] | F52: Chưa ước tính. Đây là khoản lớn thường bị bỏ sót khi tự vận hành mô hình.
A54: G. So sánh và điểm hòa vốn | B54: Giá trị | C54: Ghi chú
A55: Chi phí cố định tháng của GPU rẻ nhất tin cậy (Hetzner GEX44), USD | B55: =D47
A56: Số câu mỗi tháng để API Haiku 5.5 (kịch bản xấu) bằng GPU này | B56: =B55/(D27/1000) | C56: Dưới mức này, dùng API rẻ hơn; trên mức này, GPU rẻ hơn về tiền (chưa tính nhân sự và chất lượng)
A57: Số câu mỗi tháng để API Sonnet 5.5 (kịch bản xấu) bằng GPU này | B57: =B55/(D29/1000)
A58: Chi phí tháng VND: Haiku 5.5, 20.000 câu, kịch bản xấu | B58: =C36*$B$5
A59: Chi phí tháng VND: GPU Hetzner GEX44 | B59: =D47*$B$5
A60: Số câu mỗi tháng để API Haiku 5.5 (kịch bản xấu) bằng GPU 500 USD/tháng (cận trên) | B60: =500/(D27/1000) | C60: Khoảng hòa vốn là từ B56 (GPU rẻ nhất) đến B60 (GPU 500 USD).
A61: H. So sánh định tính | B61: API Claude | C61: VPS chạy mô hình offline
A62: Chất lượng hiểu tiếng Việt và sinh SQL | B62: Chưa đo trên bộ 161 ca (cần khóa API và thêm nhà cung cấp Claude vào hệ thống). Mô hình Claude mạnh hơn nhiều so với mô hình nhỏ. | C62: Đo thật trên Qwen2.5 7B: 88/90 câu khó và 43/47 câu so sánh, kém Gemini (90/90, 47/47); lỗi ở tin nhắn nhiều yêu cầu. Mô hình lớn hơn (14B đến 32B) trên GPU 20 đến 24GB cần đo lại.
A63: Độ trễ | B63: Khoảng 3 đến 6 giây mỗi câu cần AI (Gemini đo được 3 đến 6 giây trên web). | C63: Đo thật trên GPU 4GB cá nhân: 17 đến 35 giây mỗi lời gọi. GPU 20 đến 24GB nhanh hơn nhưng chưa đo.
A64: Nhiều người cùng lúc | B64: Mở rộng theo hạn mức tài khoản; trả theo token. | C64: Một GPU phục vụ ít yêu cầu song song; thêm người dùng cần thêm GPU.
A65: Quyền riêng tư | B65: Dữ liệu gửi đi gồm câu hỏi và mô tả chỉ số (xem sheet 'Dữ liệu gửi cho AI'); cần xác nhận điều khoản, lưu giữ và tùy chọn không lưu dữ liệu. | C65: Không có dữ liệu ra ngoài công ty.
A66: Vận hành | B66: Không phải quản lý máy chủ; phụ thuộc dịch vụ bên ngoài và hạn mức. | C66: Tự cài đặt, cập nhật mô hình, giám sát, sao lưu; cần người phụ trách.
A67: Công việc thêm vào dự án | B67: Thêm nhà cung cấp Claude vào backend (Messages API, kết quả JSON theo lược đồ) và chạy lại bộ kiểm thử: ước tính 1 đến 2 ngày. | C67: Đã có nhà cung cấp Ollama; cần máy chủ, mô hình lớn hơn và đo lại bộ kiểm thử.
A69: Khuyến nghị tạm thời
A70: Dùng API Claude Haiku 5.5 cho lời gọi hiểu câu hỏi và chọn biểu đồ; cân nhắc Sonnet 5.5 cho lời gọi đề xuất SQL nếu đo thấy Haiku chưa đủ. Opus 5.5 vượt nhu cầu. Đây là khuyến nghị theo giá và loại tác vụ, chưa được kiểm chứng bằng bộ 161 ca.
A71: Với quy mô thí điểm (vài nghìn câu mỗi tháng), chi phí API ở mức vài USD đến vài chục USD mỗi tháng (xem bảng E), thấp hơn nhiều so với một GPU chuyên dụng chạy cả tháng. VPS offline chỉ hợp lý khi bắt buộc không để dữ liệu ra ngoài, và cần đo lại chất lượng với mô hình lớn hơn.
A72: Việc cần làm trước khi chốt: (1) thêm nhà cung cấp Claude và chạy bộ 161 ca; (2) đo token bằng count_tokens; (3) xác nhận điều khoản dữ liệu của nhà cung cấp; (4) điền chi phí nhân sự.
A75: Cách đọc các khối chi phí
A76: A. Giả định chung | B76: Các hệ số tự đặt (ô chữ xanh): tỷ giá, hệ số token, hệ số suy nghĩ, tỷ lệ cache. Đổi ô thì cả bảng tự tính lại.
A77: B. Giá API | B77: Giá mỗi một triệu token (đơn vị tính tiền của dịch vụ AI) cho phần đọc vào (đầu vào) và phần AI viết ra (đầu ra).
A78: C. Token mỗi lời gọi | B78: Số token đo trên lời nhắc thật của hệ thống. Số lời gọi mỗi câu là mỗi câu hỏi trung bình gọi AI bao nhiêu lần: cột đo trên bộ test (0,47 lần vì nhiều câu không cần AI) và cột kịch bản xấu (mọi câu đều gọi AI).
A79: D. Chi phí mỗi 1.000 câu | B79: Tiền phải trả cho 1.000 câu hỏi theo từng mô hình. Có cache là khi phần lời nhắc lặp lại được tính giá rẻ hơn.
A80: E. Chi phí mỗi tháng | B80: Chi phí D nhân với số câu hỏi mỗi tháng (ô số câu nhập tay được).
A81: F. Máy chủ GPU | B81: Giá thuê máy chủ có card đồ họa để chạy mô hình offline; cố định theo tháng, không phụ thuộc số câu hỏi. Chưa gồm nhân sự.
A82: G. Điểm hòa vốn | B82: Số câu hỏi mỗi tháng mà tại đó dùng API và thuê máy chủ tốn như nhau. Ít hơn mức này thì API rẻ hơn.
A83: H. So sánh định tính | B83: Những điều tiền không nói hết: chất lượng, độ trễ, riêng tư, vận hành.
